Workbook
Name curr: [2]Lists!$B$7:$B$32
Name curr: [2]Lists!$B$7:$B$32
Name curr: [2]Lists!$B$7:$B$32
Name curr: [1]Lists!$B$7:$B$32
Name curr_table: [2]Lists!$B$7:$F$32
Name curr_table: [2]Lists!$B$7:$F$32
Name curr_table: [2]Lists!$B$7:$F$32
Name curr_table: [1]Lists!$B$7:$F$32
Name status: [2]Lists!$H$7:$H$9
Name status: [2]Lists!$H$7:$H$9
Name status: [2]Lists!$H$7:$H$9
Name status: [1]Lists!$H$7:$H$9
Name TV_growth: '[1]A. Cover'!$D$13
Name TV_growth: '[2]A. Cover'!$D$13
Name TV_growth: '[2]A. Cover'!$D$13
Name TV_growth: '[2]A. Cover'!$D$13
Name tv_growth: Inputs!$C$19
Name wacc: '[1]A. Cover'!$D$12
Name wacc: '[2]A. Cover'!$D$12
Name wacc: '[2]A. Cover'!$D$12
Name wacc: '[2]A. Cover'!$D$12
Name wacc: Inputs!$C$18
Name years: [2]Lists!$J$7:$J$12
Name years: [2]Lists!$J$7:$J$12
Name years: [2]Lists!$J$7:$J$12
Name years: [1]Lists!$J$7:$J$12
Name Yr0: '[2]A. Cover'!$D$9
Name Yr0: '[2]A. Cover'!$D$9
Name Yr0: '[2]A. Cover'!$D$9
Name Yr0: '[1]A. Cover'!$D$9

Sheet Overview
B2: Welcome to the Project Financial Model
B4: Overall Purpose
B5: This model is designed to be used to help financially evaluate a range of programs and projects. Specifically it should help to;
B6: R | C6: Identify the wide range of variables that should be considered when evaluating a project
B7: R | C7: Help identify possible costs and savings that may otherwise be missed
B8: R | C8: Provide guidance on how those costs and savings should be identified and measured
B9: R | C9: Be a simple spreadsheet to calculate the savings and the financial metrics
B10: R | C10: Provide a consistent Mgt summary with the key financial data so that go/no-go decisions can be made quickly
B11: R | C11: Help evaluate & compare projects in a similar manner such that capital allocation priority callscan be made
B13: Methodology
B14: This model provides an incremental assessment on the impact of a course of action. It requires the user to understand all applicable scenarios how they impact following the changing of the variables. The model can then assess the financial impact of the project, and describe that in the following ways;
B15:  | C15: Cash Flow
B16:  | C16: Net Present Value (NPV)
B17:  | C17: Sales (growth)
B18:  | C18: Costs (investments, cost saves, expenses, capital expense)
B19:  | C19: Profit
B20:  | C20: Payback (time)
B21:  | C21: Return on Capital Invested (ROIC)
B22: Of these the primary method for evalution is Cash Flow and NPV.
B24: How To Use the model
B25: Try to to complete the moedl in the following order;
C26: 1. Inputs Tab | D26: Project Information and descriptions. Take your time here as the inputs feed the modeling sheets.
C27: 2. Checklist | D27: Use the Checklist to help identify all the variables that might be impacted by your project and begin to pull together the details to complete the workbook. Use the filter on left hand side to selct the type of porject you are evaluating, and this will list the variables most likely to be impacted. Use the Glossary to help undestand how to measure your varaibles.
C28: 3. Model (1-7): Current State | D28: Establish your Scenarios, and complete in each tab of the model. You only need to focus on the subset of varibales that are relevant to the project.
C29: 4. Model (1-7): Future State | D29: Establish your Scenarios, and complete in each tab of the model. You only need to focus on the subset of varibales that are relevant to the project, and thereby ensure that the comparison to the Current State is a fair one.
C30: 5. Scenarios | D30: Summary of all scenarios
C31: 6. Compare | D31: Select which scenarios you want to compare and asses the variance, NPV, payback period, etc.
B33: The Model
B34: Please ensure you are using the latest veriosn of the model & reach out to the owner of the model of any questions, suggested modifications, found errors etc.
B36: The current owner of this model is:
B39: Current Version of the model is:
C40: v1.4

Sheet FAQs
E2: FAQ
E5: Why do we focus on cash generation to evaluate a project and not just profit?
B6: =IFERROR(RANK($C6,$C$6:$C$408,1),"") -> 1 | C6: =IFERROR(SEARCH([2]FAQ!$D$4,$E6)+ROW()/1000,"") -> 1.006 | E6: Cash generation is often considered the best measure for evaluating a business project because it directly reflects the amount of cash a project generates over a specific period. This is important because cash is what ultimately funds a business's operations and investments, and it's also what allows a company to pay off its debts, distribute dividends to shareholders, and reinvest in the business. In contrast, other financial measures like profits or revenues can be manipulated by accounting practices or timing differences, and may not accurately reflect the actual cash flow of a business. For example, a company may report high profits but still have trouble paying its bills if those profits are tied up in inventory.
E7: What is NPV and why do we use that?
B8: =IFERROR(RANK($C8,$C$6:$C$408,1),"") -> 2 | C8: =IFERROR(SEARCH([2]FAQ!$D$4,$E8)+ROW()/1000,"") -> 1.008 | E8: Net Present Value (NPV) is one of the most widely used measures for evaluating whether to proceed with a project or not. NPV is calculated by subtracting the present value of a project's cash outflows from the present value of its cash inflows. If the resulting NPV is positive, the project is expected to generate a return greater than the cost of capital, and therefore may be worth pursuing. The advantages of using NPV as a measure for project evaluation are: - It accounts for the time value of money: NPV adjusts future cash flows to their present values, taking into consideration the opportunity cost of investing money today versus in the future. - It considers all cash flows: NPV includes both the initial investment and all future cash flows associated with the project, providing a more comprehensive view of the project's profitability. - It provides a clear measure of profitability: NPV is expressed in monetary terms, making it easy to compare different projects and determine which one generates the highest return. However, there are also some limitations to using NPV as the sole measure for project evaluation. For example, it assumes that cash flows are known with certainty, which may not always be the case. NPV also doesn't consider non-financial factors such as environmental or social impacts, which may be important for some projects. Therefore, while NPV is a useful tool for evaluating projects, it should be used in conjunction with other measures and with consideration of other important factors to make informed decisions.
B9: =IFERROR(RANK($C9,$C$6:$C$408,1),"") -> 3 | C9: =IFERROR(SEARCH([2]FAQ!$D$4,$E9)+ROW()/1000,"") -> 1.009 | E9: How do I evaluate the cost save of reducing sidetracks?
E10: Eliminating sidetracks primarily enables increased productivity (less waiting) and also lower inventory (increases cashflow) and is definitely worth measuring within the project! In order to financially measure the increased productivity you should try and estimate the number of hours that are saved by eliminating the sidetracks. Measure the cycle time at current state, and then compare to the cycle time with the sidetracks (or other productivity impacts) eliminated --> the difference should be measured as a unit of time. Next step would be to then turn the saved time into a financial metric (usually done by using the average labour cost expressed per day/hour). And don't forget to include the Inventory reductions included in the model -- these are valuable since they mean we have less cash tied up in inventory.
B11: =IFERROR(RANK($C11,$C$6:$C$408,1),"") -> 4 | C11: =IFERROR(SEARCH([2]FAQ!$D$4,$E11)+ROW()/1000,"") -> 1.011 | E11: Should I count to cost of changing production schedules?
E12: Any change to product schedules, or cycles times, should be included if it has an impact on production efficiency. Try to assess the impact (positive or negative) in terms of labour hours, and then this can be translated into a financial metric in terms of cost. Speak to your finance business parnter to agree the right cost metric to use.
B13: =IFERROR(RANK($C13,$C$6:$C$408,1),"") -> 5 | C13: =IFERROR(SEARCH([2]FAQ!$D$4,$E13)+ROW()/1000,"") -> 1.013 | E13: How should I evaluate tax?
E14: Tax is something that impacts cashflow and should be included therefore in any NPV and ROIC calculations. Tax is usually applied to any incremental profits made in a project, using the country's local Corp tax rate which can be found out by asking the Corp Tax team. If the project involves moving profits from one country to another then there may be a difference in Corp tax rates in those countries and the difference should be counted in the project using the tax worksheet. If moving country profits you should also ask the tax team to identify if there are any unused tax credits that can be utilised and these should be dedcuted from the taxable gain. If in doubt ask your finance partner.
B15: =IFERROR(RANK($C15,$C$6:$C$408,1),"") -> 6 | C15: =IFERROR(SEARCH([2]FAQ!$D$4,$E15)+ROW()/1000,"") -> 1.015 | E15: Should the current state equal the latest financial forecast?
E16: The current state should be the "do nothing" scenario and ideally that would equal the latest financial forecast. If not then talk to your local finance rep to find out why not and if the financial foreacst should be updated. Nevertheless when assessing current adn future states you only need to appraise the elements of the financials that are relvant to the project you are appraising. For example, if you are looking at a project related to Encore Pumper volumes, then you should only include the volumes associated to Encore Pumpers in the before and after states, and not all Encore units.
B17: =IFERROR(RANK($C17,$C$6:$C$408,1),"") -> 7 | C17: =IFERROR(SEARCH([2]FAQ!$D$4,$E17)+ROW()/1000,"") -> 1.017 | E17: Do I need a financial analyst to help fill this in?
E18: No - this model can be used by any project team member. However it is quite comprehensive and so feel free to reach out to your finance business partner for support and guidance. For all large projects, dedicated finance support should be identified and made available in order to help assess the inputs and manage the financial impacts.
B19: =IFERROR(RANK($C19,$C$6:$C$408,1),"") -> 8 | C19: =IFERROR(SEARCH([2]FAQ!$D$4,$E19)+ROW()/1000,"") -> 1.019 | E19: How should I calculate the average COGS?
E20: By speaking to operations or your finance business partner you should isolate the total COGS associated with the product or part that you are assessing, and simply divide by the total number of units. It is usually helpful to think of averages instead of working our every permitation, but be careful to assess like for like. If in doubt then work with your finance business poartner.
B21: =IFERROR(RANK($C21,$C$6:$C$408,1),"") -> 9 | C21: =IFERROR(SEARCH([2]FAQ!$D$4,$E21)+ROW()/1000,"") -> 1.021 | E21: How should I calculate potential future PPV savings?
B22: =IFERROR(RANK($C22,$C$6:$C$408,1),"") -> 10 | C22: =IFERROR(SEARCH([2]FAQ!$D$4,$E22)+ROW()/1000,"") -> 1.022 | E22: First you should brainstorm all the ways that the project might change the supply chain. The main areas where PPV might be able to be achieved is if you are increasing volumes to a particular supplier, either through part consolidation, or increased throughput or other means. You should then work with the supply chain team to identify a tarageted price reduction based on those chnages that we thinkwe can ask the supplier for.
B23: =IFERROR(RANK($C23,$C$6:$C$408,1),"") | C23: =IFERROR(SEARCH([2]FAQ!$D$4,$E23)+ROW()/1000,"")
B24: =IFERROR(RANK($C24,$C$6:$C$408,1),"") | C24: =IFERROR(SEARCH([2]FAQ!$D$4,$E24)+ROW()/1000,"")
B25: =IFERROR(RANK($C25,$C$6:$C$408,1),"") | C25: =IFERROR(SEARCH([2]FAQ!$D$4,$E25)+ROW()/1000,"")
B26: =IFERROR(RANK($C26,$C$6:$C$408,1),"") | C26: =IFERROR(SEARCH([2]FAQ!$D$4,$E26)+ROW()/1000,"")
B27: =IFERROR(RANK($C27,$C$6:$C$408,1),"") | C27: =IFERROR(SEARCH([2]FAQ!$D$4,$E27)+ROW()/1000,"")
B28: =IFERROR(RANK($C28,$C$6:$C$408,1),"") | C28: =IFERROR(SEARCH([2]FAQ!$D$4,$E28)+ROW()/1000,"")
B29: =IFERROR(RANK($C29,$C$6:$C$408,1),"") | C29: =IFERROR(SEARCH([2]FAQ!$D$4,$E29)+ROW()/1000,"")
B30: =IFERROR(RANK($C30,$C$6:$C$408,1),"") | C30: =IFERROR(SEARCH([2]FAQ!$D$4,$E30)+ROW()/1000,"")
B31: =IFERROR(RANK($C31,$C$6:$C$408,1),"") | C31: =IFERROR(SEARCH([2]FAQ!$D$4,$E31)+ROW()/1000,"")
C32: =IFERROR(SEARCH([2]FAQ!$D$4,$E32)+ROW()/1000,"")
C33: =IFERROR(SEARCH([2]FAQ!$D$4,$E33)+ROW()/1000,"")
C34: =IFERROR(SEARCH([2]FAQ!$D$4,$E34)+ROW()/1000,"")
C35: =IFERROR(SEARCH([2]FAQ!$D$4,$E35)+ROW()/1000,"")
C36: =IFERROR(SEARCH([2]FAQ!$D$4,$E36)+ROW()/1000,"")
C37: =IFERROR(SEARCH([2]FAQ!$D$4,$E37)+ROW()/1000,"")
C38: =IFERROR(SEARCH([2]FAQ!$D$4,$E38)+ROW()/1000,"")
C39: =IFERROR(SEARCH([2]FAQ!$D$4,$E39)+ROW()/1000,"")
C40: =IFERROR(SEARCH([2]FAQ!$D$4,$E40)+ROW()/1000,"")
C41: =IFERROR(SEARCH([2]FAQ!$D$4,$E41)+ROW()/1000,"")
C42: =IFERROR(SEARCH([2]FAQ!$D$4,$E42)+ROW()/1000,"")
C43: =IFERROR(SEARCH([2]FAQ!$D$4,$E43)+ROW()/1000,"")
... C132: =IFERROR(SEARCH([2]FAQ!$D$4,$E132)+ROW()/1000,"")

Sheet Inputs
B2: Inputs
B4: Project Name:
B5: Project Description:
B7: PY-2 | C7: =IF(C8="","",C8-1) -> 2023
B8: PY-1 | C8: =IF(C9="","",C9-1) -> 2024
B9: Prior Year (PY): | C9: =IF(C10="","",C10-1) -> 2025
B10: Current Year (CY): | C10: 2026
B11: CY+1: | C11: =IF(C10="","",C10+1) -> 2027
B12: CY+2: | C12: =IF(C11="","",C11+1) -> 2028
B13: CY+3: | C13: =IF(C12="","",C12+1) -> 2029
B14: CY+4: | C14: =IF(C13="","",C13+1) -> 2030
B16: Model Currency: | C16: USD
B18: Weighted Avg Cost of Capital (WACC): | C18: 0.1
B19: Terminal Value (TV) Growth Rate: | C19: 0.03
B21: Scenario Name | C21: Scenario Description
B22: Scenario 1 | C22: =B22&" Description" -> Scenario 1 Description
B23: Scenario 2 | C23: =B23&" Description" -> Scenario 2 Description
B24: Scenario 3 | C24: =B24&" Description" -> Scenario 3 Description
B25: Scenario 4 | C25: =B25&" Description" -> Scenario 4 Description
B26: Scenario 5 | C26: =B26&" Description" -> Scenario 5 Description

Sheet Checklist
J2: Glossary of Items: Simplification Projects
B8: 1 | C8: 2 | D8: 3 | E8: 4 | F8: 5 | G8: 6 | H8: 7 | L8: Item | M8: Status | N8: Assumptions | O8: Page
L9: Name of the variable that is changing | N9: Comments and notes -- further detail should be added on individual worksheets | O9: find back up
B11: l | D11: l | F11: l | G11: l | H11: l | J11: VARIABLE | K11: 1 | L11: Revenue | M11: Need
B12: l | D12: l | F12: l | G12: l | H12: l | K12: 2 | L12: Price | M12: Need
B13: l | C13: l | D13: l | E13: l | F13: l | G13: l | H13: l | J13: Directly attributable cost associated with the product itself Vaiances to standard cost driven by productivity | K13: 3 | L13: Material cost of part | M13: Need
B14: l | C14: l | D14: l | E14: l | F14: l | G14: l | H14: l | K14: 4 | L14: Direct Labour | M14: Need
B15: l | C15: l | D15: l | E15: l | F15: l | G15: l | H15: l | K15: 5 | L15: Inbound Freight | M15: Need
B16: l | C16: l | D16: l | E16: l | F16: l | G16: l | H16: l | K16: 6 | L16: Outbound Freight | M16: Need
B17: l | C17: l | D17: l | E17: l | F17: l | G17: l | H17: l | K17: 7 | L17: Duties and Import taxes | M17: Need
B18: l | C18: l | D18: l | E18: l | F18: l | G18: l | H18: l | K18: 8 | L18: Overtime / Labour Variance | M18: Need
B19: l | C19: l | D19: l | E19: l | F19: l | G19: l | H19: l | K19: 9 | L19: PPV | M19: Need
B20: l | C20: l | D20: l | E20: l | F20: l | G20: l | H20: l | K20: 10 | L20: E&O | M20: Need
B21: l | C21: l | D21: l | E21: l | F21: l | G21: l | H21: l | K21: 11 | L21: Scrap | M21: Need
B22: l | C22: l | D22: l | E22: l | F22: l | G22: l | H22: l | K22: 12 | L22: Warranty | M22: Need
B23: l | C23: l | D23: l | F23: l | G23: l | H23: l | J23: Fixed OHCOGS | K23: 14 | L23: Quality | M23: Need
B24: l | D24: l | F24: l | G24: l | H24: l | K24: 15 | L24: VBS | M24: Need
B25: l | D25: l | F25: l | G25: l | H25: l | K25: 16 | L25: Customer Service | M25: Need
B26: l | D26: l | F26: l | G26: l | H26: l | K26: 17 | L26: Operations Supervisors | M26: Need
B27: l | C27: l | D27: l | F27: l | G27: l | H27: l | K27: 18 | L27: Purchasing | M27: Need
B28: l | C28: l | D28: l | F28: l | G28: l | H28: l | K28: 19 | L28: Factory consumables (paint, PPE, oil, testing) | M28: Need
B29: l | C29: l | D29: l | F29: l | G29: l | H29: l | K29: 20 | L29: Contract services - maintenance, security, leasing, general consulting | M29: Need
B30: l | D30: l | F30: l | G30: l | H30: l | K30: 21 | L30: Property Taxes | M30: Need
B31: l | D31: l | F31: l | G31: l | H31: l | K31: 22 | L31: Insurance | M31: Need
B32: l | D32: l | F32: l | G32: l | H32: l | K32: 23 | L32: Environmental costs - including reserves | M32: Need
B33: l | D33: l | F33: l | G33: l | H33: l | K33: 24 | L33: Factory Maintenance | M33: Need
B34: l | D34: l | F34: l | G34: l | H34: l | K34: 25 | L34: Shared Services (canteen, cleaning …) | M34: Need
B35: l | D35: l | F35: l | G35: l | H35: l | K35: 26 | L35: Utilities (water, electricity, gas) | M35: Need
B36: l | D36: l | F36: l | J36: OPEX | K36: 27 | L36: HR | M36: Need
B37: l | D37: l | F37: l | K37: 28 | L37: Finance | M37: Need
B38: l | D38: l | F38: l | K38: 29 | L38: IT | M38: Need
B39: l | D39: l | E39: l | F39: l | H39: l | K39: 30 | L39: Sustaining Engineering | M39: Need
B40: l | D40: l | F40: l | K40: 31 | L40: Sales | M40: Need
B41: l | D41: l | F41: l | K41: 32 | L41: Marketing | M41: Need
B42: l | D42: l | E42: l | F42: l | K42: 33 | L42: 3rd party services - IT, Engineering, Marketing, general consulting, payroll | M42: Need
B43: l | D43: l | F43: l | G43: l | H43: l | J43: Investment | K43: 34 | L43: Restructuring expense | M43: Need
B44: l | C44: l | D44: l | E44: l | F44: l | G44: l | H44: l | K44: 35 | L44: 3rd party expenses | M44: Need
B45: l | C45: l | D45: l | E45: l | F45: l | G45: l | H45: l | K45: 36 | L45: Fixed asset write off | M45: Need
B46: l | C46: l | D46: l | E46: l | F46: l | G46: l | H46: l | K46: 37 | L46: E&O/Write off of inventory impact | M46: Need
B47: l | C47: l | D47: l | E47: l | F47: l | G47: l | H47: l | K47: 38 | L47: Capital Expenditures | M47: Need
B48: l | C48: l | D48: l | E48: l | F48: l | G48: l | H48: l | K48: 39 | L48: Asset sale | M48: Need
B49: l | C49: l | D49: l | E49: l | F49: l | G49: l | H49: l | J49: Balance Sheet | K49: 40 | L49: Inventory | M49: Need
B50: l | D50: l | F50: l | G50: l | H50: l | K50: 41 | L50: Accounts Receivable | M50: Need
B51: l | C51: l | D51: l | F51: l | G51: l | H51: l | K51: 42 | L51: Accounts Payable | M51: Need
B52: l | C52: l | D52: l | E52: l | F52: l | G52: l | H52: l | J52: Other Intangibles | K52: A | L52: Productiivity | M52: Need
B53: l | C53: l | D53: l | E53: l | F53: l | G53: l | H53: l | K53: B | L53: Floor space | M53: Need
B54: l | C54: l | D54: l | E54: l | F54: l | G54: l | H54: l | K54: C | L54: Project Accumulation | M54: Need

Sheet Compare
B3: =IF(Inputs!C4="","[Insert Project Name in Inputs Tab]",Inputs!C4) -> [Insert Project Name in Inputs Tab] | D3: Variance | M3: Select>> | N3: Select Scenario | W3: Select>> | X3: Select Scenario
B4: (000s) | N4: =IFERROR(_xlfn.XLOOKUP(N3,Inputs!B22:B26,Inputs!C22:C26,""),"") | X4: =IFERROR(_xlfn.XLOOKUP(X3,Inputs!B22:B26,Inputs!C22:C26,""),"")
D6: 2023 | E6: 2024 | F6: 2025 | G6: 2026 | H6: 2027 | I6: 2028 | J6: 2029 | K6: 2030 | N6: {=IF($N$3="Select Scenario","", IF($N$3=Scenarios!D2,Scenarios!D5:K48, IF($N$3=Scenarios!M2,Scenarios!M5:T48, IF($N$3=Scenarios!V2,Scenarios!V5:AC48, IF($N$3=Scenarios!AE2,Scenarios!AE5:AL48, IF($N$3=Scenarios!AN2,Scenarios!AN5:AU48, IF($N$3=Scenarios!AW2,Scenarios!AW5:BD48,"")))))))} | X6: {=IF($X$3="Select Scenario","", IF($X$3=Scenarios!D2,Scenarios!D5:K48, IF($X$3=Scenarios!M2,Scenarios!M5:T48, IF($X$3=Scenarios!V2,Scenarios!V5:AC48, IF($X$3=Scenarios!AE2,Scenarios!AE5:AL48, IF($X$3=Scenarios!AN2,Scenarios!AN5:AU48, IF($X$3=Scenarios!AW2,Scenarios!AW5:BD48,"")))))))}
B7: Net Sales | C7: (000) | D7: =N7-X7 -> 0 | E7: =O7-Y7 -> 0 | F7: =P7-Z7 -> 0 | G7: =Q7-AA7 -> 0 | H7: =R7-AB7 -> 0 | I7: =S7-AC7 -> 0 | J7: =T7-AD7 -> 0 | K7: =U7-AE7 -> 0
B9: Direct Margin | C9: (000) | D9: =N9-X9 -> 0 | E9: =O9-Y9 -> 0 | F9: =P9-Z9 -> 0 | G9: =Q9-AA9 -> 0 | H9: =R9-AB9 -> 0 | I9: =S9-AC9 -> 0 | J9: =T9-AD9 -> 0 | K9: =U9-AE9 -> 0
B10: Direct Margin % | D10: =N10-X10 -> 0 | E10: =O10-Y10 -> 0 | F10: =P10-Z10 -> 0 | G10: =Q10-AA10 -> 0 | H10: =R10-AB10 -> 0 | I10: =S10-AC10 -> 0 | J10: =T10-AD10 -> 0 | K10: =U10-AE10 -> 0
B12: Variances | C12: (000) | D12: =N12-X12 -> 0 | E12: =O12-Y12 -> 0 | F12: =P12-Z12 -> 0 | G12: =Q12-AA12 -> 0 | H12: =R12-AB12 -> 0 | I12: =S12-AC12 -> 0 | J12: =T12-AD12 -> 0 | K12: =U12-AE12 -> 0
B13: OHCOGS | C13: (000) | D13: =N13-X13 -> 0 | E13: =O13-Y13 -> 0 | F13: =P13-Z13 -> 0 | G13: =Q13-AA13 -> 0 | H13: =R13-AB13 -> 0 | I13: =S13-AC13 -> 0 | J13: =T13-AD13 -> 0 | K13: =U13-AE13 -> 0
B15: Gross Profit | C15: (000) | D15: =D9-SUM(D12:D13) -> 0 | E15: =E9-SUM(E12:E13) -> 0 | F15: =F9-SUM(F12:F13) -> 0 | G15: =G9-SUM(G12:G13) -> 0 | H15: =H9-SUM(H12:H13) -> 0 | I15: =I9-SUM(I12:I13) -> 0 | J15: =J9-SUM(J12:J13) -> 0 | K15: =K9-SUM(K12:K13) -> 0
B16: Gross Profit % | D16: =N16-X16 -> 0 | E16: =O16-Y16 -> 0 | F16: =P16-Z16 -> 0 | G16: =Q16-AA16 -> 0 | H16: =R16-AB16 -> 0 | I16: =S16-AC16 -> 0 | J16: =T16-AD16 -> 0 | K16: =U16-AE16 -> 0
B18: R&D | C18: (000) | D18: =N18-X18 -> 0 | E18: =O18-Y18 -> 0 | F18: =P18-Z18 -> 0 | G18: =Q18-AA18 -> 0 | H18: =R18-AB18 -> 0 | I18: =S18-AC18 -> 0 | J18: =T18-AD18 -> 0 | K18: =U18-AE18 -> 0
B19: S&M | C19: (000) | D19: =N19-X19 -> 0 | E19: =O19-Y19 -> 0 | F19: =P19-Z19 -> 0 | G19: =Q19-AA19 -> 0 | H19: =R19-AB19 -> 0 | I19: =S19-AC19 -> 0 | J19: =T19-AD19 -> 0 | K19: =U19-AE19 -> 0
B20: G&A | C20: (000) | D20: =N20-X20 -> 0 | E20: =O20-Y20 -> 0 | F20: =P20-Z20 -> 0 | G20: =Q20-AA20 -> 0 | H20: =R20-AB20 -> 0 | I20: =S20-AC20 -> 0 | J20: =T20-AD20 -> 0 | K20: =U20-AE20 -> 0
B21: All Other Period Expenses | C21: (000) | D21: =N21-X21 -> 0 | E21: =O21-Y21 -> 0 | F21: =P21-Z21 -> 0 | G21: =Q21-AA21 -> 0 | H21: =R21-AB21 -> 0 | I21: =S21-AC21 -> 0 | J21: =T21-AD21 -> 0 | K21: =U21-AE21 -> 0
B22: Total Period Expenses | C22: (000) | D22: =N22-X22 -> 0 | E22: =O22-Y22 -> 0 | F22: =P22-Z22 -> 0 | G22: =Q22-AA22 -> 0 | H22: =R22-AB22 -> 0 | I22: =S22-AC22 -> 0 | J22: =T22-AD22 -> 0 | K22: =U22-AE22 -> 0
B23: Depreciation | C23: (000) | D23: =N23-X23 -> 0 | E23: =O23-Y23 -> 0 | F23: =P23-Z23 -> 0 | G23: =Q23-AA23 -> 0 | H23: =R23-AB23 -> 0 | I23: =S23-AC23 -> 0 | J23: =T23-AD23 -> 0 | K23: =U23-AE23 -> 0
B25: Operating Profit | C25: (000) | D25: =N25-X25 -> 0 | E25: =O25-Y25 -> 0 | F25: =P25-Z25 -> 0 | G25: =Q25-AA25 -> 0 | H25: =R25-AB25 -> 0 | I25: =S25-AC25 -> 0 | J25: =T25-AD25 -> 0 | K25: =U25-AE25 -> 0
B26: OP% | D26: =N26-X26 -> 0 | E26: =O26-Y26 -> 0 | F26: =P26-Z26 -> 0 | G26: =Q26-AA26 -> 0 | H26: =R26-AB26 -> 0 | I26: =S26-AC26 -> 0 | J26: =T26-AD26 -> 0 | K26: =U26-AE26 -> 0
B28: Non-Operating Expenses (Income) | C28: (000) | D28: =N28-X28 -> 0 | E28: =O28-Y28 -> 0 | F28: =P28-Z28 -> 0 | G28: =Q28-AA28 -> 0 | H28: =R28-AB28 -> 0 | I28: =S28-AC28 -> 0 | J28: =T28-AD28 -> 0 | K28: =U28-AE28 -> 0
B29: Investment Expenses | C29: (000) | D29: =N29-X29 -> 0 | E29: =O29-Y29 -> 0 | F29: =P29-Z29 -> 0 | G29: =Q29-AA29 -> 0 | H29: =R29-AB29 -> 0 | I29: =S29-AC29 -> 0 | J29: =T29-AD29 -> 0 | K29: =U29-AE29 -> 0
B30: Restructuring | C30: (000) | D30: =N30-X30 -> 0 | E30: =O30-Y30 -> 0 | F30: =P30-Z30 -> 0 | G30: =Q30-AA30 -> 0 | H30: =R30-AB30 -> 0 | I30: =S30-AC30 -> 0 | J30: =T30-AD30 -> 0 | K30: =U30-AE30 -> 0
B31: Taxes | C31: (000) | D31: =N31-X31 -> 0 | E31: =O31-Y31 -> 0 | F31: =P31-Z31 -> 0 | G31: =Q31-AA31 -> 0 | H31: =R31-AB31 -> 0 | I31: =S31-AC31 -> 0 | J31: =T31-AD31 -> 0 | K31: =U31-AE31 -> 0
B33: Net Income | C33: (000) | D33: =N33-X33 -> 0 | E33: =O33-Y33 -> 0 | F33: =P33-Z33 -> 0 | G33: =Q33-AA33 -> 0 | H33: =R33-AB33 -> 0 | I33: =S33-AC33 -> 0 | J33: =T33-AD33 -> 0 | K33: =U33-AE33 -> 0
D34: =N34-X34 -> 0 | E34: =O34-Y34 -> 0 | F34: =P34-Z34 -> 0 | G34: =Q34-AA34 -> 0 | H34: =R34-AB34 -> 0 | I34: =S34-AC34 -> 0 | J34: =T34-AD34 -> 0 | K34: =U34-AE34 -> 0
B36: Cash Flow Periodic | C36: (000) | D36: =N36-X36 -> 0 | E36: =O36-Y36 -> 0 | F36: =P36-Z36 -> 0 | G36: =Q36-AA36 -> 0 | H36: =R36-AB36 -> 0 | I36: =S36-AC36 -> 0 | J36: =T36-AD36 -> 0 | K36: =U36-AE36 -> 0
B37: Cash Flow Cumulative | C37: (000) | D37: =N37-X37 -> 0 | E37: =O37-Y37 -> 0 | F37: =P37-Z37 -> 0 | G37: =Q37-AA37 -> 0 | H37: =R37-AB37 -> 0 | I37: =S37-AC37 -> 0 | J37: =T37-AD37 -> 0 | K37: =U37-AE37 -> 0
B40: Working Capital Balance | C40: (000) | D40: =N40-X40 -> 0 | E40: =O40-Y40 -> 0 | F40: =P40-Z40 -> 0 | G40: =Q40-AA40 -> 0 | H40: =R40-AB40 -> 0 | I40: =S40-AC40 -> 0 | J40: =T40-AD40 -> 0 | K40: =U40-AE40 -> 0
B41: Change in Working Capital | C41: (000) | D41: =N41-X41 -> 0 | E41: =O41-Y41 -> 0 | F41: =P41-Z41 -> 0 | G41: =Q41-AA41 -> 0 | H41: =R41-AB41 -> 0 | I41: =S41-AC41 -> 0 | J41: =T41-AD41 -> 0 | K41: =U41-AE41 -> 0
B42: Total Investment | C42: (000) | D42: =N42-X42 -> 0 | E42: =O42-Y42 -> 0 | F42: =P42-Z42 -> 0 | G42: =Q42-AA42 -> 0 | H42: =R42-AB42 -> 0 | I42: =S42-AC42 -> 0 | J42: =T42-AD42 -> 0 | K42: =U42-AE42 -> 0
B43: ROIC (after-tax) | C43: pct. | D43: =IFERROR(D33/D42,0) -> 0 | E43: =IFERROR(E33/E42,0) -> 0 | F43: =IFERROR(F33/F42,0) -> 0 | G43: =IFERROR(G33/G42,0) -> 0 | H43: =IFERROR(H33/H42,0) -> 0 | I43: =IFERROR(I33/I42,0) -> 0 | J43: =IFERROR(J33/J42,0) -> 0 | K43: =IFERROR(K33/K42,0) -> 0
B45: Net Present Value | C45: (000) | D45: =NPV(wacc,G33:K33) -> 0
B46: Terminal Value | C46: (000) | D46: =(K33*(1+tv_growth)/(wacc-tv_growth))/(1+wacc)^5 -> 0
B47: Total EV | C47: (000) | D47: =SUM(D45:D46) -> 0
B49: Payback Period | C49: yrs | D49: {=IFERROR(MATCH(TRUE,G33:K33>=0,0),"5+")} -> 1

Sheet Scenarios
B2: =IF(Inputs!C4="","[Insert Project Name in Inputs Tab]",Inputs!C4) -> [Insert Project Name in Inputs Tab] | D2: Current State | M2: =Inputs!B22 -> Scenario 1 | V2: =Inputs!B23 -> Scenario 2 | AE2: =Inputs!B24 -> Scenario 3 | AN2: =Inputs!B25 -> Scenario 4 | AW2: =Inputs!B26 -> Scenario 5
B3: (000s) | D3: No Change - Only pulling actuals | M3: =Inputs!C22 -> Scenario 1 Description | V3: =Inputs!C23 -> Scenario 2 Description | AE3: =Inputs!C24 -> Scenario 3 Description | AN3: =Inputs!C25 -> Scenario 4 Description | AW3: =Inputs!C26 -> Scenario 5 Description
D5: 2023 | E5: 2024 | F5: 2025 | G5: 2026 | H5: 2027 | I5: 2028 | J5: 2029 | K5: 2030 | M5: 2023 | N5: 2024 | O5: 2025 | P5: 2026 | Q5: 2027 | R5: 2028 | S5: 2029 | T5: 2030 | V5: 2023 | W5: 2024 | X5: 2025 | Y5: 2026 | Z5: 2027 | AA5: 2028 | AB5: 2029 | AC5: 2030 | AE5: 2023 | AF5: 2024 | AG5: 2025 | AH5: 2026 | AI5: 2027 | AJ5: 2028 | AK5: 2029 | AL5: 2030 | AN5: 2023 | AO5: 2024 | AP5: 2025 | AQ5: 2026 | AR5: 2027 | AS5: 2028 | AT5: 2029 | AU5: 2030 | AW5: 2023 | AX5: 2024 | AY5: 2025 | AZ5: 2026 | BA5: 2027 | BB5: 2028 | BC5: 2029 | BD5: 2030
B6: Net Sales | C6: (000) | D6: ='1. Margins'!F519 -> 0 | E6: ='1. Margins'!G519 -> 0 | F6: ='1. Margins'!H519 -> 0 | G6: ='1. Margins'!M519 -> 0 | H6: ='1. Margins'!R519 -> 0 | I6: ='1. Margins'!S519 -> 0 | J6: ='1. Margins'!T519 -> 0 | K6: ='1. Margins'!U519 -> 0 | M6: ='1. Margins'!F19 -> 0 | N6: ='1. Margins'!G19 -> 0 | O6: ='1. Margins'!H19 -> 0 | P6: ='1. Margins'!M19 -> 0 | Q6: ='1. Margins'!R19 -> 0 | R6: ='1. Margins'!S19 -> 0 | S6: ='1. Margins'!T19 -> 0 | T6: ='1. Margins'!U19 -> 0 | V6: ='1. Margins'!F119 -> 0 | W6: ='1. Margins'!G119 -> 0 | X6: ='1. Margins'!H119 -> 0 | Y6: ='1. Margins'!M119 -> 0 | Z6: ='1. Margins'!R119 -> 0 | AA6: ='1. Margins'!S119 -> 0 | AB6: ='1. Margins'!T119 -> 0 | AC6: ='1. Margins'!U119 -> 0 | AE6: ='1. Margins'!F219 -> 0 | AF6: ='1. Margins'!G219 -> 0 | AG6: ='1. Margins'!H219 -> 0 | AH6: ='1. Margins'!M219 -> 0 | AI6: ='1. Margins'!R219 -> 0 | AJ6: ='1. Margins'!S219 -> 0 | AK6: ='1. Margins'!T219 -> 0 | AL6: ='1. Margins'!U219 -> 0 | AN6: ='1. Margins'!F319 -> 0 | AO6: ='1. Margins'!G319 -> 0 | AP6: ='1. Margins'!H319 -> 0 | AQ6: ='1. Margins'!M319 -> 0 | AR6: ='1. Margins'!R319 -> 0 | AS6: ='1. Margins'!S319 -> 0 | AT6: ='1. Margins'!T319 -> 0 | AU6: ='1. Margins'!U319 -> 0 | AW6: ='1. Margins'!F419 -> 0 | AX6: ='1. Margins'!G419 -> 0 | AY6: ='1. Margins'!H419 -> 0 | AZ6: ='1. Margins'!M419 -> 0 | BA6: ='1. Margins'!R419 -> 0 | BB6: ='1. Margins'!S419 -> 0 | BC6: ='1. Margins'!T419 -> 0 | BD6: ='1. Margins'!U419 -> 0
B8: Direct Margin | C8: (000) | D8: ='1. Margins'!F583 -> 0 | E8: ='1. Margins'!G583 -> 0 | F8: ='1. Margins'!H583 -> 0 | G8: ='1. Margins'!M583 -> 0 | H8: ='1. Margins'!R583 -> 0 | I8: ='1. Margins'!S583 -> 0 | J8: ='1. Margins'!T583 -> 0 | K8: ='1. Margins'!U583 -> 0 | M8: ='1. Margins'!F83 -> 0 | N8: ='1. Margins'!G83 -> 0 | O8: ='1. Margins'!H83 -> 0 | P8: ='1. Margins'!M83 -> 0 | Q8: ='1. Margins'!R83 -> 0 | R8: ='1. Margins'!S83 -> 0 | S8: ='1. Margins'!T83 -> 0 | T8: ='1. Margins'!U83 -> 0 | V8: ='1. Margins'!F183 -> 0 | W8: ='1. Margins'!G183 -> 0 | X8: ='1. Margins'!H183 -> 0 | Y8: ='1. Margins'!M183 -> 0 | Z8: ='1. Margins'!R183 -> 0 | AA8: ='1. Margins'!S183 -> 0 | AB8: ='1. Margins'!T183 -> 0 | AC8: ='1. Margins'!U183 -> 0 | AE8: ='1. Margins'!F283 -> 0 | AF8: ='1. Margins'!G283 -> 0 | AG8: ='1. Margins'!H283 -> 0 | AH8: ='1. Margins'!M283 -> 0 | AI8: ='1. Margins'!R283 -> 0 | AJ8: ='1. Margins'!S283 -> 0 | AK8: ='1. Margins'!T283 -> 0 | AL8: ='1. Margins'!U283 -> 0 | AN8: ='1. Margins'!F383 -> 0 | AO8: ='1. Margins'!G383 -> 0 | AP8: ='1. Margins'!H383 -> 0 | AQ8: ='1. Margins'!M383 -> 0 | AR8: ='1. Margins'!R383 -> 0 | AS8: ='1. Margins'!S383 -> 0 | AT8: ='1. Margins'!T383 -> 0 | AU8: ='1. Margins'!U383 -> 0 | AW8: ='1. Margins'!F483 -> 0 | AX8: ='1. Margins'!G483 -> 0 | AY8: ='1. Margins'!H483 -> 0 | AZ8: ='1. Margins'!M483 -> 0 | BA8: ='1. Margins'!R483 -> 0 | BB8: ='1. Margins'!S483 -> 0 | BC8: ='1. Margins'!T483 -> 0 | BD8: ='1. Margins'!U483 -> 0
B9: Direct Margin % | D9: =IFERROR(D8/D$6,0) -> 0 | E9: =IFERROR(E8/E$6,0) -> 0 | F9: =IFERROR(F8/F$6,0) -> 0 | G9: =IFERROR(G8/G$6,0) -> 0 | H9: =IFERROR(H8/H$6,0) -> 0 | I9: =IFERROR(I8/I$6,0) -> 0 | J9: =IFERROR(J8/J$6,0) -> 0 | K9: =IFERROR(K8/K$6,0) -> 0 | M9: =IFERROR(M8/M$6,0) -> 0 | N9: =IFERROR(N8/N$6,0) -> 0 | O9: =IFERROR(O8/O$6,0) -> 0 | P9: =IFERROR(P8/P$6,0) -> 0 | Q9: =IFERROR(Q8/Q$6,0) -> 0 | R9: =IFERROR(R8/R$6,0) -> 0 | S9: =IFERROR(S8/S$6,0) -> 0 | T9: =IFERROR(T8/T$6,0) -> 0 | V9: =IFERROR(V8/V$6,0) -> 0 | W9: =IFERROR(W8/W$6,0) -> 0 | X9: =IFERROR(X8/X$6,0) -> 0 | Y9: =IFERROR(Y8/Y$6,0) -> 0 | Z9: =IFERROR(Z8/Z$6,0) -> 0 | AA9: =IFERROR(AA8/AA$6,0) -> 0 | AB9: =IFERROR(AB8/AB$6,0) -> 0 | AC9: =IFERROR(AC8/AC$6,0) -> 0 | AE9: =IFERROR(AE8/AE$6,0) -> 0 | AF9: =IFERROR(AF8/AF$6,0) -> 0 | AG9: =IFERROR(AG8/AG$6,0) -> 0 | AH9: =IFERROR(AH8/AH$6,0) -> 0 | AI9: =IFERROR(AI8/AI$6,0) -> 0 | AJ9: =IFERROR(AJ8/AJ$6,0) -> 0 | AK9: =IFERROR(AK8/AK$6,0) -> 0 | AL9: =IFERROR(AL8/AL$6,0) -> 0 | AN9: =IFERROR(AN8/AN$6,0) -> 0 | AO9: =IFERROR(AO8/AO$6,0) -> 0 | AP9: =IFERROR(AP8/AP$6,0) -> 0 | AQ9: =IFERROR(AQ8/AQ$6,0) -> 0 | AR9: =IFERROR(AR8/AR$6,0) -> 0 | AS9: =IFERROR(AS8/AS$6,0) -> 0 | AT9: =IFERROR(AT8/AT$6,0) -> 0 | AU9: =IFERROR(AU8/AU$6,0) -> 0 | AW9: =IFERROR(AW8/AW$6,0) -> 0 | AX9: =IFERROR(AX8/AX$6,0) -> 0 | AY9: =IFERROR(AY8/AY$6,0) -> 0 | AZ9: =IFERROR(AZ8/AZ$6,0) -> 0 | BA9: =IFERROR(BA8/BA$6,0) -> 0 | BB9: =IFERROR(BB8/BB$6,0) -> 0 | BC9: =IFERROR(BC8/BC$6,0) -> 0 | BD9: =IFERROR(BD8/BD$6,0) -> 0
B11: Variances | C11: (000) | D11: ='2. OHCOGS'!F210 -> 0 | E11: ='2. OHCOGS'!G210 -> 0 | F11: ='2. OHCOGS'!H210 -> 0 | G11: ='2. OHCOGS'!M210 -> 0 | H11: ='2. OHCOGS'!R210 -> 0 | I11: ='2. OHCOGS'!S210 -> 0 | J11: ='2. OHCOGS'!T210 -> 0 | K11: ='2. OHCOGS'!U210 -> 0 | M11: ='2. OHCOGS'!F20 -> 0 | N11: ='2. OHCOGS'!G20 -> 0 | O11: ='2. OHCOGS'!H20 -> 0 | P11: ='2. OHCOGS'!M20 -> 0 | Q11: ='2. OHCOGS'!R20 -> 0 | R11: ='2. OHCOGS'!S20 -> 0 | S11: ='2. OHCOGS'!T20 -> 0 | T11: ='2. OHCOGS'!U20 -> 0 | V11: ='2. OHCOGS'!F58 -> 0 | W11: ='2. OHCOGS'!G58 -> 0 | X11: ='2. OHCOGS'!H58 -> 0 | Y11: ='2. OHCOGS'!M58 -> 0 | Z11: ='2. OHCOGS'!R58 -> 0 | AA11: ='2. OHCOGS'!S58 -> 0 | AB11: ='2. OHCOGS'!T58 -> 0 | AC11: ='2. OHCOGS'!U58 -> 0 | AE11: ='2. OHCOGS'!F96 -> 0 | AF11: ='2. OHCOGS'!G96 -> 0 | AG11: ='2. OHCOGS'!H96 -> 0 | AH11: ='2. OHCOGS'!M96 -> 0 | AI11: ='2. OHCOGS'!R96 -> 0 | AJ11: ='2. OHCOGS'!S96 -> 0 | AK11: ='2. OHCOGS'!T96 -> 0 | AL11: ='2. OHCOGS'!U96 -> 0 | AN11: ='2. OHCOGS'!F134 -> 0 | AO11: ='2. OHCOGS'!G134 -> 0 | AP11: ='2. OHCOGS'!H134 -> 0 | AQ11: ='2. OHCOGS'!M134 -> 0 | AR11: ='2. OHCOGS'!R134 -> 0 | AS11: ='2. OHCOGS'!S134 -> 0 | AT11: ='2. OHCOGS'!T134 -> 0 | AU11: ='2. OHCOGS'!U134 -> 0 | AW11: ='2. OHCOGS'!F172 -> 0 | AX11: ='2. OHCOGS'!G172 -> 0 | AY11: ='2. OHCOGS'!H172 -> 0 | AZ11: ='2. OHCOGS'!M172 -> 0 | BA11: ='2. OHCOGS'!R172 -> 0 | BB11: ='2. OHCOGS'!S172 -> 0 | BC11: ='2. OHCOGS'!T172 -> 0 | BD11: ='2. OHCOGS'!U172 -> 0
B12: OHCOGS | C12: (000) | D12: ='2. OHCOGS'!F223 -> 0 | E12: ='2. OHCOGS'!G223 -> 0 | F12: ='2. OHCOGS'!H223 -> 0 | G12: ='2. OHCOGS'!M223 -> 0 | H12: ='2. OHCOGS'!R223 -> 0 | I12: ='2. OHCOGS'!S223 -> 0 | J12: ='2. OHCOGS'!T223 -> 0 | K12: ='2. OHCOGS'!U223 -> 0 | M12: ='2. OHCOGS'!F37 -> 0 | N12: ='2. OHCOGS'!G37 -> 0 | O12: ='2. OHCOGS'!H37 -> 0 | P12: ='2. OHCOGS'!M37 -> 0 | Q12: ='2. OHCOGS'!R37 -> 0 | R12: ='2. OHCOGS'!S37 -> 0 | S12: ='2. OHCOGS'!T37 -> 0 | T12: ='2. OHCOGS'!U37 -> 0 | V12: ='2. OHCOGS'!F75 -> 0 | W12: ='2. OHCOGS'!G75 -> 0 | X12: ='2. OHCOGS'!H75 -> 0 | Y12: ='2. OHCOGS'!M75 -> 0 | Z12: ='2. OHCOGS'!R75 -> 0 | AA12: ='2. OHCOGS'!S75 -> 0 | AB12: ='2. OHCOGS'!T75 -> 0 | AC12: ='2. OHCOGS'!U75 -> 0 | AE12: ='2. OHCOGS'!F113 -> 0 | AF12: ='2. OHCOGS'!G113 -> 0 | AG12: ='2. OHCOGS'!H113 -> 0 | AH12: ='2. OHCOGS'!M113 -> 0 | AI12: ='2. OHCOGS'!R113 -> 0 | AJ12: ='2. OHCOGS'!S113 -> 0 | AK12: ='2. OHCOGS'!T113 -> 0 | AL12: ='2. OHCOGS'!U113 -> 0 | AN12: ='2. OHCOGS'!F151 -> 0 | AO12: ='2. OHCOGS'!G151 -> 0 | AP12: ='2. OHCOGS'!H151 -> 0 | AQ12: ='2. OHCOGS'!M151 -> 0 | AR12: ='2. OHCOGS'!R151 -> 0 | AS12: ='2. OHCOGS'!S151 -> 0 | AT12: ='2. OHCOGS'!T151 -> 0 | AU12: ='2. OHCOGS'!U151 -> 0 | AW12: ='2. OHCOGS'!F189 -> 0 | AX12: ='2. OHCOGS'!G189 -> 0 | AY12: ='2. OHCOGS'!H189 -> 0 | AZ12: ='2. OHCOGS'!M189 -> 0 | BA12: ='2. OHCOGS'!R189 -> 0 | BB12: ='2. OHCOGS'!S189 -> 0 | BC12: ='2. OHCOGS'!T189 -> 0 | BD12: ='2. OHCOGS'!U189 -> 0
B14: Gross Profit | C14: (000) | D14: =D8-SUM(D11:D12) -> 0 | E14: =E8-SUM(E11:E12) -> 0 | F14: =F8-SUM(F11:F12) -> 0 | G14: =G8-SUM(G11:G12) -> 0 | H14: =H8-SUM(H11:H12) -> 0 | I14: =I8-SUM(I11:I12) -> 0 | J14: =J8-SUM(J11:J12) -> 0 | K14: =K8-SUM(K11:K12) -> 0 | M14: =M8-SUM(M11:M12) -> 0 | N14: =N8-SUM(N11:N12) -> 0 | O14: =O8-SUM(O11:O12) -> 0 | P14: =P8-SUM(P11:P12) -> 0 | Q14: =Q8-SUM(Q11:Q12) -> 0 | R14: =R8-SUM(R11:R12) -> 0 | S14: =S8-SUM(S11:S12) -> 0 | T14: =T8-SUM(T11:T12) -> 0 | V14: =V8-SUM(V11:V12) -> 0 | W14: =W8-SUM(W11:W12) -> 0 | X14: =X8-SUM(X11:X12) -> 0 | Y14: =Y8-SUM(Y11:Y12) -> 0 | Z14: =Z8-SUM(Z11:Z12) -> 0 | AA14: =AA8-SUM(AA11:AA12) -> 0 | AB14: =AB8-SUM(AB11:AB12) -> 0 | AC14: =AC8-SUM(AC11:AC12) -> 0 | AE14: =AE8-SUM(AE11:AE12) -> 0 | AF14: =AF8-SUM(AF11:AF12) -> 0 | AG14: =AG8-SUM(AG11:AG12) -> 0 | AH14: =AH8-SUM(AH11:AH12) -> 0 | AI14: =AI8-SUM(AI11:AI12) -> 0 | AJ14: =AJ8-SUM(AJ11:AJ12) -> 0 | AK14: =AK8-SUM(AK11:AK12) -> 0 | AL14: =AL8-SUM(AL11:AL12) -> 0 | AN14: =AN8-SUM(AN11:AN12) -> 0 | AO14: =AO8-SUM(AO11:AO12) -> 0 | AP14: =AP8-SUM(AP11:AP12) -> 0 | AQ14: =AQ8-SUM(AQ11:AQ12) -> 0 | AR14: =AR8-SUM(AR11:AR12) -> 0 | AS14: =AS8-SUM(AS11:AS12) -> 0 | AT14: =AT8-SUM(AT11:AT12) -> 0 | AU14: =AU8-SUM(AU11:AU12) -> 0 | AW14: =AW8-SUM(AW11:AW12) -> 0 | AX14: =AX8-SUM(AX11:AX12) -> 0 | AY14: =AY8-SUM(AY11:AY12) -> 0 | AZ14: =AZ8-SUM(AZ11:AZ12) -> 0 | BA14: =BA8-SUM(BA11:BA12) -> 0 | BB14: =BB8-SUM(BB11:BB12) -> 0 | BC14: =BC8-SUM(BC11:BC12) -> 0 | BD14: =BD8-SUM(BD11:BD12) -> 0
B15: Gross Profit % | D15: =IFERROR(D14/D$6,0) -> 0 | E15: =IFERROR(E14/E$6,0) -> 0 | F15: =IFERROR(F14/F$6,0) -> 0 | G15: =IFERROR(G14/G$6,0) -> 0 | H15: =IFERROR(H14/H$6,0) -> 0 | I15: =IFERROR(I14/I$6,0) -> 0 | J15: =IFERROR(J14/J$6,0) -> 0 | K15: =IFERROR(K14/K$6,0) -> 0 | M15: =IFERROR(M14/M$6,0) -> 0 | N15: =IFERROR(N14/N$6,0) -> 0 | O15: =IFERROR(O14/O$6,0) -> 0 | P15: =IFERROR(P14/P$6,0) -> 0 | Q15: =IFERROR(Q14/Q$6,0) -> 0 | R15: =IFERROR(R14/R$6,0) -> 0 | S15: =IFERROR(S14/S$6,0) -> 0 | T15: =IFERROR(T14/T$6,0) -> 0 | V15: =IFERROR(V14/V$6,0) -> 0 | W15: =IFERROR(W14/W$6,0) -> 0 | X15: =IFERROR(X14/X$6,0) -> 0 | Y15: =IFERROR(Y14/Y$6,0) -> 0 | Z15: =IFERROR(Z14/Z$6,0) -> 0 | AA15: =IFERROR(AA14/AA$6,0) -> 0 | AB15: =IFERROR(AB14/AB$6,0) -> 0 | AC15: =IFERROR(AC14/AC$6,0) -> 0 | AE15: =IFERROR(AE14/AE$6,0) -> 0 | AF15: =IFERROR(AF14/AF$6,0) -> 0 | AG15: =IFERROR(AG14/AG$6,0) -> 0 | AH15: =IFERROR(AH14/AH$6,0) -> 0 | AI15: =IFERROR(AI14/AI$6,0) -> 0 | AJ15: =IFERROR(AJ14/AJ$6,0) -> 0 | AK15: =IFERROR(AK14/AK$6,0) -> 0 | AL15: =IFERROR(AL14/AL$6,0) -> 0 | AN15: =IFERROR(AN14/AN$6,0) -> 0 | AO15: =IFERROR(AO14/AO$6,0) -> 0 | AP15: =IFERROR(AP14/AP$6,0) -> 0 | AQ15: =IFERROR(AQ14/AQ$6,0) -> 0 | AR15: =IFERROR(AR14/AR$6,0) -> 0 | AS15: =IFERROR(AS14/AS$6,0) -> 0 | AT15: =IFERROR(AT14/AT$6,0) -> 0 | AU15: =IFERROR(AU14/AU$6,0) -> 0 | AW15: =IFERROR(AW14/AW$6,0) -> 0 | AX15: =IFERROR(AX14/AX$6,0) -> 0 | AY15: =IFERROR(AY14/AY$6,0) -> 0 | AZ15: =IFERROR(AZ14/AZ$6,0) -> 0 | BA15: =IFERROR(BA14/BA$6,0) -> 0 | BB15: =IFERROR(BB14/BB$6,0) -> 0 | BC15: =IFERROR(BC14/BC$6,0) -> 0 | BD15: =IFERROR(BD14/BD$6,0) -> 0
B17: R&D | C17: (000) | D17: ='3. Opex'!F132 -> 0 | E17: ='3. Opex'!G132 -> 0 | F17: ='3. Opex'!H132 -> 0 | G17: ='3. Opex'!M132 -> 0 | H17: ='3. Opex'!R132 -> 0 | I17: ='3. Opex'!S132 -> 0 | J17: ='3. Opex'!T132 -> 0 | K17: ='3. Opex'!U132 -> 0 | M17: ='3. Opex'!F12 -> 0 | N17: ='3. Opex'!G12 -> 0 | O17: ='3. Opex'!H12 -> 0 | P17: ='3. Opex'!M12 -> 0 | Q17: ='3. Opex'!R12 -> 0 | R17: ='3. Opex'!S12 -> 0 | S17: ='3. Opex'!T12 -> 0 | T17: ='3. Opex'!U12 -> 0 | V17: ='3. Opex'!F36 -> 0 | W17: ='3. Opex'!G36 -> 0 | X17: ='3. Opex'!H36 -> 0 | Y17: ='3. Opex'!M36 -> 0 | Z17: ='3. Opex'!R36 -> 0 | AA17: ='3. Opex'!S36 -> 0 | AB17: ='3. Opex'!T36 -> 0 | AC17: ='3. Opex'!U36 -> 0 | AE17: ='3. Opex'!F60 -> 0 | AF17: ='3. Opex'!G60 -> 0 | AG17: ='3. Opex'!H60 -> 0 | AH17: ='3. Opex'!M60 -> 0 | AI17: ='3. Opex'!R60 -> 0 | AJ17: ='3. Opex'!S60 -> 0 | AK17: ='3. Opex'!T60 -> 0 | AL17: ='3. Opex'!U60 -> 0 | AN17: ='3. Opex'!F84 -> 0 | AO17: ='3. Opex'!G84 -> 0 | AP17: ='3. Opex'!H84 -> 0 | AQ17: ='3. Opex'!M84 -> 0 | AR17: ='3. Opex'!R84 -> 0 | AS17: ='3. Opex'!S84 -> 0 | AT17: ='3. Opex'!T84 -> 0 | AU17: ='3. Opex'!U84 -> 0 | AW17: ='3. Opex'!F108 -> 0 | AX17: ='3. Opex'!G108 -> 0 | AY17: ='3. Opex'!H108 -> 0 | AZ17: ='3. Opex'!M108 -> 0 | BA17: ='3. Opex'!R108 -> 0 | BB17: ='3. Opex'!S108 -> 0 | BC17: ='3. Opex'!T108 -> 0 | BD17: ='3. Opex'!U108 -> 0
B18: S&M | C18: (000) | D18: =SUM('3. Opex'!F133:F134) -> 0 | E18: =SUM('3. Opex'!G133:G134) -> 0 | F18: =SUM('3. Opex'!H133:H134) -> 0 | G18: =SUM('3. Opex'!M133:M134) -> 0 | H18: =SUM('3. Opex'!R133:R134) -> 0 | I18: =SUM('3. Opex'!S133:S134) -> 0 | J18: =SUM('3. Opex'!T133:T134) -> 0 | K18: =SUM('3. Opex'!U133:U134) -> 0 | M18: =SUM('3. Opex'!F13:F14) -> 0 | N18: =SUM('3. Opex'!G13:G14) -> 0 | O18: =SUM('3. Opex'!H13:H14) -> 0 | P18: =SUM('3. Opex'!M13:M14) -> 0 | Q18: =SUM('3. Opex'!R13:R14) -> 0 | R18: =SUM('3. Opex'!S13:S14) -> 0 | S18: =SUM('3. Opex'!T13:T14) -> 0 | T18: =SUM('3. Opex'!U13:U14) -> 0 | V18: =SUM('3. Opex'!F37:F38) -> 0 | W18: =SUM('3. Opex'!G37:G38) -> 0 | X18: =SUM('3. Opex'!H37:H38) -> 0 | Y18: =SUM('3. Opex'!M37:M38) -> 0 | Z18: =SUM('3. Opex'!R37:R38) -> 0 | AA18: =SUM('3. Opex'!S37:S38) -> 0 | AB18: =SUM('3. Opex'!T37:T38) -> 0 | AC18: =SUM('3. Opex'!U37:U38) -> 0 | AE18: =SUM('3. Opex'!F61:F62) -> 0 | AF18: =SUM('3. Opex'!G61:G62) -> 0 | AG18: =SUM('3. Opex'!H61:H62) -> 0 | AH18: =SUM('3. Opex'!M61:M62) -> 0 | AI18: =SUM('3. Opex'!R61:R62) -> 0 | AJ18: =SUM('3. Opex'!S61:S62) -> 0 | AK18: =SUM('3. Opex'!T61:T62) -> 0 | AL18: =SUM('3. Opex'!U61:U62) -> 0 | AN18: =SUM('3. Opex'!F85:F86) -> 0 | AO18: =SUM('3. Opex'!G85:G86) -> 0 | AP18: =SUM('3. Opex'!H85:H86) -> 0 | AQ18: =SUM('3. Opex'!M85:M86) -> 0 | AR18: =SUM('3. Opex'!R85:R86) -> 0 | AS18: =SUM('3. Opex'!S85:S86) -> 0 | AT18: =SUM('3. Opex'!T85:T86) -> 0 | AU18: =SUM('3. Opex'!U85:U86) -> 0 | AW18: =SUM('3. Opex'!F109:F110) -> 0 | AX18: =SUM('3. Opex'!G109:G110) -> 0 | AY18: =SUM('3. Opex'!H109:H110) -> 0 | AZ18: =SUM('3. Opex'!M109:M110) -> 0 | BA18: =SUM('3. Opex'!R109:R110) -> 0 | BB18: =SUM('3. Opex'!S109:S110) -> 0 | BC18: =SUM('3. Opex'!T109:T110) -> 0 | BD18: =SUM('3. Opex'!U109:U110) -> 0
B19: G&A | C19: (000) | D19: =SUM('3. Opex'!F135:F139) -> 0 | E19: =SUM('3. Opex'!G135:G139) -> 0 | F19: =SUM('3. Opex'!H135:H139) -> 0 | G19: =SUM('3. Opex'!M135:M139) -> 0 | H19: =SUM('3. Opex'!R135:R139) -> 0 | I19: =SUM('3. Opex'!S135:S139) -> 0 | J19: =SUM('3. Opex'!T135:T139) -> 0 | K19: =SUM('3. Opex'!U135:U139) -> 0 | M19: =SUM('3. Opex'!F15:F19) -> 0 | N19: =SUM('3. Opex'!G15:G19) -> 0 | O19: =SUM('3. Opex'!H15:H19) -> 0 | P19: =SUM('3. Opex'!M15:M19) -> 0 | Q19: =SUM('3. Opex'!R15:R19) -> 0 | R19: =SUM('3. Opex'!S15:S19) -> 0 | S19: =SUM('3. Opex'!T15:T19) -> 0 | T19: =SUM('3. Opex'!U15:U19) -> 0 | V19: =SUM('3. Opex'!F39:F43) -> 0 | W19: =SUM('3. Opex'!G39:G43) -> 0 | X19: =SUM('3. Opex'!H39:H43) -> 0 | Y19: =SUM('3. Opex'!M39:M43) -> 0 | Z19: =SUM('3. Opex'!R39:R43) -> 0 | AA19: =SUM('3. Opex'!S39:S43) -> 0 | AB19: =SUM('3. Opex'!T39:T43) -> 0 | AC19: =SUM('3. Opex'!U39:U43) -> 0 | AE19: =SUM('3. Opex'!F63:F67) -> 0 | AF19: =SUM('3. Opex'!G63:G67) -> 0 | AG19: =SUM('3. Opex'!H63:H67) -> 0 | AH19: =SUM('3. Opex'!M63:M67) -> 0 | AI19: =SUM('3. Opex'!R63:R67) -> 0 | AJ19: =SUM('3. Opex'!S63:S67) -> 0 | AK19: =SUM('3. Opex'!T63:T67) -> 0 | AL19: =SUM('3. Opex'!U63:U67) -> 0 | AN19: =SUM('3. Opex'!F87:F91) -> 0 | AO19: =SUM('3. Opex'!G87:G91) -> 0 | AP19: =SUM('3. Opex'!H87:H91) -> 0 | AQ19: =SUM('3. Opex'!M87:M91) -> 0 | AR19: =SUM('3. Opex'!R87:R91) -> 0 | AS19: =SUM('3. Opex'!S87:S91) -> 0 | AT19: =SUM('3. Opex'!T87:T91) -> 0 | AU19: =SUM('3. Opex'!U87:U91) -> 0 | AW19: =SUM('3. Opex'!F111:F115) -> 0 | AX19: =SUM('3. Opex'!G111:G115) -> 0 | AY19: =SUM('3. Opex'!H111:H115) -> 0 | AZ19: =SUM('3. Opex'!M111:M115) -> 0 | BA19: =SUM('3. Opex'!R111:R115) -> 0 | BB19: =SUM('3. Opex'!S111:S115) -> 0 | BC19: =SUM('3. Opex'!T111:T115) -> 0 | BD19: =SUM('3. Opex'!U111:U115) -> 0
B20: All Other Period Expenses | C20: (000) | D20: =SUM('3. Opex'!F140:F142) -> 0 | E20: =SUM('3. Opex'!G140:G142) -> 0 | F20: =SUM('3. Opex'!H140:H142) -> 0 | G20: =SUM('3. Opex'!M140:M142) -> 0 | H20: =SUM('3. Opex'!R140:R142) -> 0 | I20: =SUM('3. Opex'!S140:S142) -> 0 | J20: =SUM('3. Opex'!T140:T142) -> 0 | K20: =SUM('3. Opex'!U140:U142) -> 0 | M20: =SUM('3. Opex'!F20:F22) -> 0 | N20: =SUM('3. Opex'!G20:G22) -> 0 | O20: =SUM('3. Opex'!H20:H22) -> 0 | P20: =SUM('3. Opex'!M20:M22) -> 0 | Q20: =SUM('3. Opex'!R20:R22) -> 0 | R20: =SUM('3. Opex'!S20:S22) -> 0 | S20: =SUM('3. Opex'!T20:T22) -> 0 | T20: =SUM('3. Opex'!U20:U22) -> 0 | V20: =SUM('3. Opex'!F44:F46) -> 0 | W20: =SUM('3. Opex'!G44:G46) -> 0 | X20: =SUM('3. Opex'!H44:H46) -> 0 | Y20: =SUM('3. Opex'!M44:M46) -> 0 | Z20: =SUM('3. Opex'!R44:R46) -> 0 | AA20: =SUM('3. Opex'!S44:S46) -> 0 | AB20: =SUM('3. Opex'!T44:T46) -> 0 | AC20: =SUM('3. Opex'!U44:U46) -> 0 | AE20: =SUM('3. Opex'!F68:F70) -> 0 | AF20: =SUM('3. Opex'!G68:G70) -> 0 | AG20: =SUM('3. Opex'!H68:H70) -> 0 | AH20: =SUM('3. Opex'!M68:M70) -> 0 | AI20: =SUM('3. Opex'!R68:R70) -> 0 | AJ20: =SUM('3. Opex'!S68:S70) -> 0 | AK20: =SUM('3. Opex'!T68:T70) -> 0 | AL20: =SUM('3. Opex'!U68:U70) -> 0 | AN20: =SUM('3. Opex'!F92:F94) -> 0 | AO20: =SUM('3. Opex'!G92:G94) -> 0 | AP20: =SUM('3. Opex'!H92:H94) -> 0 | AQ20: =SUM('3. Opex'!M92:M94) -> 0 | AR20: =SUM('3. Opex'!R92:R94) -> 0 | AS20: =SUM('3. Opex'!S92:S94) -> 0 | AT20: =SUM('3. Opex'!T92:T94) -> 0 | AU20: =SUM('3. Opex'!U92:U94) -> 0 | AW20: =SUM('3. Opex'!F116:F118) -> 0 | AX20: =SUM('3. Opex'!G116:G118) -> 0 | AY20: =SUM('3. Opex'!H116:H118) -> 0 | AZ20: =SUM('3. Opex'!M116:M118) -> 0 | BA20: =SUM('3. Opex'!R116:R118) -> 0 | BB20: =SUM('3. Opex'!S116:S118) -> 0 | BC20: =SUM('3. Opex'!T116:T118) -> 0 | BD20: =SUM('3. Opex'!U116:U118) -> 0
B21: Total Period Expenses | C21: (000) | D21: =SUM(D17:D20) -> 0 | E21: =SUM(E17:E20) -> 0 | F21: =SUM(F17:F20) -> 0 | G21: =SUM(G17:G20) -> 0 | H21: =SUM(H17:H20) -> 0 | I21: =SUM(I17:I20) -> 0 | J21: =SUM(J17:J20) -> 0 | K21: =SUM(K17:K20) -> 0 | M21: =SUM(M17:M20) -> 0 | N21: =SUM(N17:N20) -> 0 | O21: =SUM(O17:O20) -> 0 | P21: =SUM(P17:P20) -> 0 | Q21: =SUM(Q17:Q20) -> 0 | R21: =SUM(R17:R20) -> 0 | S21: =SUM(S17:S20) -> 0 | T21: =SUM(T17:T20) -> 0 | V21: =SUM(V17:V20) -> 0 | W21: =SUM(W17:W20) -> 0 | X21: =SUM(X17:X20) -> 0 | Y21: =SUM(Y17:Y20) -> 0 | Z21: =SUM(Z17:Z20) -> 0 | AA21: =SUM(AA17:AA20) -> 0 | AB21: =SUM(AB17:AB20) -> 0 | AC21: =SUM(AC17:AC20) -> 0 | AE21: =SUM(AE17:AE20) -> 0 | AF21: =SUM(AF17:AF20) -> 0 | AG21: =SUM(AG17:AG20) -> 0 | AH21: =SUM(AH17:AH20) -> 0 | AI21: =SUM(AI17:AI20) -> 0 | AJ21: =SUM(AJ17:AJ20) -> 0 | AK21: =SUM(AK17:AK20) -> 0 | AL21: =SUM(AL17:AL20) -> 0 | AN21: =SUM(AN17:AN20) -> 0 | AO21: =SUM(AO17:AO20) -> 0 | AP21: =SUM(AP17:AP20) -> 0 | AQ21: =SUM(AQ17:AQ20) -> 0 | AR21: =SUM(AR17:AR20) -> 0 | AS21: =SUM(AS17:AS20) -> 0 | AT21: =SUM(AT17:AT20) -> 0 | AU21: =SUM(AU17:AU20) -> 0 | AW21: =SUM(AW17:AW20) -> 0 | AX21: =SUM(AX17:AX20) -> 0 | AY21: =SUM(AY17:AY20) -> 0 | AZ21: =SUM(AZ17:AZ20) -> 0 | BA21: =SUM(BA17:BA20) -> 0 | BB21: =SUM(BB17:BB20) -> 0 | BC21: =SUM(BC17:BC20) -> 0 | BD21: =SUM(BD17:BD20) -> 0
B22: Depreciation | C22: (000) | D22: ='4. Investments'!F429 -> 0 | E22: ='4. Investments'!G429 -> 0 | F22: ='4. Investments'!H429 -> 0 | G22: ='4. Investments'!M429 -> 0 | H22: ='4. Investments'!R429 -> 0 | I22: ='4. Investments'!S429 -> 0 | J22: ='4. Investments'!T429 -> 0 | K22: ='4. Investments'!U429 -> 0 | M22: ='4. Investments'!F44 -> 0 | N22: ='4. Investments'!G44 -> 0 | O22: ='4. Investments'!H44 -> 0 | P22: ='4. Investments'!M44 -> 0 | Q22: ='4. Investments'!R44 -> 0 | R22: ='4. Investments'!S44 -> 0 | S22: ='4. Investments'!T44 -> 0 | T22: ='4. Investments'!U44 -> 0 | V22: ='4. Investments'!F121 -> 0 | W22: ='4. Investments'!G121 -> 0 | X22: ='4. Investments'!H121 -> 0 | Y22: ='4. Investments'!M121 -> 0 | Z22: ='4. Investments'!R121 -> 0 | AA22: ='4. Investments'!S121 -> 0 | AB22: ='4. Investments'!T121 -> 0 | AC22: ='4. Investments'!U121 -> 0 | AE22: ='4. Investments'!F198 -> 0 | AF22: ='4. Investments'!G198 -> 0 | AG22: ='4. Investments'!H198 -> 0 | AH22: ='4. Investments'!M198 -> 0 | AI22: ='4. Investments'!R198 -> 0 | AJ22: ='4. Investments'!S198 -> 0 | AK22: ='4. Investments'!T198 -> 0 | AL22: ='4. Investments'!U198 -> 0 | AN22: ='4. Investments'!F275 -> 0 | AO22: ='4. Investments'!G275 -> 0 | AP22: ='4. Investments'!H275 -> 0 | AQ22: ='4. Investments'!M275 -> 0 | AR22: ='4. Investments'!R275 -> 0 | AS22: ='4. Investments'!S275 -> 0 | AT22: ='4. Investments'!T275 -> 0 | AU22: ='4. Investments'!U275 -> 0 | AW22: ='4. Investments'!F352 -> 0 | AX22: ='4. Investments'!G352 -> 0 | AY22: ='4. Investments'!H352 -> 0 | AZ22: ='4. Investments'!M352 -> 0 | BA22: ='4. Investments'!R352 -> 0 | BB22: ='4. Investments'!S352 -> 0 | BC22: ='4. Investments'!T352 -> 0 | BD22: ='4. Investments'!U352 -> 0
B24: Operating Profit | C24: (000) | D24: =D14-D21-D22 -> 0 | E24: =E14-E21-E22 -> 0 | F24: =F14-F21-F22 -> 0 | G24: =G14-G21-G22 -> 0 | H24: =H14-H21-H22 -> 0 | I24: =I14-I21-I22 -> 0 | J24: =J14-J21-J22 -> 0 | K24: =K14-K21-K22 -> 0 | M24: =M14-M21-M22 -> 0 | N24: =N14-N21-N22 -> 0 | O24: =O14-O21-O22 -> 0 | P24: =P14-P21-P22 -> 0 | Q24: =Q14-Q21-Q22 -> 0 | R24: =R14-R21-R22 -> 0 | S24: =S14-S21-S22 -> 0 | T24: =T14-T21-T22 -> 0 | V24: =V14-V21-V22 -> 0 | W24: =W14-W21-W22 -> 0 | X24: =X14-X21-X22 -> 0 | Y24: =Y14-Y21-Y22 -> 0 | Z24: =Z14-Z21-Z22 -> 0 | AA24: =AA14-AA21-AA22 -> 0 | AB24: =AB14-AB21-AB22 -> 0 | AC24: =AC14-AC21-AC22 -> 0 | AE24: =AE14-AE21-AE22 -> 0 | AF24: =AF14-AF21-AF22 -> 0 | AG24: =AG14-AG21-AG22 -> 0 | AH24: =AH14-AH21-AH22 -> 0 | AI24: =AI14-AI21-AI22 -> 0 | AJ24: =AJ14-AJ21-AJ22 -> 0 | AK24: =AK14-AK21-AK22 -> 0 | AL24: =AL14-AL21-AL22 -> 0 | AN24: =AN14-AN21-AN22 -> 0 | AO24: =AO14-AO21-AO22 -> 0 | AP24: =AP14-AP21-AP22 -> 0 | AQ24: =AQ14-AQ21-AQ22 -> 0 | AR24: =AR14-AR21-AR22 -> 0 | AS24: =AS14-AS21-AS22 -> 0 | AT24: =AT14-AT21-AT22 -> 0 | AU24: =AU14-AU21-AU22 -> 0 | AW24: =AW14-AW21-AW22 -> 0 | AX24: =AX14-AX21-AX22 -> 0 | AY24: =AY14-AY21-AY22 -> 0 | AZ24: =AZ14-AZ21-AZ22 -> 0 | BA24: =BA14-BA21-BA22 -> 0 | BB24: =BB14-BB21-BB22 -> 0 | BC24: =BC14-BC21-BC22 -> 0 | BD24: =BD14-BD21-BD22 -> 0
B25: OP% | D25: =IFERROR(D24/D$6,0) -> 0 | E25: =IFERROR(E24/E$6,0) -> 0 | F25: =IFERROR(F24/F$6,0) -> 0 | G25: =IFERROR(G24/G$6,0) -> 0 | H25: =IFERROR(H24/H$6,0) -> 0 | I25: =IFERROR(I24/I$6,0) -> 0 | J25: =IFERROR(J24/J$6,0) -> 0 | K25: =IFERROR(K24/K$6,0) -> 0 | M25: =IFERROR(M24/M$6,0) -> 0 | N25: =IFERROR(N24/N$6,0) -> 0 | O25: =IFERROR(O24/O$6,0) -> 0 | P25: =IFERROR(P24/P$6,0) -> 0 | Q25: =IFERROR(Q24/Q$6,0) -> 0 | R25: =IFERROR(R24/R$6,0) -> 0 | S25: =IFERROR(S24/S$6,0) -> 0 | T25: =IFERROR(T24/T$6,0) -> 0 | V25: =IFERROR(V24/V$6,0) -> 0 | W25: =IFERROR(W24/W$6,0) -> 0 | X25: =IFERROR(X24/X$6,0) -> 0 | Y25: =IFERROR(Y24/Y$6,0) -> 0 | Z25: =IFERROR(Z24/Z$6,0) -> 0 | AA25: =IFERROR(AA24/AA$6,0) -> 0 | AB25: =IFERROR(AB24/AB$6,0) -> 0 | AC25: =IFERROR(AC24/AC$6,0) -> 0 | AE25: =IFERROR(AE24/AE$6,0) -> 0 | AF25: =IFERROR(AF24/AF$6,0) -> 0 | AG25: =IFERROR(AG24/AG$6,0) -> 0 | AH25: =IFERROR(AH24/AH$6,0) -> 0 | AI25: =IFERROR(AI24/AI$6,0) -> 0 | AJ25: =IFERROR(AJ24/AJ$6,0) -> 0 | AK25: =IFERROR(AK24/AK$6,0) -> 0 | AL25: =IFERROR(AL24/AL$6,0) -> 0 | AN25: =IFERROR(AN24/AN$6,0) -> 0 | AO25: =IFERROR(AO24/AO$6,0) -> 0 | AP25: =IFERROR(AP24/AP$6,0) -> 0 | AQ25: =IFERROR(AQ24/AQ$6,0) -> 0 | AR25: =IFERROR(AR24/AR$6,0) -> 0 | AS25: =IFERROR(AS24/AS$6,0) -> 0 | AT25: =IFERROR(AT24/AT$6,0) -> 0 | AU25: =IFERROR(AU24/AU$6,0) -> 0 | AW25: =IFERROR(AW24/AW$6,0) -> 0 | AX25: =IFERROR(AX24/AX$6,0) -> 0 | AY25: =IFERROR(AY24/AY$6,0) -> 0 | AZ25: =IFERROR(AZ24/AZ$6,0) -> 0 | BA25: =IFERROR(BA24/BA$6,0) -> 0 | BB25: =IFERROR(BB24/BB$6,0) -> 0 | BC25: =IFERROR(BC24/BC$6,0) -> 0 | BD25: =IFERROR(BD24/BD$6,0) -> 0
B27: Non-Operating Expenses (Income) | C27: (000) | D27: =SUM('7. Non-Opex'!F232,'7. Non-Opex'!F251) -> 0 | E27: =SUM('7. Non-Opex'!G232,'7. Non-Opex'!G251) -> 0 | F27: =SUM('7. Non-Opex'!H232,'7. Non-Opex'!H251) -> 0 | G27: =SUM('7. Non-Opex'!M232,'7. Non-Opex'!M251) -> 0 | H27: =SUM('7. Non-Opex'!R232,'7. Non-Opex'!R251) -> 0 | I27: =SUM('7. Non-Opex'!S232,'7. Non-Opex'!S251) -> 0 | J27: =SUM('7. Non-Opex'!T232,'7. Non-Opex'!T251) -> 0 | K27: =SUM('7. Non-Opex'!U232,'7. Non-Opex'!U251) -> 0 | M27: =SUM('7. Non-Opex'!F22,'7. Non-Opex'!F41) -> 0 | N27: =SUM('7. Non-Opex'!G22,'7. Non-Opex'!G41) -> 0 | O27: =SUM('7. Non-Opex'!H22,'7. Non-Opex'!H41) -> 0 | P27: =SUM('7. Non-Opex'!M22,'7. Non-Opex'!M41) -> 0 | Q27: =SUM('7. Non-Opex'!R22,'7. Non-Opex'!R41) -> 0 | R27: =SUM('7. Non-Opex'!S22,'7. Non-Opex'!S41) -> 0 | S27: =SUM('7. Non-Opex'!T22,'7. Non-Opex'!T41) -> 0 | T27: =SUM('7. Non-Opex'!U22,'7. Non-Opex'!U41) -> 0 | V27: =SUM('7. Non-Opex'!F64,'7. Non-Opex'!F83) -> 0 | W27: =SUM('7. Non-Opex'!G64,'7. Non-Opex'!G83) -> 0 | X27: =SUM('7. Non-Opex'!H64,'7. Non-Opex'!H83) -> 0 | Y27: =SUM('7. Non-Opex'!M64,'7. Non-Opex'!M83) -> 0 | Z27: =SUM('7. Non-Opex'!R64,'7. Non-Opex'!R83) -> 0 | AA27: =SUM('7. Non-Opex'!S64,'7. Non-Opex'!S83) -> 0 | AB27: =SUM('7. Non-Opex'!T64,'7. Non-Opex'!T83) -> 0 | AC27: =SUM('7. Non-Opex'!U64,'7. Non-Opex'!U83) -> 0 | AE27: =SUM('7. Non-Opex'!F106,'7. Non-Opex'!F125) -> 0 | AF27: =SUM('7. Non-Opex'!G106,'7. Non-Opex'!G125) -> 0 | AG27: =SUM('7. Non-Opex'!H106,'7. Non-Opex'!H125) -> 0 | AH27: =SUM('7. Non-Opex'!M106,'7. Non-Opex'!M125) -> 0 | AI27: =SUM('7. Non-Opex'!R106,'7. Non-Opex'!R125) -> 0 | AJ27: =SUM('7. Non-Opex'!S106,'7. Non-Opex'!S125) -> 0 | AK27: =SUM('7. Non-Opex'!T106,'7. Non-Opex'!T125) -> 0 | AL27: =SUM('7. Non-Opex'!U106,'7. Non-Opex'!U125) -> 0 | AN27: =SUM('7. Non-Opex'!F148,'7. Non-Opex'!F167) -> 0 | AO27: =SUM('7. Non-Opex'!G148,'7. Non-Opex'!G167) -> 0 | AP27: =SUM('7. Non-Opex'!H148,'7. Non-Opex'!H167) -> 0 | AQ27: =SUM('7. Non-Opex'!M148,'7. Non-Opex'!M167) -> 0 | AR27: =SUM('7. Non-Opex'!R148,'7. Non-Opex'!R167) -> 0 | AS27: =SUM('7. Non-Opex'!S148,'7. Non-Opex'!S167) -> 0 | AT27: =SUM('7. Non-Opex'!T148,'7. Non-Opex'!T167) -> 0 | AU27: =SUM('7. Non-Opex'!U148,'7. Non-Opex'!U167) -> 0 | AW27: =SUM('7. Non-Opex'!F190,'7. Non-Opex'!F209) -> 0 | AX27: =SUM('7. Non-Opex'!G190,'7. Non-Opex'!G209) -> 0 | AY27: =SUM('7. Non-Opex'!H190,'7. Non-Opex'!H209) -> 0 | AZ27: =SUM('7. Non-Opex'!M190,'7. Non-Opex'!M209) -> 0 | BA27: =SUM('7. Non-Opex'!R190,'7. Non-Opex'!R209) -> 0 | BB27: =SUM('7. Non-Opex'!S190,'7. Non-Opex'!S209) -> 0 | BC27: =SUM('7. Non-Opex'!T190,'7. Non-Opex'!T209) -> 0 | BD27: =SUM('7. Non-Opex'!U190,'7. Non-Opex'!U209) -> 0
B28: Investment Expenses | C28: (000) | D28: ='4. Investments'!F404 -> 0 | E28: ='4. Investments'!G404 -> 0 | F28: ='4. Investments'!H404 -> 0 | G28: ='4. Investments'!M404 -> 0 | H28: ='4. Investments'!R404 -> 0 | I28: ='4. Investments'!S404 -> 0 | J28: ='4. Investments'!T404 -> 0 | K28: ='4. Investments'!U404 -> 0 | M28: ='4. Investments'!F19 -> 0 | N28: ='4. Investments'!G19 -> 0 | O28: ='4. Investments'!H19 -> 0 | P28: ='4. Investments'!M19 -> 0 | Q28: ='4. Investments'!R19 -> 0 | R28: ='4. Investments'!S19 -> 0 | S28: ='4. Investments'!T19 -> 0 | T28: ='4. Investments'!U19 -> 0 | V28: ='4. Investments'!F96 -> 0 | W28: ='4. Investments'!G96 -> 0 | X28: ='4. Investments'!H96 -> 0 | Y28: ='4. Investments'!M96 -> 0 | Z28: ='4. Investments'!R96 -> 0 | AA28: ='4. Investments'!S96 -> 0 | AB28: ='4. Investments'!T96 -> 0 | AC28: ='4. Investments'!U96 -> 0 | AE28: ='4. Investments'!F173 -> 0 | AF28: ='4. Investments'!G173 -> 0 | AG28: ='4. Investments'!H173 -> 0 | AH28: ='4. Investments'!M173 -> 0 | AI28: ='4. Investments'!R173 -> 0 | AJ28: ='4. Investments'!S173 -> 0 | AK28: ='4. Investments'!T173 -> 0 | AL28: ='4. Investments'!U173 -> 0 | AN28: ='4. Investments'!F250 -> 0 | AO28: ='4. Investments'!G250 -> 0 | AP28: ='4. Investments'!H250 -> 0 | AQ28: ='4. Investments'!M250 -> 0 | AR28: ='4. Investments'!R250 -> 0 | AS28: ='4. Investments'!S250 -> 0 | AT28: ='4. Investments'!T250 -> 0 | AU28: ='4. Investments'!U250 -> 0 | AW28: ='4. Investments'!F327 -> 0 | AX28: ='4. Investments'!G327 -> 0 | AY28: ='4. Investments'!H327 -> 0 | AZ28: ='4. Investments'!M327 -> 0 | BA28: ='4. Investments'!R327 -> 0 | BB28: ='4. Investments'!S327 -> 0 | BC28: ='4. Investments'!T327 -> 0 | BD28: ='4. Investments'!U327 -> 0
B29: Restructuring | C29: (000) | D29: ='4. Investments'!F461 -> 0 | E29: ='4. Investments'!G461 -> 0 | F29: ='4. Investments'!H461 -> 0 | G29: ='4. Investments'!M461 -> 0 | H29: ='4. Investments'!R461 -> 0 | I29: ='4. Investments'!S461 -> 0 | J29: ='4. Investments'!T461 -> 0 | K29: ='4. Investments'!U461 -> 0 | M29: ='4. Investments'!F76 -> 0 | N29: ='4. Investments'!G76 -> 0 | O29: ='4. Investments'!H76 -> 0 | P29: ='4. Investments'!M76 -> 0 | Q29: ='4. Investments'!R76 -> 0 | R29: ='4. Investments'!S76 -> 0 | S29: ='4. Investments'!T76 -> 0 | T29: ='4. Investments'!U76 -> 0 | V29: ='4. Investments'!F153 -> 0 | W29: ='4. Investments'!G153 -> 0 | X29: ='4. Investments'!H153 -> 0 | Y29: ='4. Investments'!M153 -> 0 | Z29: ='4. Investments'!R153 -> 0 | AA29: ='4. Investments'!S153 -> 0 | AB29: ='4. Investments'!T153 -> 0 | AC29: ='4. Investments'!U153 -> 0 | AE29: ='4. Investments'!F230 -> 0 | AF29: ='4. Investments'!G230 -> 0 | AG29: ='4. Investments'!H230 -> 0 | AH29: ='4. Investments'!M230 -> 0 | AI29: ='4. Investments'!R230 -> 0 | AJ29: ='4. Investments'!S230 -> 0 | AK29: ='4. Investments'!T230 -> 0 | AL29: ='4. Investments'!U230 -> 0 | AN29: ='4. Investments'!F307 -> 0 | AO29: ='4. Investments'!G307 -> 0 | AP29: ='4. Investments'!H307 -> 0 | AQ29: ='4. Investments'!M307 -> 0 | AR29: ='4. Investments'!R307 -> 0 | AS29: ='4. Investments'!S307 -> 0 | AT29: ='4. Investments'!T307 -> 0 | AU29: ='4. Investments'!U307 -> 0 | AW29: ='4. Investments'!F384 -> 0 | AX29: ='4. Investments'!G384 -> 0 | AY29: ='4. Investments'!H384 -> 0 | AZ29: ='4. Investments'!M384 -> 0 | BA29: ='4. Investments'!R384 -> 0 | BB29: ='4. Investments'!S384 -> 0 | BC29: ='4. Investments'!T384 -> 0 | BD29: ='4. Investments'!U384 -> 0
B30: Taxes | C30: (000) | D30: ='6. Tax'!F137 -> 0 | E30: ='6. Tax'!G137 -> 0 | F30: ='6. Tax'!H137 -> 0 | G30: ='6. Tax'!M137 -> 0 | H30: ='6. Tax'!R137 -> 0 | I30: ='6. Tax'!S137 -> 0 | J30: ='6. Tax'!T137 -> 0 | K30: ='6. Tax'!U137 -> 0 | M30: ='6. Tax'!F22 -> 0 | N30: ='6. Tax'!G22 -> 0 | O30: ='6. Tax'!H22 -> 0 | P30: ='6. Tax'!M22 -> 0 | Q30: ='6. Tax'!R22 -> 0 | R30: ='6. Tax'!S22 -> 0 | S30: ='6. Tax'!T22 -> 0 | T30: ='6. Tax'!U22 -> 0 | V30: ='6. Tax'!F45 -> 0 | W30: ='6. Tax'!G45 -> 0 | X30: ='6. Tax'!H45 -> 0 | Y30: ='6. Tax'!M45 -> 0 | Z30: ='6. Tax'!R45 -> 0 | AA30: ='6. Tax'!S45 -> 0 | AB30: ='6. Tax'!T45 -> 0 | AC30: ='6. Tax'!U45 -> 0 | AE30: ='6. Tax'!F68 -> 0 | AF30: ='6. Tax'!G68 -> 0 | AG30: ='6. Tax'!H68 -> 0 | AH30: ='6. Tax'!M68 -> 0 | AI30: ='6. Tax'!R68 -> 0 | AJ30: ='6. Tax'!S68 -> 0 | AK30: ='6. Tax'!T68 -> 0 | AL30: ='6. Tax'!U68 -> 0 | AN30: ='6. Tax'!F91 -> 0 | AO30: ='6. Tax'!G91 -> 0 | AP30: ='6. Tax'!H91 -> 0 | AQ30: ='6. Tax'!M91 -> 0 | AR30: ='6. Tax'!R91 -> 0 | AS30: ='6. Tax'!S91 -> 0 | AT30: ='6. Tax'!T91 -> 0 | AU30: ='6. Tax'!U91 -> 0 | AW30: ='6. Tax'!F114 -> 0 | AX30: ='6. Tax'!G114 -> 0 | AY30: ='6. Tax'!H114 -> 0 | AZ30: ='6. Tax'!M114 -> 0 | BA30: ='6. Tax'!R114 -> 0 | BB30: ='6. Tax'!S114 -> 0 | BC30: ='6. Tax'!T114 -> 0 | BD30: ='6. Tax'!U114 -> 0
B32: Net Income | C32: (000) | D32: =D24-SUM(D27:D30) -> 0 | E32: =E24-SUM(E27:E30) -> 0 | F32: =F24-SUM(F27:F30) -> 0 | G32: =G24-SUM(G27:G30) -> 0 | H32: =H24-SUM(H27:H30) -> 0 | I32: =I24-SUM(I27:I30) -> 0 | J32: =J24-SUM(J27:J30) -> 0 | K32: =K24-SUM(K27:K30) -> 0 | M32: =M24-SUM(M27:M30) -> 0 | N32: =N24-SUM(N27:N30) -> 0 | O32: =O24-SUM(O27:O30) -> 0 | P32: =P24-SUM(P27:P30) -> 0 | Q32: =Q24-SUM(Q27:Q30) -> 0 | R32: =R24-SUM(R27:R30) -> 0 | S32: =S24-SUM(S27:S30) -> 0 | T32: =T24-SUM(T27:T30) -> 0 | V32: =V24-SUM(V27:V30) -> 0 | W32: =W24-SUM(W27:W30) -> 0 | X32: =X24-SUM(X27:X30) -> 0 | Y32: =Y24-SUM(Y27:Y30) -> 0 | Z32: =Z24-SUM(Z27:Z30) -> 0 | AA32: =AA24-SUM(AA27:AA30) -> 0 | AB32: =AB24-SUM(AB27:AB30) -> 0 | AC32: =AC24-SUM(AC27:AC30) -> 0 | AE32: =AE24-SUM(AE27:AE30) -> 0 | AF32: =AF24-SUM(AF27:AF30) -> 0 | AG32: =AG24-SUM(AG27:AG30) -> 0 | AH32: =AH24-SUM(AH27:AH30) -> 0 | AI32: =AI24-SUM(AI27:AI30) -> 0 | AJ32: =AJ24-SUM(AJ27:AJ30) -> 0 | AK32: =AK24-SUM(AK27:AK30) -> 0 | AL32: =AL24-SUM(AL27:AL30) -> 0 | AN32: =AN24-SUM(AN27:AN30) -> 0 | AO32: =AO24-SUM(AO27:AO30) -> 0 | AP32: =AP24-SUM(AP27:AP30) -> 0 | AQ32: =AQ24-SUM(AQ27:AQ30) -> 0 | AR32: =AR24-SUM(AR27:AR30) -> 0 | AS32: =AS24-SUM(AS27:AS30) -> 0 | AT32: =AT24-SUM(AT27:AT30) -> 0 | AU32: =AU24-SUM(AU27:AU30) -> 0 | AW32: =AW24-SUM(AW27:AW30) -> 0 | AX32: =AX24-SUM(AX27:AX30) -> 0 | AY32: =AY24-SUM(AY27:AY30) -> 0 | AZ32: =AZ24-SUM(AZ27:AZ30) -> 0 | BA32: =BA24-SUM(BA27:BA30) -> 0 | BB32: =BB24-SUM(BB27:BB30) -> 0 | BC32: =BC24-SUM(BC27:BC30) -> 0 | BD32: =BD24-SUM(BD27:BD30) -> 0
D33: =IFERROR(D32/D$6,0) -> 0 | E33: =IFERROR(E32/E$6,0) -> 0 | F33: =IFERROR(F32/F$6,0) -> 0 | G33: =IFERROR(G32/G$6,0) -> 0 | H33: =IFERROR(H32/H$6,0) -> 0 | I33: =IFERROR(I32/I$6,0) -> 0 | J33: =IFERROR(J32/J$6,0) -> 0 | K33: =IFERROR(K32/K$6,0) -> 0 | M33: =IFERROR(M32/M$6,0) -> 0 | N33: =IFERROR(N32/N$6,0) -> 0 | O33: =IFERROR(O32/O$6,0) -> 0 | P33: =IFERROR(P32/P$6,0) -> 0 | Q33: =IFERROR(Q32/Q$6,0) -> 0 | R33: =IFERROR(R32/R$6,0) -> 0 | S33: =IFERROR(S32/S$6,0) -> 0 | T33: =IFERROR(T32/T$6,0) -> 0 | V33: =IFERROR(V32/V$6,0) -> 0 | W33: =IFERROR(W32/W$6,0) -> 0 | X33: =IFERROR(X32/X$6,0) -> 0 | Y33: =IFERROR(Y32/Y$6,0) -> 0 | Z33: =IFERROR(Z32/Z$6,0) -> 0 | AA33: =IFERROR(AA32/AA$6,0) -> 0 | AB33: =IFERROR(AB32/AB$6,0) -> 0 | AC33: =IFERROR(AC32/AC$6,0) -> 0 | AE33: =IFERROR(AE32/AE$6,0) -> 0 | AF33: =IFERROR(AF32/AF$6,0) -> 0 | AG33: =IFERROR(AG32/AG$6,0) -> 0 | AH33: =IFERROR(AH32/AH$6,0) -> 0 | AI33: =IFERROR(AI32/AI$6,0) -> 0 | AJ33: =IFERROR(AJ32/AJ$6,0) -> 0 | AK33: =IFERROR(AK32/AK$6,0) -> 0 | AL33: =IFERROR(AL32/AL$6,0) -> 0 | AN33: =IFERROR(AN32/AN$6,0) -> 0 | AO33: =IFERROR(AO32/AO$6,0) -> 0 | AP33: =IFERROR(AP32/AP$6,0) -> 0 | AQ33: =IFERROR(AQ32/AQ$6,0) -> 0 | AR33: =IFERROR(AR32/AR$6,0) -> 0 | AS33: =IFERROR(AS32/AS$6,0) -> 0 | AT33: =IFERROR(AT32/AT$6,0) -> 0 | AU33: =IFERROR(AU32/AU$6,0) -> 0 | AW33: =IFERROR(AW32/AW$6,0) -> 0 | AX33: =IFERROR(AX32/AX$6,0) -> 0 | AY33: =IFERROR(AY32/AY$6,0) -> 0 | AZ33: =IFERROR(AZ32/AZ$6,0) -> 0 | BA33: =IFERROR(BA32/BA$6,0) -> 0 | BB33: =IFERROR(BB32/BB$6,0) -> 0 | BC33: =IFERROR(BC32/BC$6,0) -> 0 | BD33: =IFERROR(BD32/BD$6,0) -> 0
B35: Cash Flow Periodic | C35: (000) | D35: =(D22+D32)-SUM('4. Investments'!F420,'4. Investments'!F445)+D40 -> 0 | E35: =(E22+E32)-SUM('4. Investments'!G420,'4. Investments'!G445)+E40 -> 0 | F35: =(F22+F32)-SUM('4. Investments'!H420,'4. Investments'!H445)+F40 -> 0 | G35: =(G22+G32)-SUM('4. Investments'!M420,'4. Investments'!M445)+G40 -> 0 | H35: =(H22+H32)-SUM('4. Investments'!R420,'4. Investments'!R445)+H40 -> 0 | I35: =(I22+I32)-SUM('4. Investments'!S420,'4. Investments'!S445)+I40 -> 0 | J35: =(J22+J32)-SUM('4. Investments'!T420,'4. Investments'!T445)+J40 -> 0 | K35: =(K22+K32)-SUM('4. Investments'!U420,'4. Investments'!U445)+K40 -> 0 | M35: =(M22+M32)-SUM('4. Investments'!F35,'4. Investments'!F60)+M40 -> 0 | N35: =(N22+N32)-SUM('4. Investments'!G35,'4. Investments'!G60)+N40 -> 0 | O35: =(O22+O32)-SUM('4. Investments'!H35,'4. Investments'!H60)+O40 -> 0 | P35: =(P22+P32)-SUM('4. Investments'!M35,'4. Investments'!M60)+P40 -> 0 | Q35: =(Q22+Q32)-SUM('4. Investments'!R35,'4. Investments'!R60)+Q40 -> 0 | R35: =(R22+R32)-SUM('4. Investments'!S35,'4. Investments'!S60)+R40 -> 0 | S35: =(S22+S32)-SUM('4. Investments'!T35,'4. Investments'!T60)+S40 -> 0 | T35: =(T22+T32)-SUM('4. Investments'!U35,'4. Investments'!U60)+T40 -> 0 | V35: =(V22+V32)-SUM('4. Investments'!F112,'4. Investments'!F137)+V40 -> 0 | W35: =(W22+W32)-SUM('4. Investments'!G112,'4. Investments'!G137)+W40 -> 0 | X35: =(X22+X32)-SUM('4. Investments'!H112,'4. Investments'!H137)+X40 -> 0 | Y35: =(Y22+Y32)-SUM('4. Investments'!M112,'4. Investments'!M137)+Y40 -> 0 | Z35: =(Z22+Z32)-SUM('4. Investments'!R112,'4. Investments'!R137)+Z40 -> 0 | AA35: =(AA22+AA32)-SUM('4. Investments'!S112,'4. Investments'!S137)+AA40 -> 0 | AB35: =(AB22+AB32)-SUM('4. Investments'!T112,'4. Investments'!T137)+AB40 -> 0 | AC35: =(AC22+AC32)-SUM('4. Investments'!U112,'4. Investments'!U137)+AC40 -> 0 | AE35: =(AE22+AE32)-SUM('4. Investments'!F189,'4. Investments'!F214)+AE40 -> 0 | AF35: =(AF22+AF32)-SUM('4. Investments'!G189,'4. Investments'!G214)+AF40 -> 0 | AG35: =(AG22+AG32)-SUM('4. Investments'!H189,'4. Investments'!H214)+AG40 -> 0 | AH35: =(AH22+AH32)-SUM('4. Investments'!M189,'4. Investments'!M214)+AH40 -> 0 | AI35: =(AI22+AI32)-SUM('4. Investments'!R189,'4. Investments'!R214)+AI40 -> 0 | AJ35: =(AJ22+AJ32)-SUM('4. Investments'!S189,'4. Investments'!S214)+AJ40 -> 0 | AK35: =(AK22+AK32)-SUM('4. Investments'!T189,'4. Investments'!T214)+AK40 -> 0 | AL35: =(AL22+AL32)-SUM('4. Investments'!U189,'4. Investments'!U214)+AL40 -> 0 | AN35: =(AN22+AN32)-SUM('4. Investments'!F266,'4. Investments'!F291)+AN40 -> 0 | AO35: =(AO22+AO32)-SUM('4. Investments'!G266,'4. Investments'!G291)+AO40 -> 0 | AP35: =(AP22+AP32)-SUM('4. Investments'!H266,'4. Investments'!H291)+AP40 -> 0 | AQ35: =(AQ22+AQ32)-SUM('4. Investments'!M266,'4. Investments'!M291)+AQ40 -> 0 | AR35: =(AR22+AR32)-SUM('4. Investments'!R266,'4. Investments'!R291)+AR40 -> 0 | AS35: =(AS22+AS32)-SUM('4. Investments'!S266,'4. Investments'!S291)+AS40 -> 0 | AT35: =(AT22+AT32)-SUM('4. Investments'!T266,'4. Investments'!T291)+AT40 -> 0 | AU35: =(AU22+AU32)-SUM('4. Investments'!U266,'4. Investments'!U291)+AU40 -> 0 | AW35: =(AW22+AW32)-SUM('4. Investments'!F343,'4. Investments'!F368)+AW40 -> 0 | AX35: =(AX22+AX32)-SUM('4. Investments'!G343,'4. Investments'!G368)+AX40 -> 0 | AY35: =(AY22+AY32)-SUM('4. Investments'!H343,'4. Investments'!H368)+AY40 -> 0 | AZ35: =(AZ22+AZ32)-SUM('4. Investments'!M343,'4. Investments'!M368)+AZ40 -> 0 | BA35: =(BA22+BA32)-SUM('4. Investments'!R343,'4. Investments'!R368)+BA40 -> 0 | BB35: =(BB22+BB32)-SUM('4. Investments'!S343,'4. Investments'!S368)+BB40 -> 0 | BC35: =(BC22+BC32)-SUM('4. Investments'!T343,'4. Investments'!T368)+BC40 -> 0 | BD35: =(BD22+BD32)-SUM('4. Investments'!U343,'4. Investments'!U368)+BD40 -> 0
B36: Cash Flow Cumulative | C36: (000) | D36: =D35 -> 0 | E36: =E35+D36 -> 0 | F36: =F35+E36 -> 0 | G36: =G35+F36 -> 0 | H36: =H35+G36 -> 0 | I36: =I35+H36 -> 0 | J36: =J35+I36 -> 0 | K36: =K35+J36 -> 0 | M36: =M35 -> 0 | N36: =N35+M36 -> 0 | O36: =O35+N36 -> 0 | P36: =P35+O36 -> 0 | Q36: =Q35+P36 -> 0 | R36: =R35+Q36 -> 0 | S36: =S35+R36 -> 0 | T36: =T35+S36 -> 0 | V36: =V35 -> 0 | W36: =W35+V36 -> 0 | X36: =X35+W36 -> 0 | Y36: =Y35+X36 -> 0 | Z36: =Z35+Y36 -> 0 | AA36: =AA35+Z36 -> 0 | AB36: =AB35+AA36 -> 0 | AC36: =AC35+AB36 -> 0 | AE36: =AE35 -> 0 | AF36: =AF35+AE36 -> 0 | AG36: =AG35+AF36 -> 0 | AH36: =AH35+AG36 -> 0 | AI36: =AI35+AH36 -> 0 | AJ36: =AJ35+AI36 -> 0 | AK36: =AK35+AJ36 -> 0 | AL36: =AL35+AK36 -> 0 | AN36: =AN35 -> 0 | AO36: =AO35+AN36 -> 0 | AP36: =AP35+AO36 -> 0 | AQ36: =AQ35+AP36 -> 0 | AR36: =AR35+AQ36 -> 0 | AS36: =AS35+AR36 -> 0 | AT36: =AT35+AS36 -> 0 | AU36: =AU35+AT36 -> 0 | AW36: =AW35 -> 0 | AX36: =AX35+AW36 -> 0 | AY36: =AY35+AX36 -> 0 | AZ36: =AZ35+AY36 -> 0 | BA36: =BA35+AZ36 -> 0 | BB36: =BB35+BA36 -> 0 | BC36: =BC35+BB36 -> 0 | BD36: =BD35+BC36 -> 0
B39: Working Capital Balance | C39: (000) | D39: =SUM('5. Balance Sheet'!F422,'5. Balance Sheet'!F441)-SUM('5. Balance Sheet'!F460,'5. Balance Sheet'!F479) -> 0 | E39: =SUM('5. Balance Sheet'!G422,'5. Balance Sheet'!G441)-SUM('5. Balance Sheet'!G460,'5. Balance Sheet'!G479) -> 0 | F39: =SUM('5. Balance Sheet'!H422,'5. Balance Sheet'!H441)-SUM('5. Balance Sheet'!H460,'5. Balance Sheet'!H479) -> 0 | G39: =SUM('5. Balance Sheet'!M422,'5. Balance Sheet'!M441)-SUM('5. Balance Sheet'!M460,'5. Balance Sheet'!M479) -> 0 | H39: =SUM('5. Balance Sheet'!R422,'5. Balance Sheet'!R441)-SUM('5. Balance Sheet'!R460,'5. Balance Sheet'!R479) -> 0 | I39: =SUM('5. Balance Sheet'!S422,'5. Balance Sheet'!S441)-SUM('5. Balance Sheet'!S460,'5. Balance Sheet'!S479) -> 0 | J39: =SUM('5. Balance Sheet'!T422,'5. Balance Sheet'!T441)-SUM('5. Balance Sheet'!T460,'5. Balance Sheet'!T479) -> 0 | K39: =SUM('5. Balance Sheet'!U422,'5. Balance Sheet'!U441)-SUM('5. Balance Sheet'!U460,'5. Balance Sheet'!U479) -> 0 | M39: =SUM('5. Balance Sheet'!F22,'5. Balance Sheet'!F41)-SUM('5. Balance Sheet'!F60,'5. Balance Sheet'!F79) -> 0 | N39: =SUM('5. Balance Sheet'!G22,'5. Balance Sheet'!G41)-SUM('5. Balance Sheet'!G60,'5. Balance Sheet'!G79) -> 0 | O39: =SUM('5. Balance Sheet'!H22,'5. Balance Sheet'!H41)-SUM('5. Balance Sheet'!H60,'5. Balance Sheet'!H79) -> 0 | P39: =SUM('5. Balance Sheet'!M22,'5. Balance Sheet'!M41)-SUM('5. Balance Sheet'!M60,'5. Balance Sheet'!M79) -> 0 | Q39: =SUM('5. Balance Sheet'!R22,'5. Balance Sheet'!R41)-SUM('5. Balance Sheet'!R60,'5. Balance Sheet'!R79) -> 0 | R39: =SUM('5. Balance Sheet'!S22,'5. Balance Sheet'!S41)-SUM('5. Balance Sheet'!S60,'5. Balance Sheet'!S79) -> 0 | S39: =SUM('5. Balance Sheet'!T22,'5. Balance Sheet'!T41)-SUM('5. Balance Sheet'!T60,'5. Balance Sheet'!T79) -> 0 | T39: =SUM('5. Balance Sheet'!U22,'5. Balance Sheet'!U41)-SUM('5. Balance Sheet'!U60,'5. Balance Sheet'!U79) -> 0 | V39: =SUM('5. Balance Sheet'!F102,'5. Balance Sheet'!F121)-SUM('5. Balance Sheet'!F140,'5. Balance Sheet'!F159) -> 0 | W39: =SUM('5. Balance Sheet'!G102,'5. Balance Sheet'!G121)-SUM('5. Balance Sheet'!G140,'5. Balance Sheet'!G159) -> 0 | X39: =SUM('5. Balance Sheet'!H102,'5. Balance Sheet'!H121)-SUM('5. Balance Sheet'!H140,'5. Balance Sheet'!H159) -> 0 | Y39: =SUM('5. Balance Sheet'!M102,'5. Balance Sheet'!M121)-SUM('5. Balance Sheet'!M140,'5. Balance Sheet'!M159) -> 0 | Z39: =SUM('5. Balance Sheet'!R102,'5. Balance Sheet'!R121)-SUM('5. Balance Sheet'!R140,'5. Balance Sheet'!R159) -> 0 | AA39: =SUM('5. Balance Sheet'!S102,'5. Balance Sheet'!S121)-SUM('5. Balance Sheet'!S140,'5. Balance Sheet'!S159) -> 0 | AB39: =SUM('5. Balance Sheet'!T102,'5. Balance Sheet'!T121)-SUM('5. Balance Sheet'!T140,'5. Balance Sheet'!T159) -> 0 | AC39: =SUM('5. Balance Sheet'!U102,'5. Balance Sheet'!U121)-SUM('5. Balance Sheet'!U140,'5. Balance Sheet'!U159) -> 0 | AE39: =SUM('5. Balance Sheet'!F182,'5. Balance Sheet'!F201)-SUM('5. Balance Sheet'!F220,'5. Balance Sheet'!F239) -> 0 | AF39: =SUM('5. Balance Sheet'!G182,'5. Balance Sheet'!G201)-SUM('5. Balance Sheet'!G220,'5. Balance Sheet'!G239) -> 0 | AG39: =SUM('5. Balance Sheet'!H182,'5. Balance Sheet'!H201)-SUM('5. Balance Sheet'!H220,'5. Balance Sheet'!H239) -> 0 | AH39: =SUM('5. Balance Sheet'!M182,'5. Balance Sheet'!M201)-SUM('5. Balance Sheet'!M220,'5. Balance Sheet'!M239) -> 0 | AI39: =SUM('5. Balance Sheet'!R182,'5. Balance Sheet'!R201)-SUM('5. Balance Sheet'!R220,'5. Balance Sheet'!R239) -> 0 | AJ39: =SUM('5. Balance Sheet'!S182,'5. Balance Sheet'!S201)-SUM('5. Balance Sheet'!S220,'5. Balance Sheet'!S239) -> 0 | AK39: =SUM('5. Balance Sheet'!T182,'5. Balance Sheet'!T201)-SUM('5. Balance Sheet'!T220,'5. Balance Sheet'!T239) -> 0 | AL39: =SUM('5. Balance Sheet'!U182,'5. Balance Sheet'!U201)-SUM('5. Balance Sheet'!U220,'5. Balance Sheet'!U239) -> 0 | AN39: =SUM('5. Balance Sheet'!F262,'5. Balance Sheet'!F281)-SUM('5. Balance Sheet'!F300,'5. Balance Sheet'!F319) -> 0 | AO39: =SUM('5. Balance Sheet'!G262,'5. Balance Sheet'!G281)-SUM('5. Balance Sheet'!G300,'5. Balance Sheet'!G319) -> 0 | AP39: =SUM('5. Balance Sheet'!H262,'5. Balance Sheet'!H281)-SUM('5. Balance Sheet'!H300,'5. Balance Sheet'!H319) -> 0 | AQ39: =SUM('5. Balance Sheet'!M262,'5. Balance Sheet'!M281)-SUM('5. Balance Sheet'!M300,'5. Balance Sheet'!M319) -> 0 | AR39: =SUM('5. Balance Sheet'!R262,'5. Balance Sheet'!R281)-SUM('5. Balance Sheet'!R300,'5. Balance Sheet'!R319) -> 0 | AS39: =SUM('5. Balance Sheet'!S262,'5. Balance Sheet'!S281)-SUM('5. Balance Sheet'!S300,'5. Balance Sheet'!S319) -> 0 | AT39: =SUM('5. Balance Sheet'!T262,'5. Balance Sheet'!T281)-SUM('5. Balance Sheet'!T300,'5. Balance Sheet'!T319) -> 0 | AU39: =SUM('5. Balance Sheet'!U262,'5. Balance Sheet'!U281)-SUM('5. Balance Sheet'!U300,'5. Balance Sheet'!U319) -> 0 | AW39: =SUM('5. Balance Sheet'!F342,'5. Balance Sheet'!F361)-SUM('5. Balance Sheet'!F380,'5. Balance Sheet'!F399) -> 0 | AX39: =SUM('5. Balance Sheet'!G342,'5. Balance Sheet'!G361)-SUM('5. Balance Sheet'!G380,'5. Balance Sheet'!G399) -> 0 | AY39: =SUM('5. Balance Sheet'!H342,'5. Balance Sheet'!H361)-SUM('5. Balance Sheet'!H380,'5. Balance Sheet'!H399) -> 0 | AZ39: =SUM('5. Balance Sheet'!M342,'5. Balance Sheet'!M361)-SUM('5. Balance Sheet'!M380,'5. Balance Sheet'!M399) -> 0 | BA39: =SUM('5. Balance Sheet'!R342,'5. Balance Sheet'!R361)-SUM('5. Balance Sheet'!R380,'5. Balance Sheet'!R399) -> 0 | BB39: =SUM('5. Balance Sheet'!S342,'5. Balance Sheet'!S361)-SUM('5. Balance Sheet'!S380,'5. Balance Sheet'!S399) -> 0 | BC39: =SUM('5. Balance Sheet'!T342,'5. Balance Sheet'!T361)-SUM('5. Balance Sheet'!T380,'5. Balance Sheet'!T399) -> 0 | BD39: =SUM('5. Balance Sheet'!U342,'5. Balance Sheet'!U361)-SUM('5. Balance Sheet'!U380,'5. Balance Sheet'!U399) -> 0
B40: Change in Working Capital | C40: (000) | D40: 0 | E40: =E39-D39 -> 0 | F40: =F39-E39 -> 0 | G40: =G39-F39 -> 0 | H40: =H39-G39 -> 0 | I40: =I39-H39 -> 0 | J40: =J39-I39 -> 0 | K40: =K39-J39 -> 0 | M40: 0 | N40: =N39-M39 -> 0 | O40: =O39-N39 -> 0 | P40: =P39-O39 -> 0 | Q40: =Q39-P39 -> 0 | R40: =R39-Q39 -> 0 | S40: =S39-R39 -> 0 | T40: =T39-S39 -> 0 | V40: 0 | W40: =W39-V39 -> 0 | X40: =X39-W39 -> 0 | Y40: =Y39-X39 -> 0 | Z40: =Z39-Y39 -> 0 | AA40: =AA39-Z39 -> 0 | AB40: =AB39-AA39 -> 0 | AC40: =AC39-AB39 -> 0 | AE40: 0 | AF40: =AF39-AE39 -> 0 | AG40: =AG39-AF39 -> 0 | AH40: =AH39-AG39 -> 0 | AI40: =AI39-AH39 -> 0 | AJ40: =AJ39-AI39 -> 0 | AK40: =AK39-AJ39 -> 0 | AL40: =AL39-AK39 -> 0 | AN40: 0 | AO40: =AO39-AN39 -> 0 | AP40: =AP39-AO39 -> 0 | AQ40: =AQ39-AP39 -> 0 | AR40: =AR39-AQ39 -> 0 | AS40: =AS39-AR39 -> 0 | AT40: =AT39-AS39 -> 0 | AU40: =AU39-AT39 -> 0 | AW40: 0 | AX40: =AX39-AW39 -> 0 | AY40: =AY39-AX39 -> 0 | AZ40: =AZ39-AY39 -> 0 | BA40: =BA39-AZ39 -> 0 | BB40: =BB39-BA39 -> 0 | BC40: =BC39-BB39 -> 0 | BD40: =BD39-BC39 -> 0
B41: Total Investment | C41: (000) | D41: =SUM(D28:D29) -> 0 | E41: =SUM(E28:E29) -> 0 | F41: =SUM(F28:F29) -> 0 | G41: =SUM(G28:G29) -> 0 | H41: =SUM(H28:H29) -> 0 | I41: =SUM(I28:I29) -> 0 | J41: =SUM(J28:J29) -> 0 | K41: =SUM(K28:K29) -> 0 | M41: =SUM(M28:M29) -> 0 | N41: =SUM(N28:N29) -> 0 | O41: =SUM(O28:O29) -> 0 | P41: =SUM(P28:P29) -> 0 | Q41: =SUM(Q28:Q29) -> 0 | R41: =SUM(R28:R29) -> 0 | S41: =SUM(S28:S29) -> 0 | T41: =SUM(T28:T29) -> 0 | V41: =SUM(V28:V29) -> 0 | W41: =SUM(W28:W29) -> 0 | X41: =SUM(X28:X29) -> 0 | Y41: =SUM(Y28:Y29) -> 0 | Z41: =SUM(Z28:Z29) -> 0 | AA41: =SUM(AA28:AA29) -> 0 | AB41: =SUM(AB28:AB29) -> 0 | AC41: =SUM(AC28:AC29) -> 0 | AE41: =SUM(AE28:AE29) -> 0 | AF41: =SUM(AF28:AF29) -> 0 | AG41: =SUM(AG28:AG29) -> 0 | AH41: =SUM(AH28:AH29) -> 0 | AI41: =SUM(AI28:AI29) -> 0 | AJ41: =SUM(AJ28:AJ29) -> 0 | AK41: =SUM(AK28:AK29) -> 0 | AL41: =SUM(AL28:AL29) -> 0 | AN41: =SUM(AN28:AN29) -> 0 | AO41: =SUM(AO28:AO29) -> 0 | AP41: =SUM(AP28:AP29) -> 0 | AQ41: =SUM(AQ28:AQ29) -> 0 | AR41: =SUM(AR28:AR29) -> 0 | AS41: =SUM(AS28:AS29) -> 0 | AT41: =SUM(AT28:AT29) -> 0 | AU41: =SUM(AU28:AU29) -> 0 | AW41: =SUM(AW28:AW29) -> 0 | AX41: =SUM(AX28:AX29) -> 0 | AY41: =SUM(AY28:AY29) -> 0 | AZ41: =SUM(AZ28:AZ29) -> 0 | BA41: =SUM(BA28:BA29) -> 0 | BB41: =SUM(BB28:BB29) -> 0 | BC41: =SUM(BC28:BC29) -> 0 | BD41: =SUM(BD28:BD29) -> 0
B42: ROIC (after-tax) | C42: pct. | D42: =IFERROR(D32/D41,0) -> 0 | E42: =IFERROR(E32/E41,0) -> 0 | F42: =IFERROR(F32/F41,0) -> 0 | G42: =IFERROR(G32/G41,0) -> 0 | H42: =IFERROR(H32/H41,0) -> 0 | I42: =IFERROR(I32/I41,0) -> 0 | J42: =IFERROR(J32/J41,0) -> 0 | K42: =IFERROR(K32/K41,0) -> 0 | M42: =IFERROR(M32/M41,0) -> 0 | N42: =IFERROR(N32/N41,0) -> 0 | O42: =IFERROR(O32/O41,0) -> 0 | P42: =IFERROR(P32/P41,0) -> 0 | Q42: =IFERROR(Q32/Q41,0) -> 0 | R42: =IFERROR(R32/R41,0) -> 0 | S42: =IFERROR(S32/S41,0) -> 0 | T42: =IFERROR(T32/T41,0) -> 0 | V42: =IFERROR(V32/V41,0) -> 0 | W42: =IFERROR(W32/W41,0) -> 0 | X42: =IFERROR(X32/X41,0) -> 0 | Y42: =IFERROR(Y32/Y41,0) -> 0 | Z42: =IFERROR(Z32/Z41,0) -> 0 | AA42: =IFERROR(AA32/AA41,0) -> 0 | AB42: =IFERROR(AB32/AB41,0) -> 0 | AC42: =IFERROR(AC32/AC41,0) -> 0 | AE42: =IFERROR(AE32/AE41,0) -> 0 | AF42: =IFERROR(AF32/AF41,0) -> 0 | AG42: =IFERROR(AG32/AG41,0) -> 0 | AH42: =IFERROR(AH32/AH41,0) -> 0 | AI42: =IFERROR(AI32/AI41,0) -> 0 | AJ42: =IFERROR(AJ32/AJ41,0) -> 0 | AK42: =IFERROR(AK32/AK41,0) -> 0 | AL42: =IFERROR(AL32/AL41,0) -> 0 | AN42: =IFERROR(AN32/AN41,0) -> 0 | AO42: =IFERROR(AO32/AO41,0) -> 0 | AP42: =IFERROR(AP32/AP41,0) -> 0 | AQ42: =IFERROR(AQ32/AQ41,0) -> 0 | AR42: =IFERROR(AR32/AR41,0) -> 0 | AS42: =IFERROR(AS32/AS41,0) -> 0 | AT42: =IFERROR(AT32/AT41,0) -> 0 | AU42: =IFERROR(AU32/AU41,0) -> 0 | AW42: =IFERROR(AW32/AW41,0) -> 0 | AX42: =IFERROR(AX32/AX41,0) -> 0 | AY42: =IFERROR(AY32/AY41,0) -> 0 | AZ42: =IFERROR(AZ32/AZ41,0) -> 0 | BA42: =IFERROR(BA32/BA41,0) -> 0 | BB42: =IFERROR(BB32/BB41,0) -> 0 | BC42: =IFERROR(BC32/BC41,0) -> 0 | BD42: =IFERROR(BD32/BD41,0) -> 0
B44: Net Present Value | C44: (000) | D44: =NPV(wacc,G32:K32) -> 0 | M44: =NPV(wacc,P32:T32) -> 0 | V44: =NPV(wacc,Y32:AC32) -> 0 | AE44: =NPV(wacc,AH32:AL32) -> 0 | AN44: =NPV(wacc,AQ32:AU32) -> 0 | AW44: =NPV(wacc,AZ32:BD32) -> 0
B45: Terminal Value | C45: (000) | D45: =(K32*(1+tv_growth)/(wacc-tv_growth))/(1+wacc)^5 -> 0 | M45: =(T32*(1+tv_growth)/(wacc-tv_growth))/(1+wacc)^5 -> 0 | V45: =(AC32*(1+tv_growth)/(wacc-tv_growth))/(1+wacc)^5 -> 0 | AE45: =(AL32*(1+tv_growth)/(wacc-tv_growth))/(1+wacc)^5 -> 0 | AN45: =(AU32*(1+tv_growth)/(wacc-tv_growth))/(1+wacc)^5 -> 0 | AW45: =(BD32*(1+tv_growth)/(wacc-tv_growth))/(1+wacc)^5 -> 0
B46: Total EV | C46: (000) | D46: =SUM(D44:D45) -> 0 | M46: =SUM(M44:M45) -> 0 | V46: =SUM(V44:V45) -> 0 | AE46: =SUM(AE44:AE45) -> 0 | AN46: =SUM(AN44:AN45) -> 0 | AW46: =SUM(AW44:AW45) -> 0
B48: Payback Period | C48: yrs | D48: {=IFERROR(MATCH(TRUE,G32:K32>=0,0),"5+")} -> 1 | M48: {=IFERROR(MATCH(TRUE,P32:T32>=0,0),"5+")} -> 1 | V48: {=IFERROR(MATCH(TRUE,Y32:AC32>=0,0),"5+")} -> 1 | AE48: {=IFERROR(MATCH(TRUE,AH32:AL32>=0,0),"5+")} -> 1 | AN48: {=IFERROR(MATCH(TRUE,AQ32:AU32>=0,0),"5+")} -> 1 | AW48: {=IFERROR(MATCH(TRUE,AZ32:BD32>=0,0),"5+")} -> 1

Sheet 1. Margins
B3: Cash | C3: P&L | E3: ="Scenario 1: "&Inputs!B22 -> Scenario 1: Scenario 1
E4: =Inputs!C22 -> Scenario 1 Description
E7: Total Net Sales | W7: Total Net Sales
E8: Commerical assumptions 000s | W8: Key In expected Dollar amounts in 000s
F10: =Inputs!$C$7 -> 2023 | G10: =Inputs!$C$8 -> 2024 | H10: =Inputs!$C$9 -> 2025 | I10: Q1 | J10: Q2 | K10: Q3 | L10: Q4 | M10: =Inputs!$C$10 -> 2026 | N10: Q1 | O10: Q2 | P10: Q3 | Q10: Q4 | R10: =Inputs!$C$11 -> 2027 | S10: =Inputs!$C$12 -> 2028 | T10: =Inputs!$C$13 -> 2029 | U10: =Inputs!$C$14 -> 2030 | X10: Q1 | Y10: Q2 | Z10: Q3 | AA10: Q4 | AB10: =Inputs!$C$10 -> 2026 | AC10: Q1 | AD10: Q2 | AE10: Q3 | AF10: Q4 | AG10: =Inputs!$C$11 -> 2027 | AH10: =Inputs!$C$12 -> 2028 | AI10: =Inputs!$C$13 -> 2029 | AJ10: =Inputs!$C$14 -> 2030
F11: (000) | G11: (000) | H11: (000) | I11: (000) | J11: (000) | K11: (000) | L11: (000) | M11: (000) | N11: (000) | O11: (000) | P11: (000) | Q11: (000) | R11: (000) | S11: (000) | T11: (000) | U11: (000) | X11: $ | Y11: $ | Z11: $ | AA11: $ | AC11: $ | AD11: $ | AE11: $ | AF11: $ | AH11: $ | AI11: $ | AJ11: $
B12: l | C12: l | E12: Product Line 1 | F12: =F512 -> 0 | G12: =G512 -> 0 | H12: =H512 -> 0 | I12: =IF(X12="",I512,X12) -> 0 | J12: =IF(Y12="",J512,Y12) -> 0 | K12: =IF(Z12="",K512,Z12) -> 0 | L12: =IF(AA12="",L512,AA12) -> 0 | M12: =SUM(I12:L12) -> 0 | N12: =IF(AC12="",N512,AC12) -> 0 | O12: =IF(AD12="",O512,AD12) -> 0 | P12: =IF(AE12="",P512,AE12) -> 0 | Q12: =IF(AF12="",Q512,AF12) -> 0 | R12: =SUM(N12:Q12) -> 0 | S12: =IF(AH12="",S512,AH12) -> 0 | T12: =IF(AI12="",T512,AI12) -> 0 | U12: =IF(AJ12="",U512,AJ12) -> 0 | W12: =E12 -> Product Line 1
B13: l | C13: l | E13: Product Line 2 | F13: =F513 -> 0 | G13: =G513 -> 0 | H13: =H513 -> 0 | I13: =IF(X13="",I513,X13) -> 0 | J13: =IF(Y13="",J513,Y13) -> 0 | K13: =IF(Z13="",K513,Z13) -> 0 | L13: =IF(AA13="",L513,AA13) -> 0 | M13: =SUM(I13:L13) -> 0 | N13: =IF(AC13="",N513,AC13) -> 0 | O13: =IF(AD13="",O513,AD13) -> 0 | P13: =IF(AE13="",P513,AE13) -> 0 | Q13: =IF(AF13="",Q513,AF13) -> 0 | R13: =SUM(N13:Q13) -> 0 | S13: =IF(AH13="",S513,AH13) -> 0 | T13: =IF(AI13="",T513,AI13) -> 0 | U13: =IF(AJ13="",U513,AJ13) -> 0 | W13: =E13 -> Product Line 2
B14: l | C14: l | E14: Product Line 3 | F14: =F514 -> 0 | G14: =G514 -> 0 | H14: =H514 -> 0 | I14: =IF(X14="",I514,X14) -> 0 | J14: =IF(Y14="",J514,Y14) -> 0 | K14: =IF(Z14="",K514,Z14) -> 0 | L14: =IF(AA14="",L514,AA14) -> 0 | M14: =SUM(I14:L14) -> 0 | N14: =IF(AC14="",N514,AC14) -> 0 | O14: =IF(AD14="",O514,AD14) -> 0 | P14: =IF(AE14="",P514,AE14) -> 0 | Q14: =IF(AF14="",Q514,AF14) -> 0 | R14: =SUM(N14:Q14) -> 0 | S14: =IF(AH14="",S514,AH14) -> 0 | T14: =IF(AI14="",T514,AI14) -> 0 | U14: =IF(AJ14="",U514,AJ14) -> 0 | W14: =E14 -> Product Line 3
B15: l | C15: l | E15: Product Line 4 | F15: =F515 -> 0 | G15: =G515 -> 0 | H15: =H515 -> 0 | I15: =IF(X15="",I515,X15) -> 0 | J15: =IF(Y15="",J515,Y15) -> 0 | K15: =IF(Z15="",K515,Z15) -> 0 | L15: =IF(AA15="",L515,AA15) -> 0 | M15: =SUM(I15:L15) -> 0 | N15: =IF(AC15="",N515,AC15) -> 0 | O15: =IF(AD15="",O515,AD15) -> 0 | P15: =IF(AE15="",P515,AE15) -> 0 | Q15: =IF(AF15="",Q515,AF15) -> 0 | R15: =SUM(N15:Q15) -> 0 | S15: =IF(AH15="",S515,AH15) -> 0 | T15: =IF(AI15="",T515,AI15) -> 0 | U15: =IF(AJ15="",U515,AJ15) -> 0 | W15: =E15 -> Product Line 4
B16: l | C16: l | E16: Product Line 5 | F16: =F516 -> 0 | G16: =G516 -> 0 | H16: =H516 -> 0 | I16: =IF(X16="",I516,X16) -> 0 | J16: =IF(Y16="",J516,Y16) -> 0 | K16: =IF(Z16="",K516,Z16) -> 0 | L16: =IF(AA16="",L516,AA16) -> 0 | M16: =SUM(I16:L16) -> 0 | N16: =IF(AC16="",N516,AC16) -> 0 | O16: =IF(AD16="",O516,AD16) -> 0 | P16: =IF(AE16="",P516,AE16) -> 0 | Q16: =IF(AF16="",Q516,AF16) -> 0 | R16: =SUM(N16:Q16) -> 0 | S16: =IF(AH16="",S516,AH16) -> 0 | T16: =IF(AI16="",T516,AI16) -> 0 | U16: =IF(AJ16="",U516,AJ16) -> 0 | W16: =E16 -> Product Line 5
B17: l | C17: l | E17: Product Line 6 | F17: =F517 -> 0 | G17: =G517 -> 0 | H17: =H517 -> 0 | I17: =IF(X17="",I517,X17) -> 0 | J17: =IF(Y17="",J517,Y17) -> 0 | K17: =IF(Z17="",K517,Z17) -> 0 | L17: =IF(AA17="",L517,AA17) -> 0 | M17: =SUM(I17:L17) -> 0 | N17: =IF(AC17="",N517,AC17) -> 0 | O17: =IF(AD17="",O517,AD17) -> 0 | P17: =IF(AE17="",P517,AE17) -> 0 | Q17: =IF(AF17="",Q517,AF17) -> 0 | R17: =SUM(N17:Q17) -> 0 | S17: =IF(AH17="",S517,AH17) -> 0 | T17: =IF(AI17="",T517,AI17) -> 0 | U17: =IF(AJ17="",U517,AJ17) -> 0 | W17: =E17 -> Product Line 6
B18: l | C18: l | E18: Product Line 7 | F18: =F518 -> 0 | G18: =G518 -> 0 | H18: =H518 -> 0 | I18: =IF(X18="",I518,X18) -> 0 | J18: =IF(Y18="",J518,Y18) -> 0 | K18: =IF(Z18="",K518,Z18) -> 0 | L18: =IF(AA18="",L518,AA18) -> 0 | M18: =SUM(I18:L18) -> 0 | N18: =IF(AC18="",N518,AC18) -> 0 | O18: =IF(AD18="",O518,AD18) -> 0 | P18: =IF(AE18="",P518,AE18) -> 0 | Q18: =IF(AF18="",Q518,AF18) -> 0 | R18: =SUM(N18:Q18) -> 0 | S18: =IF(AH18="",S518,AH18) -> 0 | T18: =IF(AI18="",T518,AI18) -> 0 | U18: =IF(AJ18="",U518,AJ18) -> 0 | W18: =E18 -> Product Line 7
E19: Total | F19: =SUM(F12:F18) -> 0 | G19: =SUM(G12:G18) -> 0 | H19: =SUM(H12:H18) -> 0 | I19: =SUM(I12:I18) -> 0 | J19: =SUM(J12:J18) -> 0 | K19: =SUM(K12:K18) -> 0 | L19: =SUM(L12:L18) -> 0 | M19: =SUM(M12:M18) -> 0 | ... U19: =SUM(U12:U18) -> 0
E23: Material Costs (Variable) | W23: Material Costs (Variable)
E24: Commerical assumptions 000s | W24: Key In expected Dollar amounts in 000s
F26: =Inputs!$C$7 -> 2023 | G26: =Inputs!$C$8 -> 2024 | H26: =Inputs!$C$9 -> 2025 | I26: Q1 | J26: Q2 | K26: Q3 | L26: Q4 | M26: =Inputs!$C$10 -> 2026 | N26: Q1 | O26: Q2 | P26: Q3 | Q26: Q4 | R26: =Inputs!$C$11 -> 2027 | S26: =Inputs!$C$12 -> 2028 | T26: =Inputs!$C$13 -> 2029 | U26: =Inputs!$C$14 -> 2030 | X26: Q1 | Y26: Q2 | Z26: Q3 | AA26: Q4 | AB26: =Inputs!$C$10 -> 2026 | AC26: Q1 | AD26: Q2 | AE26: Q3 | AF26: Q4 | AG26: =Inputs!$C$11 -> 2027 | AH26: =Inputs!$C$12 -> 2028 | AI26: =Inputs!$C$13 -> 2029 | AJ26: =Inputs!$C$14 -> 2030
F27: (000) | G27: (000) | H27: (000) | I27: (000) | J27: (000) | K27: (000) | L27: (000) | M27: (000) | N27: (000) | O27: (000) | P27: (000) | Q27: (000) | R27: (000) | S27: (000) | T27: (000) | U27: (000) | X27: $ | Y27: $ | Z27: $ | AA27: $ | AC27: $ | AD27: $ | AE27: $ | AF27: $ | AH27: $ | AI27: $ | AJ27: $
B28: l | C28: l | E28: Product Line 1 | F28: =F528 -> 0 | G28: =G528 -> 0 | H28: =H528 -> 0 | I28: =IF(X28="",I528,X28) -> 0 | J28: =IF(Y28="",J528,Y28) -> 0 | K28: =IF(Z28="",K528,Z28) -> 0 | L28: =IF(AA28="",L528,AA28) -> 0 | M28: =SUM(I28:L28) -> 0 | N28: =IF(AC28="",N528,AC28) -> 0 | O28: =IF(AD28="",O528,AD28) -> 0 | P28: =IF(AE28="",P528,AE28) -> 0 | Q28: =IF(AF28="",Q528,AF28) -> 0 | R28: =SUM(N28:Q28) -> 0 | S28: =IF(AH28="",S528,AH28) -> 0 | T28: =IF(AI28="",T528,AI28) -> 0 | U28: =IF(AJ28="",U528,AJ28) -> 0 | W28: =E28 -> Product Line 1
B29: l | C29: l | E29: Product Line 2 | F29: =F529 -> 0 | G29: =G529 -> 0 | H29: =H529 -> 0 | I29: =IF(X29="",I529,X29) -> 0 | J29: =IF(Y29="",J529,Y29) -> 0 | K29: =IF(Z29="",K529,Z29) -> 0 | L29: =IF(AA29="",L529,AA29) -> 0 | M29: =SUM(I29:L29) -> 0 | N29: =IF(AC29="",N529,AC29) -> 0 | O29: =IF(AD29="",O529,AD29) -> 0 | P29: =IF(AE29="",P529,AE29) -> 0 | Q29: =IF(AF29="",Q529,AF29) -> 0 | R29: =SUM(N29:Q29) -> 0 | S29: =IF(AH29="",S529,AH29) -> 0 | T29: =IF(AI29="",T529,AI29) -> 0 | U29: =IF(AJ29="",U529,AJ29) -> 0 | W29: =E29 -> Product Line 2
B30: l | C30: l | E30: Product Line 3 | F30: =F530 -> 0 | G30: =G530 -> 0 | H30: =H530 -> 0 | I30: =IF(X30="",I530,X30) -> 0 | J30: =IF(Y30="",J530,Y30) -> 0 | K30: =IF(Z30="",K530,Z30) -> 0 | L30: =IF(AA30="",L530,AA30) -> 0 | M30: =SUM(I30:L30) -> 0 | N30: =IF(AC30="",N530,AC30) -> 0 | O30: =IF(AD30="",O530,AD30) -> 0 | P30: =IF(AE30="",P530,AE30) -> 0 | Q30: =IF(AF30="",Q530,AF30) -> 0 | R30: =SUM(N30:Q30) -> 0 | S30: =IF(AH30="",S530,AH30) -> 0 | T30: =IF(AI30="",T530,AI30) -> 0 | U30: =IF(AJ30="",U530,AJ30) -> 0 | W30: =E30 -> Product Line 3
B31: l | C31: l | E31: Product Line 4 | F31: =F531 -> 0 | G31: =G531 -> 0 | H31: =H531 -> 0 | I31: =IF(X31="",I531,X31) -> 0 | J31: =IF(Y31="",J531,Y31) -> 0 | K31: =IF(Z31="",K531,Z31) -> 0 | L31: =IF(AA31="",L531,AA31) -> 0 | M31: =SUM(I31:L31) -> 0 | N31: =IF(AC31="",N531,AC31) -> 0 | O31: =IF(AD31="",O531,AD31) -> 0 | P31: =IF(AE31="",P531,AE31) -> 0 | Q31: =IF(AF31="",Q531,AF31) -> 0 | R31: =SUM(N31:Q31) -> 0 | S31: =IF(AH31="",S531,AH31) -> 0 | T31: =IF(AI31="",T531,AI31) -> 0 | U31: =IF(AJ31="",U531,AJ31) -> 0 | W31: =E31 -> Product Line 4
B32: l | C32: l | E32: Product Line 5 | F32: =F532 -> 0 | G32: =G532 -> 0 | H32: =H532 -> 0 | I32: =IF(X32="",I532,X32) -> 0 | J32: =IF(Y32="",J532,Y32) -> 0 | K32: =IF(Z32="",K532,Z32) -> 0 | L32: =IF(AA32="",L532,AA32) -> 0 | M32: =SUM(I32:L32) -> 0 | N32: =IF(AC32="",N532,AC32) -> 0 | O32: =IF(AD32="",O532,AD32) -> 0 | P32: =IF(AE32="",P532,AE32) -> 0 | Q32: =IF(AF32="",Q532,AF32) -> 0 | R32: =SUM(N32:Q32) -> 0 | S32: =IF(AH32="",S532,AH32) -> 0 | T32: =IF(AI32="",T532,AI32) -> 0 | U32: =IF(AJ32="",U532,AJ32) -> 0 | W32: =E32 -> Product Line 5
B33: l | C33: l | E33: Product Line 6 | F33: =F533 -> 0 | G33: =G533 -> 0 | H33: =H533 -> 0 | I33: =IF(X33="",I533,X33) -> 0 | J33: =IF(Y33="",J533,Y33) -> 0 | K33: =IF(Z33="",K533,Z33) -> 0 | L33: =IF(AA33="",L533,AA33) -> 0 | M33: =SUM(I33:L33) -> 0 | N33: =IF(AC33="",N533,AC33) -> 0 | O33: =IF(AD33="",O533,AD33) -> 0 | P33: =IF(AE33="",P533,AE33) -> 0 | Q33: =IF(AF33="",Q533,AF33) -> 0 | R33: =SUM(N33:Q33) -> 0 | S33: =IF(AH33="",S533,AH33) -> 0 | T33: =IF(AI33="",T533,AI33) -> 0 | U33: =IF(AJ33="",U533,AJ33) -> 0 | W33: =E33 -> Product Line 6
B34: l | C34: l | E34: Product Line 7 | F34: =F534 -> 0 | G34: =G534 -> 0 | H34: =H534 -> 0 | I34: =IF(X34="",I534,X34) -> 0 | J34: =IF(Y34="",J534,Y34) -> 0 | K34: =IF(Z34="",K534,Z34) -> 0 | L34: =IF(AA34="",L534,AA34) -> 0 | M34: =SUM(I34:L34) -> 0 | N34: =IF(AC34="",N534,AC34) -> 0 | O34: =IF(AD34="",O534,AD34) -> 0 | P34: =IF(AE34="",P534,AE34) -> 0 | Q34: =IF(AF34="",Q534,AF34) -> 0 | R34: =SUM(N34:Q34) -> 0 | S34: =IF(AH34="",S534,AH34) -> 0 | T34: =IF(AI34="",T534,AI34) -> 0 | U34: =IF(AJ34="",U534,AJ34) -> 0 | W34: =E34 -> Product Line 7
E35: Total | F35: =SUM(F28:F34) -> 0 | G35: =SUM(G28:G34) -> 0 | H35: =SUM(H28:H34) -> 0 | I35: =SUM(I28:I34) -> 0 | J35: =SUM(J28:J34) -> 0 | K35: =SUM(K28:K34) -> 0 | L35: =SUM(L28:L34) -> 0 | M35: =SUM(M28:M34) -> 0 | ... U35: =SUM(U28:U34) -> 0
E39: Direct Labor (Variable) | W39: Direct Labor (Variable)
E40: Commerical assumptions 000s | W40: Key In expected Dollar amounts in 000s
F42: =Inputs!$C$7 -> 2023 | G42: =Inputs!$C$8 -> 2024 | H42: =Inputs!$C$9 -> 2025 | I42: Q1 | J42: Q2 | K42: Q3 | L42: Q4 | M42: =Inputs!$C$10 -> 2026 | N42: Q1 | O42: Q2 | P42: Q3 | Q42: Q4 | R42: =Inputs!$C$11 -> 2027 | S42: =Inputs!$C$12 -> 2028 | T42: =Inputs!$C$13 -> 2029 | U42: =Inputs!$C$14 -> 2030 | X42: Q1 | Y42: Q2 | Z42: Q3 | AA42: Q4 | AB42: =Inputs!$C$10 -> 2026 | AC42: Q1 | AD42: Q2 | AE42: Q3 | AF42: Q4 | AG42: =Inputs!$C$11 -> 2027 | AH42: =Inputs!$C$12 -> 2028 | AI42: =Inputs!$C$13 -> 2029 | AJ42: =Inputs!$C$14 -> 2030
F43: (000) | G43: (000) | H43: (000) | I43: (000) | J43: (000) | K43: (000) | L43: (000) | M43: (000) | N43: (000) | O43: (000) | P43: (000) | Q43: (000) | R43: (000) | S43: (000) | T43: (000) | U43: (000) | X43: $ | Y43: $ | Z43: $ | AA43: $ | AC43: $ | AD43: $ | AE43: $ | AF43: $ | AH43: $ | AI43: $ | AJ43: $
B44: l | C44: l | E44: Product Line 1 | F44: =F544 -> 0 | G44: =G544 -> 0 | H44: =H544 -> 0 | I44: =IF(X44="",I544,X44) -> 0 | J44: =IF(Y44="",J544,Y44) -> 0 | K44: =IF(Z44="",K544,Z44) -> 0 | L44: =IF(AA44="",L544,AA44) -> 0 | M44: =SUM(I44:L44) -> 0 | N44: =IF(AC44="",N544,AC44) -> 0 | O44: =IF(AD44="",O544,AD44) -> 0 | P44: =IF(AE44="",P544,AE44) -> 0 | Q44: =IF(AF44="",Q544,AF44) -> 0 | R44: =SUM(N44:Q44) -> 0 | S44: =IF(AH44="",S544,AH44) -> 0 | T44: =IF(AI44="",T544,AI44) -> 0 | U44: =IF(AJ44="",U544,AJ44) -> 0 | W44: =E44 -> Product Line 1
B45: l | C45: l | E45: Product Line 2 | F45: =F545 -> 0 | G45: =G545 -> 0 | H45: =H545 -> 0 | I45: =IF(X45="",I545,X45) -> 0 | J45: =IF(Y45="",J545,Y45) -> 0 | K45: =IF(Z45="",K545,Z45) -> 0 | L45: =IF(AA45="",L545,AA45) -> 0 | M45: =SUM(I45:L45) -> 0 | N45: =IF(AC45="",N545,AC45) -> 0 | O45: =IF(AD45="",O545,AD45) -> 0 | P45: =IF(AE45="",P545,AE45) -> 0 | Q45: =IF(AF45="",Q545,AF45) -> 0 | R45: =SUM(N45:Q45) -> 0 | S45: =IF(AH45="",S545,AH45) -> 0 | T45: =IF(AI45="",T545,AI45) -> 0 | U45: =IF(AJ45="",U545,AJ45) -> 0 | W45: =E45 -> Product Line 2
B46: l | C46: l | E46: Product Line 3 | F46: =F546 -> 0 | G46: =G546 -> 0 | H46: =H546 -> 0 | I46: =IF(X46="",I546,X46) -> 0 | J46: =IF(Y46="",J546,Y46) -> 0 | K46: =IF(Z46="",K546,Z46) -> 0 | L46: =IF(AA46="",L546,AA46) -> 0 | M46: =SUM(I46:L46) -> 0 | N46: =IF(AC46="",N546,AC46) -> 0 | O46: =IF(AD46="",O546,AD46) -> 0 | P46: =IF(AE46="",P546,AE46) -> 0 | Q46: =IF(AF46="",Q546,AF46) -> 0 | R46: =SUM(N46:Q46) -> 0 | S46: =IF(AH46="",S546,AH46) -> 0 | T46: =IF(AI46="",T546,AI46) -> 0 | U46: =IF(AJ46="",U546,AJ46) -> 0 | W46: =E46 -> Product Line 3
B47: l | C47: l | E47: Product Line 4 | F47: =F547 -> 0 | G47: =G547 -> 0 | H47: =H547 -> 0 | I47: =IF(X47="",I547,X47) -> 0 | J47: =IF(Y47="",J547,Y47) -> 0 | K47: =IF(Z47="",K547,Z47) -> 0 | L47: =IF(AA47="",L547,AA47) -> 0 | M47: =SUM(I47:L47) -> 0 | N47: =IF(AC47="",N547,AC47) -> 0 | O47: =IF(AD47="",O547,AD47) -> 0 | P47: =IF(AE47="",P547,AE47) -> 0 | Q47: =IF(AF47="",Q547,AF47) -> 0 | R47: =SUM(N47:Q47) -> 0 | S47: =IF(AH47="",S547,AH47) -> 0 | T47: =IF(AI47="",T547,AI47) -> 0 | U47: =IF(AJ47="",U547,AJ47) -> 0 | W47: =E47 -> Product Line 4
B48: l | C48: l | E48: Product Line 5 | F48: =F548 -> 0 | G48: =G548 -> 0 | H48: =H548 -> 0 | I48: =IF(X48="",I548,X48) -> 0 | J48: =IF(Y48="",J548,Y48) -> 0 | K48: =IF(Z48="",K548,Z48) -> 0 | L48: =IF(AA48="",L548,AA48) -> 0 | M48: =SUM(I48:L48) -> 0 | N48: =IF(AC48="",N548,AC48) -> 0 | O48: =IF(AD48="",O548,AD48) -> 0 | P48: =IF(AE48="",P548,AE48) -> 0 | Q48: =IF(AF48="",Q548,AF48) -> 0 | R48: =SUM(N48:Q48) -> 0 | S48: =IF(AH48="",S548,AH48) -> 0 | T48: =IF(AI48="",T548,AI48) -> 0 | U48: =IF(AJ48="",U548,AJ48) -> 0 | W48: =E48 -> Product Line 5
B49: l | C49: l | E49: Product Line 6 | F49: =F549 -> 0 | G49: =G549 -> 0 | H49: =H549 -> 0 | I49: =IF(X49="",I549,X49) -> 0 | J49: =IF(Y49="",J549,Y49) -> 0 | K49: =IF(Z49="",K549,Z49) -> 0 | L49: =IF(AA49="",L549,AA49) -> 0 | M49: =SUM(I49:L49) -> 0 | N49: =IF(AC49="",N549,AC49) -> 0 | O49: =IF(AD49="",O549,AD49) -> 0 | P49: =IF(AE49="",P549,AE49) -> 0 | Q49: =IF(AF49="",Q549,AF49) -> 0 | R49: =SUM(N49:Q49) -> 0 | S49: =IF(AH49="",S549,AH49) -> 0 | T49: =IF(AI49="",T549,AI49) -> 0 | U49: =IF(AJ49="",U549,AJ49) -> 0 | W49: =E49 -> Product Line 6
B50: l | C50: l | E50: Product Line 7 | F50: =F550 -> 0 | G50: =G550 -> 0 | H50: =H550 -> 0 | I50: =IF(X50="",I550,X50) -> 0 | J50: =IF(Y50="",J550,Y50) -> 0 | K50: =IF(Z50="",K550,Z50) -> 0 | L50: =IF(AA50="",L550,AA50) -> 0 | M50: =SUM(I50:L50) -> 0 | N50: =IF(AC50="",N550,AC50) -> 0 | O50: =IF(AD50="",O550,AD50) -> 0 | P50: =IF(AE50="",P550,AE50) -> 0 | Q50: =IF(AF50="",Q550,AF50) -> 0 | R50: =SUM(N50:Q50) -> 0 | S50: =IF(AH50="",S550,AH50) -> 0 | T50: =IF(AI50="",T550,AI50) -> 0 | U50: =IF(AJ50="",U550,AJ50) -> 0 | W50: =E50 -> Product Line 7
E51: Total | F51: =SUM(F44:F50) -> 0 | G51: =SUM(G44:G50) -> 0 | H51: =SUM(H44:H50) -> 0 | I51: =SUM(I44:I50) -> 0 | J51: =SUM(J44:J50) -> 0 | K51: =SUM(K44:K50) -> 0 | L51: =SUM(L44:L50) -> 0 | M51: =SUM(M44:M50) -> 0 | ... U51: =SUM(U44:U50) -> 0
E55: Variable Overheads | W55: Variable Overheads
E56: Commerical assumptions 000s | W56: Key In expected Dollar amounts in 000s
F58: =Inputs!$C$7 -> 2023 | G58: =Inputs!$C$8 -> 2024 | H58: =Inputs!$C$9 -> 2025 | I58: Q1 | J58: Q2 | K58: Q3 | L58: Q4 | M58: =Inputs!$C$10 -> 2026 | N58: Q1 | O58: Q2 | P58: Q3 | Q58: Q4 | R58: =Inputs!$C$11 -> 2027 | S58: =Inputs!$C$12 -> 2028 | T58: =Inputs!$C$13 -> 2029 | U58: =Inputs!$C$14 -> 2030 | X58: Q1 | Y58: Q2 | Z58: Q3 | AA58: Q4 | AB58: =Inputs!$C$10 -> 2026 | AC58: Q1 | AD58: Q2 | AE58: Q3 | AF58: Q4 | AG58: =Inputs!$C$11 -> 2027 | AH58: =Inputs!$C$12 -> 2028 | AI58: =Inputs!$C$13 -> 2029 | AJ58: =Inputs!$C$14 -> 2030
F59: (000) | G59: (000) | H59: (000) | I59: (000) | J59: (000) | K59: (000) | L59: (000) | M59: (000) | N59: (000) | O59: (000) | P59: (000) | Q59: (000) | R59: (000) | S59: (000) | T59: (000) | U59: (000) | X59: $ | Y59: $ | Z59: $ | AA59: $ | AC59: $ | AD59: $ | AE59: $ | AF59: $ | AH59: $ | AI59: $ | AJ59: $
B60: l | C60: l | E60: Product Line 1 | F60: =F560 -> 0 | G60: =G560 -> 0 | H60: =H560 -> 0 | I60: =IF(X60="",I560,X60) -> 0 | J60: =IF(Y60="",J560,Y60) -> 0 | K60: =IF(Z60="",K560,Z60) -> 0 | L60: =IF(AA60="",L560,AA60) -> 0 | M60: =SUM(I60:L60) -> 0 | N60: =IF(AC60="",N560,AC60) -> 0 | O60: =IF(AD60="",O560,AD60) -> 0 | P60: =IF(AE60="",P560,AE60) -> 0 | Q60: =IF(AF60="",Q560,AF60) -> 0 | R60: =SUM(N60:Q60) -> 0 | S60: =IF(AH60="",S560,AH60) -> 0 | T60: =IF(AI60="",T560,AI60) -> 0 | U60: =IF(AJ60="",U560,AJ60) -> 0 | W60: =E60 -> Product Line 1
B61: l | C61: l | E61: Product Line 2 | F61: =F561 -> 0 | G61: =G561 -> 0 | H61: =H561 -> 0 | I61: =IF(X61="",I561,X61) -> 0 | J61: =IF(Y61="",J561,Y61) -> 0 | K61: =IF(Z61="",K561,Z61) -> 0 | L61: =IF(AA61="",L561,AA61) -> 0 | M61: =SUM(I61:L61) -> 0 | N61: =IF(AC61="",N561,AC61) -> 0 | O61: =IF(AD61="",O561,AD61) -> 0 | P61: =IF(AE61="",P561,AE61) -> 0 | Q61: =IF(AF61="",Q561,AF61) -> 0 | R61: =SUM(N61:Q61) -> 0 | S61: =IF(AH61="",S561,AH61) -> 0 | T61: =IF(AI61="",T561,AI61) -> 0 | U61: =IF(AJ61="",U561,AJ61) -> 0 | W61: =E61 -> Product Line 2
B62: l | C62: l | E62: Product Line 3 | F62: =F562 -> 0 | G62: =G562 -> 0 | H62: =H562 -> 0 | I62: =IF(X62="",I562,X62) -> 0 | J62: =IF(Y62="",J562,Y62) -> 0 | K62: =IF(Z62="",K562,Z62) -> 0 | L62: =IF(AA62="",L562,AA62) -> 0 | M62: =SUM(I62:L62) -> 0 | N62: =IF(AC62="",N562,AC62) -> 0 | O62: =IF(AD62="",O562,AD62) -> 0 | P62: =IF(AE62="",P562,AE62) -> 0 | Q62: =IF(AF62="",Q562,AF62) -> 0 | R62: =SUM(N62:Q62) -> 0 | S62: =IF(AH62="",S562,AH62) -> 0 | T62: =IF(AI62="",T562,AI62) -> 0 | U62: =IF(AJ62="",U562,AJ62) -> 0 | W62: =E62 -> Product Line 3
B63: l | C63: l | E63: Product Line 4 | F63: =F563 -> 0 | G63: =G563 -> 0 | H63: =H563 -> 0 | I63: =IF(X63="",I563,X63) -> 0 | J63: =IF(Y63="",J563,Y63) -> 0 | K63: =IF(Z63="",K563,Z63) -> 0 | L63: =IF(AA63="",L563,AA63) -> 0 | M63: =SUM(I63:L63) -> 0 | N63: =IF(AC63="",N563,AC63) -> 0 | O63: =IF(AD63="",O563,AD63) -> 0 | P63: =IF(AE63="",P563,AE63) -> 0 | Q63: =IF(AF63="",Q563,AF63) -> 0 | R63: =SUM(N63:Q63) -> 0 | S63: =IF(AH63="",S563,AH63) -> 0 | T63: =IF(AI63="",T563,AI63) -> 0 | U63: =IF(AJ63="",U563,AJ63) -> 0 | W63: =E63 -> Product Line 4
B64: l | C64: l | E64: Product Line 5 | F64: =F564 -> 0 | G64: =G564 -> 0 | H64: =H564 -> 0 | I64: =IF(X64="",I564,X64) -> 0 | J64: =IF(Y64="",J564,Y64) -> 0 | K64: =IF(Z64="",K564,Z64) -> 0 | L64: =IF(AA64="",L564,AA64) -> 0 | M64: =SUM(I64:L64) -> 0 | N64: =IF(AC64="",N564,AC64) -> 0 | O64: =IF(AD64="",O564,AD64) -> 0 | P64: =IF(AE64="",P564,AE64) -> 0 | Q64: =IF(AF64="",Q564,AF64) -> 0 | R64: =SUM(N64:Q64) -> 0 | S64: =IF(AH64="",S564,AH64) -> 0 | T64: =IF(AI64="",T564,AI64) -> 0 | U64: =IF(AJ64="",U564,AJ64) -> 0 | W64: =E64 -> Product Line 5
B65: l | C65: l | E65: Product Line 6 | F65: =F565 -> 0 | G65: =G565 -> 0 | H65: =H565 -> 0 | I65: =IF(X65="",I565,X65) -> 0 | J65: =IF(Y65="",J565,Y65) -> 0 | K65: =IF(Z65="",K565,Z65) -> 0 | L65: =IF(AA65="",L565,AA65) -> 0 | M65: =SUM(I65:L65) -> 0 | N65: =IF(AC65="",N565,AC65) -> 0 | O65: =IF(AD65="",O565,AD65) -> 0 | P65: =IF(AE65="",P565,AE65) -> 0 | Q65: =IF(AF65="",Q565,AF65) -> 0 | R65: =SUM(N65:Q65) -> 0 | S65: =IF(AH65="",S565,AH65) -> 0 | T65: =IF(AI65="",T565,AI65) -> 0 | U65: =IF(AJ65="",U565,AJ65) -> 0 | W65: =E65 -> Product Line 6
B66: l | C66: l | E66: Product Line 7 | F66: =F566 -> 0 | G66: =G566 -> 0 | H66: =H566 -> 0 | I66: =IF(X66="",I566,X66) -> 0 | J66: =IF(Y66="",J566,Y66) -> 0 | K66: =IF(Z66="",K566,Z66) -> 0 | L66: =IF(AA66="",L566,AA66) -> 0 | M66: =SUM(I66:L66) -> 0 | N66: =IF(AC66="",N566,AC66) -> 0 | O66: =IF(AD66="",O566,AD66) -> 0 | P66: =IF(AE66="",P566,AE66) -> 0 | Q66: =IF(AF66="",Q566,AF66) -> 0 | R66: =SUM(N66:Q66) -> 0 | S66: =IF(AH66="",S566,AH66) -> 0 | T66: =IF(AI66="",T566,AI66) -> 0 | U66: =IF(AJ66="",U566,AJ66) -> 0 | W66: =E66 -> Product Line 7
E67: Total | F67: =SUM(F60:F66) -> 0 | G67: =SUM(G60:G66) -> 0 | H67: =SUM(H60:H66) -> 0 | I67: =SUM(I60:I66) -> 0 | J67: =SUM(J60:J66) -> 0 | K67: =SUM(K60:K66) -> 0 | L67: =SUM(L60:L66) -> 0 | M67: =SUM(M60:M66) -> 0 | ... U67: =SUM(U60:U66) -> 0
E71: Direct Margin at Standard
E72: Commerical assumptions 000s
F74: =Inputs!$C$7 -> 2023 | G74: =Inputs!$C$8 -> 2024 | H74: =Inputs!$C$9 -> 2025 | I74: Q1 | J74: Q2 | K74: Q3 | L74: Q4 | M74: =Inputs!$C$10 -> 2026 | N74: Q1 | O74: Q2 | P74: Q3 | Q74: Q4 | R74: =Inputs!$C$11 -> 2027 | S74: =Inputs!$C$12 -> 2028 | T74: =Inputs!$C$13 -> 2029 | U74: =Inputs!$C$14 -> 2030
F75: (000) | G75: (000) | H75: (000) | I75: (000) | J75: (000) | K75: (000) | L75: (000) | M75: (000) | N75: (000) | O75: (000) | P75: (000) | Q75: (000) | R75: (000) | S75: (000) | T75: (000) | U75: (000)
B76: l | C76: l | E76: Product Line 1 | F76: =F576 -> 0 | G76: =G576 -> 0 | H76: =H576 -> 0 | I76: =IF(X92="",I12*I592,I12*X92) -> 0 | J76: =IF(Y92="",J12*J592,J12*Y92) -> 0 | K76: =IF(Z92="",K12*K592,K12*Z92) -> 0 | L76: =IF(AA92="",L12*L592,L12*AA92) -> 0 | M76: =SUM(I76:L76) -> 0 | N76: =IF(AC92="",N12*N592,N12*AC92) -> 0 | O76: =IF(AD92="",O12*O592,O12*AD92) -> 0 | P76: =IF(AE92="",P12*P592,P12*AE92) -> 0 | Q76: =IF(AF92="",Q12*Q592,Q12*AF92) -> 0 | R76: =SUM(N76:Q76) -> 0 | S76: =IF(AH92="",S12*S592,S12*AH92) -> 0 | T76: =IF(AI92="",T12*T592,T12*AI92) -> 0 | U76: =IF(AJ92="",U12*U592,U12*AJ92) -> 0
B77: l | C77: l | E77: Product Line 2 | F77: =F577 -> 0 | G77: =G577 -> 0 | H77: =H577 -> 0 | I77: =IF(X93="",I13*I593,I13*X93) -> 0 | J77: =IF(Y93="",J13*J593,J13*Y93) -> 0 | K77: =IF(Z93="",K13*K593,K13*Z93) -> 0 | L77: =IF(AA93="",L13*L593,L13*AA93) -> 0 | M77: =SUM(I77:L77) -> 0 | N77: =IF(AC93="",N13*N593,N13*AC93) -> 0 | O77: =IF(AD93="",O13*O593,O13*AD93) -> 0 | P77: =IF(AE93="",P13*P593,P13*AE93) -> 0 | Q77: =IF(AF93="",Q13*Q593,Q13*AF93) -> 0 | R77: =SUM(N77:Q77) -> 0 | S77: =IF(AH93="",S13*S593,S13*AH93) -> 0 | T77: =IF(AI93="",T13*T593,T13*AI93) -> 0 | U77: =IF(AJ93="",U13*U593,U13*AJ93) -> 0
B78: l | C78: l | E78: Product Line 3 | F78: =F578 -> 0 | G78: =G578 -> 0 | H78: =H578 -> 0 | I78: =IF(X94="",I14*I594,I14*X94) -> 0 | J78: =IF(Y94="",J14*J594,J14*Y94) -> 0 | K78: =IF(Z94="",K14*K594,K14*Z94) -> 0 | L78: =IF(AA94="",L14*L594,L14*AA94) -> 0 | M78: =SUM(I78:L78) -> 0 | N78: =IF(AC94="",N14*N594,N14*AC94) -> 0 | O78: =IF(AD94="",O14*O594,O14*AD94) -> 0 | P78: =IF(AE94="",P14*P594,P14*AE94) -> 0 | Q78: =IF(AF94="",Q14*Q594,Q14*AF94) -> 0 | R78: =SUM(N78:Q78) -> 0 | S78: =IF(AH94="",S14*S594,S14*AH94) -> 0 | T78: =IF(AI94="",T14*T594,T14*AI94) -> 0 | U78: =IF(AJ94="",U14*U594,U14*AJ94) -> 0
B79: l | C79: l | E79: Product Line 4 | F79: =F579 -> 0 | G79: =G579 -> 0 | H79: =H579 -> 0 | I79: =IF(X95="",I15*I595,I15*X95) -> 0 | J79: =IF(Y95="",J15*J595,J15*Y95) -> 0 | K79: =IF(Z95="",K15*K595,K15*Z95) -> 0 | L79: =IF(AA95="",L15*L595,L15*AA95) -> 0 | M79: =SUM(I79:L79) -> 0 | N79: =IF(AC95="",N15*N595,N15*AC95) -> 0 | O79: =IF(AD95="",O15*O595,O15*AD95) -> 0 | P79: =IF(AE95="",P15*P595,P15*AE95) -> 0 | Q79: =IF(AF95="",Q15*Q595,Q15*AF95) -> 0 | R79: =SUM(N79:Q79) -> 0 | S79: =IF(AH95="",S15*S595,S15*AH95) -> 0 | T79: =IF(AI95="",T15*T595,T15*AI95) -> 0 | U79: =IF(AJ95="",U15*U595,U15*AJ95) -> 0
B80: l | C80: l | E80: Product Line 5 | F80: =F580 -> 0 | G80: =G580 -> 0 | H80: =H580 -> 0 | I80: =IF(X96="",I16*I596,I16*X96) -> 0 | J80: =IF(Y96="",J16*J596,J16*Y96) -> 0 | K80: =IF(Z96="",K16*K596,K16*Z96) -> 0 | L80: =IF(AA96="",L16*L596,L16*AA96) -> 0 | M80: =SUM(I80:L80) -> 0 | N80: =IF(AC96="",N16*N596,N16*AC96) -> 0 | O80: =IF(AD96="",O16*O596,O16*AD96) -> 0 | P80: =IF(AE96="",P16*P596,P16*AE96) -> 0 | Q80: =IF(AF96="",Q16*Q596,Q16*AF96) -> 0 | R80: =SUM(N80:Q80) -> 0 | S80: =IF(AH96="",S16*S596,S16*AH96) -> 0 | T80: =IF(AI96="",T16*T596,T16*AI96) -> 0 | U80: =IF(AJ96="",U16*U596,U16*AJ96) -> 0
B81: l | C81: l | E81: Product Line 6 | F81: =F581 -> 0 | G81: =G581 -> 0 | H81: =H581 -> 0 | I81: =IF(X97="",I17*I597,I17*X97) -> 0 | J81: =IF(Y97="",J17*J597,J17*Y97) -> 0 | K81: =IF(Z97="",K17*K597,K17*Z97) -> 0 | L81: =IF(AA97="",L17*L597,L17*AA97) -> 0 | M81: =SUM(I81:L81) -> 0 | N81: =IF(AC97="",N17*N597,N17*AC97) -> 0 | O81: =IF(AD97="",O17*O597,O17*AD97) -> 0 | P81: =IF(AE97="",P17*P597,P17*AE97) -> 0 | Q81: =IF(AF97="",Q17*Q597,Q17*AF97) -> 0 | R81: =SUM(N81:Q81) -> 0 | S81: =IF(AH97="",S17*S597,S17*AH97) -> 0 | T81: =IF(AI97="",T17*T597,T17*AI97) -> 0 | U81: =IF(AJ97="",U17*U597,U17*AJ97) -> 0
B82: l | C82: l | E82: Product Line 7 | F82: =F582 -> 0 | G82: =G582 -> 0 | H82: =H582 -> 0 | I82: =IF(X98="",I18*I598,I18*X98) -> 0 | J82: =IF(Y98="",J18*J598,J18*Y98) -> 0 | K82: =IF(Z98="",K18*K598,K18*Z98) -> 0 | L82: =IF(AA98="",L18*L598,L18*AA98) -> 0 | M82: =SUM(I82:L82) -> 0 | N82: =IF(AC98="",N18*N598,N18*AC98) -> 0 | O82: =IF(AD98="",O18*O598,O18*AD98) -> 0 | P82: =IF(AE98="",P18*P598,P18*AE98) -> 0 | Q82: =IF(AF98="",Q18*Q598,Q18*AF98) -> 0 | R82: =SUM(N82:Q82) -> 0 | S82: =IF(AH98="",S18*S598,S18*AH98) -> 0 | T82: =IF(AI98="",T18*T598,T18*AI98) -> 0 | U82: =IF(AJ98="",U18*U598,U18*AJ98) -> 0
E83: Total | F83: =SUM(F76:F82) -> 0 | G83: =SUM(G76:G82) -> 0 | H83: =SUM(H76:H82) -> 0 | I83: =SUM(I76:I82) -> 0 | J83: =SUM(J76:J82) -> 0 | K83: =SUM(K76:K82) -> 0 | L83: =SUM(L76:L82) -> 0 | M83: =SUM(M76:M82) -> 0 | ... U83: =SUM(U76:U82) -> 0
E87: Direct Margin at Standard % | W87: Direct Margin at Standard %
E88: Commerical assumptions % | W88: Key In expected DM%, this will shift Direct Margin Dollars in section directly above
F90: =Inputs!$C$7 -> 2023 | G90: =Inputs!$C$8 -> 2024 | H90: =Inputs!$C$9 -> 2025 | I90: Q1 | J90: Q2 | K90: Q3 | L90: Q4 | M90: =Inputs!$C$10 -> 2026 | N90: Q1 | O90: Q2 | P90: Q3 | Q90: Q4 | R90: =Inputs!$C$11 -> 2027 | S90: =Inputs!$C$12 -> 2028 | T90: =Inputs!$C$13 -> 2029 | U90: =Inputs!$C$14 -> 2030 | X90: Q1 | Y90: Q2 | Z90: Q3 | AA90: Q4 | AB90: =Inputs!$C$10 -> 2026 | AC90: Q1 | AD90: Q2 | AE90: Q3 | AF90: Q4 | AG90: =Inputs!$C$11 -> 2027 | AH90: =Inputs!$C$12 -> 2028 | AI90: =Inputs!$C$13 -> 2029 | AJ90: =Inputs!$C$14 -> 2030
F91: % | G91: % | H91: % | I91: % | J91: % | K91: % | L91: % | M91: % | N91: % | O91: % | P91: % | Q91: % | R91: % | S91: % | T91: % | U91: % | X91: % | Y91: % | Z91: % | AA91: % | AC91: % | AD91: % | AE91: % | AF91: % | AH91: % | AI91: % | AJ91: %
B92: l | C92: l | E92: Product Line 1 | F92: =IFERROR(F76/F12,0) -> 0 | G92: =IFERROR(G76/G12,0) -> 0 | H92: =IFERROR(H76/H12,0) -> 0 | I92: =IFERROR(I76/I12,0) -> 0 | J92: =IFERROR(J76/J12,0) -> 0 | K92: =IFERROR(K76/K12,0) -> 0 | L92: =IFERROR(L76/L12,0) -> 0 | M92: =IFERROR(M76/M12,0) -> 0 | ... U92: =IFERROR(U76/U12,0) -> 0 | W92: =E92 -> Product Line 1
B93: l | C93: l | E93: Product Line 2 | F93: =IFERROR(F77/F13,0) -> 0 | G93: =IFERROR(G77/G13,0) -> 0 | H93: =IFERROR(H77/H13,0) -> 0 | I93: =IFERROR(I77/I13,0) -> 0 | J93: =IFERROR(J77/J13,0) -> 0 | K93: =IFERROR(K77/K13,0) -> 0 | L93: =IFERROR(L77/L13,0) -> 0 | M93: =IFERROR(M77/M13,0) -> 0 | ... U93: =IFERROR(U77/U13,0) -> 0 | W93: =E93 -> Product Line 2
B94: l | C94: l | E94: Product Line 3 | F94: =IFERROR(F78/F14,0) -> 0 | G94: =IFERROR(G78/G14,0) -> 0 | H94: =IFERROR(H78/H14,0) -> 0 | I94: =IFERROR(I78/I14,0) -> 0 | J94: =IFERROR(J78/J14,0) -> 0 | K94: =IFERROR(K78/K14,0) -> 0 | L94: =IFERROR(L78/L14,0) -> 0 | M94: =IFERROR(M78/M14,0) -> 0 | ... U94: =IFERROR(U78/U14,0) -> 0 | W94: =E94 -> Product Line 3
B95: l | C95: l | E95: Product Line 4 | F95: =IFERROR(F79/F15,0) -> 0 | G95: =IFERROR(G79/G15,0) -> 0 | H95: =IFERROR(H79/H15,0) -> 0 | I95: =IFERROR(I79/I15,0) -> 0 | J95: =IFERROR(J79/J15,0) -> 0 | K95: =IFERROR(K79/K15,0) -> 0 | L95: =IFERROR(L79/L15,0) -> 0 | M95: =IFERROR(M79/M15,0) -> 0 | ... U95: =IFERROR(U79/U15,0) -> 0 | W95: =E95 -> Product Line 4
B96: l | C96: l | E96: Product Line 5 | F96: =IFERROR(F80/F16,0) -> 0 | G96: =IFERROR(G80/G16,0) -> 0 | H96: =IFERROR(H80/H16,0) -> 0 | I96: =IFERROR(I80/I16,0) -> 0 | J96: =IFERROR(J80/J16,0) -> 0 | K96: =IFERROR(K80/K16,0) -> 0 | L96: =IFERROR(L80/L16,0) -> 0 | M96: =IFERROR(M80/M16,0) -> 0 | ... U96: =IFERROR(U80/U16,0) -> 0 | W96: =E96 -> Product Line 5
B97: l | C97: l | E97: Product Line 6 | F97: =IFERROR(F81/F17,0) -> 0 | G97: =IFERROR(G81/G17,0) -> 0 | H97: =IFERROR(H81/H17,0) -> 0 | I97: =IFERROR(I81/I17,0) -> 0 | J97: =IFERROR(J81/J17,0) -> 0 | K97: =IFERROR(K81/K17,0) -> 0 | L97: =IFERROR(L81/L17,0) -> 0 | M97: =IFERROR(M81/M17,0) -> 0 | ... U97: =IFERROR(U81/U17,0) -> 0 | W97: =E97 -> Product Line 6
B98: l | C98: l | E98: Product Line 7 | F98: =IFERROR(F82/F18,0) -> 0 | G98: =IFERROR(G82/G18,0) -> 0 | H98: =IFERROR(H82/H18,0) -> 0 | I98: =IFERROR(I82/I18,0) -> 0 | J98: =IFERROR(J82/J18,0) -> 0 | K98: =IFERROR(K82/K18,0) -> 0 | L98: =IFERROR(L82/L18,0) -> 0 | M98: =IFERROR(M82/M18,0) -> 0 | ... U98: =IFERROR(U82/U18,0) -> 0 | W98: =E98 -> Product Line 7
E99: Total | F99: =IFERROR(F83/F19,0) -> 0 | G99: =IFERROR(G83/G19,0) -> 0 | H99: =IFERROR(H83/H19,0) -> 0 | I99: =IFERROR(I83/I19,0) -> 0 | J99: =IFERROR(J83/J19,0) -> 0 | K99: =IFERROR(K83/K19,0) -> 0 | L99: =IFERROR(L83/L19,0) -> 0 | M99: =IFERROR(M83/M19,0) -> 0 | ... U99: =IFERROR(U83/U19,0) -> 0
B103: Cash | C103: P&L | E103: ="Scenario 2: "&Inputs!B23 -> Scenario 2: Scenario 2
E104: =Inputs!C23 -> Scenario 2 Description
E107: Total Net Sales | W107: Total Net Sales
E108: Commerical assumptions 000s | W108: Key In expected Dollar amounts in 000s
F110: =Inputs!$C$7 -> 2023 | G110: =Inputs!$C$8 -> 2024 | H110: =Inputs!$C$9 -> 2025 | I110: Q1 | J110: Q2 | K110: Q3 | L110: Q4 | M110: =Inputs!$C$10 -> 2026 | N110: Q1 | O110: Q2 | P110: Q3 | Q110: Q4 | R110: =Inputs!$C$11 -> 2027 | S110: =Inputs!$C$12 -> 2028 | T110: =Inputs!$C$13 -> 2029 | U110: =Inputs!$C$14 -> 2030 | X110: Q1 | Y110: Q2 | Z110: Q3 | AA110: Q4 | AB110: =Inputs!$C$10 -> 2026 | AC110: Q1 | AD110: Q2 | AE110: Q3 | AF110: Q4 | AG110: =Inputs!$C$11 -> 2027 | AH110: =Inputs!$C$12 -> 2028 | AI110: =Inputs!$C$13 -> 2029 | AJ110: =Inputs!$C$14 -> 2030
F111: (000) | G111: (000) | H111: (000) | I111: (000) | J111: (000) | K111: (000) | L111: (000) | M111: (000) | N111: (000) | O111: (000) | P111: (000) | Q111: (000) | R111: (000) | S111: (000) | T111: (000) | U111: (000) | X111: $ | Y111: $ | Z111: $ | AA111: $ | AC111: $ | AD111: $ | AE111: $ | AF111: $ | AH111: $ | AI111: $ | AJ111: $
B112: l | C112: l | E112: Product Line 1 | F112: =F512 -> 0 | G112: =G512 -> 0 | H112: =H512 -> 0 | I112: =IF(X112="",I512,X112) -> 0 | J112: =IF(Y112="",J512,Y112) -> 0 | K112: =IF(Z112="",K512,Z112) -> 0 | L112: =IF(AA112="",L512,AA112) -> 0 | M112: =SUM(I112:L112) -> 0 | N112: =IF(AC112="",N512,AC112) -> 0 | O112: =IF(AD112="",O512,AD112) -> 0 | P112: =IF(AE112="",P512,AE112) -> 0 | Q112: =IF(AF112="",Q512,AF112) -> 0 | R112: =SUM(N112:Q112) -> 0 | S112: =IF(AH112="",S512,AH112) -> 0 | T112: =IF(AI112="",T512,AI112) -> 0 | U112: =IF(AJ112="",U512,AJ112) -> 0 | W112: =E112 -> Product Line 1
B113: l | C113: l | E113: Product Line 2 | F113: =F513 -> 0 | G113: =G513 -> 0 | H113: =H513 -> 0 | I113: =IF(X113="",I513,X113) -> 0 | J113: =IF(Y113="",J513,Y113) -> 0 | K113: =IF(Z113="",K513,Z113) -> 0 | L113: =IF(AA113="",L513,AA113) -> 0 | M113: =SUM(I113:L113) -> 0 | N113: =IF(AC113="",N513,AC113) -> 0 | O113: =IF(AD113="",O513,AD113) -> 0 | P113: =IF(AE113="",P513,AE113) -> 0 | Q113: =IF(AF113="",Q513,AF113) -> 0 | R113: =SUM(N113:Q113) -> 0 | S113: =IF(AH113="",S513,AH113) -> 0 | T113: =IF(AI113="",T513,AI113) -> 0 | U113: =IF(AJ113="",U513,AJ113) -> 0 | W113: =E113 -> Product Line 2
B114: l | C114: l | E114: Product Line 3 | F114: =F514 -> 0 | G114: =G514 -> 0 | H114: =H514 -> 0 | I114: =IF(X114="",I514,X114) -> 0 | J114: =IF(Y114="",J514,Y114) -> 0 | K114: =IF(Z114="",K514,Z114) -> 0 | L114: =IF(AA114="",L514,AA114) -> 0 | M114: =SUM(I114:L114) -> 0 | N114: =IF(AC114="",N514,AC114) -> 0 | O114: =IF(AD114="",O514,AD114) -> 0 | P114: =IF(AE114="",P514,AE114) -> 0 | Q114: =IF(AF114="",Q514,AF114) -> 0 | R114: =SUM(N114:Q114) -> 0 | S114: =IF(AH114="",S514,AH114) -> 0 | T114: =IF(AI114="",T514,AI114) -> 0 | U114: =IF(AJ114="",U514,AJ114) -> 0 | W114: =E114 -> Product Line 3
B115: l | C115: l | E115: Product Line 4 | F115: =F515 -> 0 | G115: =G515 -> 0 | H115: =H515 -> 0 | I115: =IF(X115="",I515,X115) -> 0 | J115: =IF(Y115="",J515,Y115) -> 0 | K115: =IF(Z115="",K515,Z115) -> 0 | L115: =IF(AA115="",L515,AA115) -> 0 | M115: =SUM(I115:L115) -> 0 | N115: =IF(AC115="",N515,AC115) -> 0 | O115: =IF(AD115="",O515,AD115) -> 0 | P115: =IF(AE115="",P515,AE115) -> 0 | Q115: =IF(AF115="",Q515,AF115) -> 0 | R115: =SUM(N115:Q115) -> 0 | S115: =IF(AH115="",S515,AH115) -> 0 | T115: =IF(AI115="",T515,AI115) -> 0 | U115: =IF(AJ115="",U515,AJ115) -> 0 | W115: =E115 -> Product Line 4
B116: l | C116: l | E116: Product Line 5 | F116: =F516 -> 0 | G116: =G516 -> 0 | H116: =H516 -> 0 | I116: =IF(X116="",I516,X116) -> 0 | J116: =IF(Y116="",J516,Y116) -> 0 | K116: =IF(Z116="",K516,Z116) -> 0 | L116: =IF(AA116="",L516,AA116) -> 0 | M116: =SUM(I116:L116) -> 0 | N116: =IF(AC116="",N516,AC116) -> 0 | O116: =IF(AD116="",O516,AD116) -> 0 | P116: =IF(AE116="",P516,AE116) -> 0 | Q116: =IF(AF116="",Q516,AF116) -> 0 | R116: =SUM(N116:Q116) -> 0 | S116: =IF(AH116="",S516,AH116) -> 0 | T116: =IF(AI116="",T516,AI116) -> 0 | U116: =IF(AJ116="",U516,AJ116) -> 0 | W116: =E116 -> Product Line 5
B117: l | C117: l | E117: Product Line 6 | F117: =F517 -> 0 | G117: =G517 -> 0 | H117: =H517 -> 0 | I117: =IF(X117="",I517,X117) -> 0 | J117: =IF(Y117="",J517,Y117) -> 0 | K117: =IF(Z117="",K517,Z117) -> 0 | L117: =IF(AA117="",L517,AA117) -> 0 | M117: =SUM(I117:L117) -> 0 | N117: =IF(AC117="",N517,AC117) -> 0 | O117: =IF(AD117="",O517,AD117) -> 0 | P117: =IF(AE117="",P517,AE117) -> 0 | Q117: =IF(AF117="",Q517,AF117) -> 0 | R117: =SUM(N117:Q117) -> 0 | S117: =IF(AH117="",S517,AH117) -> 0 | T117: =IF(AI117="",T517,AI117) -> 0 | U117: =IF(AJ117="",U517,AJ117) -> 0 | W117: =E117 -> Product Line 6
B118: l | C118: l | E118: Product Line 7 | F118: =F518 -> 0 | G118: =G518 -> 0 | H118: =H518 -> 0 | I118: =IF(X118="",I518,X118) -> 0 | J118: =IF(Y118="",J518,Y118) -> 0 | K118: =IF(Z118="",K518,Z118) -> 0 | L118: =IF(AA118="",L518,AA118) -> 0 | M118: =SUM(I118:L118) -> 0 | N118: =IF(AC118="",N518,AC118) -> 0 | O118: =IF(AD118="",O518,AD118) -> 0 | P118: =IF(AE118="",P518,AE118) -> 0 | Q118: =IF(AF118="",Q518,AF118) -> 0 | R118: =SUM(N118:Q118) -> 0 | S118: =IF(AH118="",S518,AH118) -> 0 | T118: =IF(AI118="",T518,AI118) -> 0 | U118: =IF(AJ118="",U518,AJ118) -> 0 | W118: =E118 -> Product Line 7
E119: Total | F119: =SUM(F112:F118) -> 0 | G119: =SUM(G112:G118) -> 0 | H119: =SUM(H112:H118) -> 0 | I119: =SUM(I112:I118) -> 0 | J119: =SUM(J112:J118) -> 0 | K119: =SUM(K112:K118) -> 0 | L119: =SUM(L112:L118) -> 0 | M119: =SUM(M112:M118) -> 0 | ... U119: =SUM(U112:U118) -> 0
E123: Material Costs (Variable) | W123: Material Costs (Variable)
E124: Commerical assumptions 000s | W124: Key In expected Dollar amounts in 000s
F126: =Inputs!$C$7 -> 2023 | G126: =Inputs!$C$8 -> 2024 | H126: =Inputs!$C$9 -> 2025 | I126: Q1 | J126: Q2 | K126: Q3 | L126: Q4 | M126: =Inputs!$C$10 -> 2026 | N126: Q1 | O126: Q2 | P126: Q3 | Q126: Q4 | R126: =Inputs!$C$11 -> 2027 | S126: =Inputs!$C$12 -> 2028 | T126: =Inputs!$C$13 -> 2029 | U126: =Inputs!$C$14 -> 2030 | X126: Q1 | Y126: Q2 | Z126: Q3 | AA126: Q4 | AB126: =Inputs!$C$10 -> 2026 | AC126: Q1 | AD126: Q2 | AE126: Q3 | AF126: Q4 | AG126: =Inputs!$C$11 -> 2027 | AH126: =Inputs!$C$12 -> 2028 | AI126: =Inputs!$C$13 -> 2029 | AJ126: =Inputs!$C$14 -> 2030
F127: (000) | G127: (000) | H127: (000) | I127: (000) | J127: (000) | K127: (000) | L127: (000) | M127: (000) | N127: (000) | O127: (000) | P127: (000) | Q127: (000) | R127: (000) | S127: (000) | T127: (000) | U127: (000) | X127: $ | Y127: $ | Z127: $ | AA127: $ | AC127: $ | AD127: $ | AE127: $ | AF127: $ | AH127: $ | AI127: $ | AJ127: $
B128: l | C128: l | E128: Product Line 1 | F128: =F528 -> 0 | G128: =G528 -> 0 | H128: =H528 -> 0 | I128: =IF(X128="",I528,X128) -> 0 | J128: =IF(Y128="",J528,Y128) -> 0 | K128: =IF(Z128="",K528,Z128) -> 0 | L128: =IF(AA128="",L528,AA128) -> 0 | M128: =SUM(I128:L128) -> 0 | N128: =IF(AC128="",N528,AC128) -> 0 | O128: =IF(AD128="",O528,AD128) -> 0 | P128: =IF(AE128="",P528,AE128) -> 0 | Q128: =IF(AF128="",Q528,AF128) -> 0 | R128: =SUM(N128:Q128) -> 0 | S128: =IF(AH128="",S528,AH128) -> 0 | T128: =IF(AI128="",T528,AI128) -> 0 | U128: =IF(AJ128="",U528,AJ128) -> 0 | W128: =E128 -> Product Line 1
B129: l | C129: l | E129: Product Line 2 | F129: =F529 -> 0 | G129: =G529 -> 0 | H129: =H529 -> 0 | I129: =IF(X129="",I529,X129) -> 0 | J129: =IF(Y129="",J529,Y129) -> 0 | K129: =IF(Z129="",K529,Z129) -> 0 | L129: =IF(AA129="",L529,AA129) -> 0 | M129: =SUM(I129:L129) -> 0 | N129: =IF(AC129="",N529,AC129) -> 0 | O129: =IF(AD129="",O529,AD129) -> 0 | P129: =IF(AE129="",P529,AE129) -> 0 | Q129: =IF(AF129="",Q529,AF129) -> 0 | R129: =SUM(N129:Q129) -> 0 | S129: =IF(AH129="",S529,AH129) -> 0 | T129: =IF(AI129="",T529,AI129) -> 0 | U129: =IF(AJ129="",U529,AJ129) -> 0 | W129: =E129 -> Product Line 2
B130: l | C130: l | E130: Product Line 3 | F130: =F530 -> 0 | G130: =G530 -> 0 | H130: =H530 -> 0 | I130: =IF(X130="",I530,X130) -> 0 | J130: =IF(Y130="",J530,Y130) -> 0 | K130: =IF(Z130="",K530,Z130) -> 0 | L130: =IF(AA130="",L530,AA130) -> 0 | M130: =SUM(I130:L130) -> 0 | N130: =IF(AC130="",N530,AC130) -> 0 | O130: =IF(AD130="",O530,AD130) -> 0 | P130: =IF(AE130="",P530,AE130) -> 0 | Q130: =IF(AF130="",Q530,AF130) -> 0 | R130: =SUM(N130:Q130) -> 0 | S130: =IF(AH130="",S530,AH130) -> 0 | T130: =IF(AI130="",T530,AI130) -> 0 | U130: =IF(AJ130="",U530,AJ130) -> 0 | W130: =E130 -> Product Line 3
B131: l | C131: l | E131: Product Line 4 | F131: =F531 -> 0 | G131: =G531 -> 0 | H131: =H531 -> 0 | I131: =IF(X131="",I531,X131) -> 0 | J131: =IF(Y131="",J531,Y131) -> 0 | K131: =IF(Z131="",K531,Z131) -> 0 | L131: =IF(AA131="",L531,AA131) -> 0 | M131: =SUM(I131:L131) -> 0 | N131: =IF(AC131="",N531,AC131) -> 0 | O131: =IF(AD131="",O531,AD131) -> 0 | P131: =IF(AE131="",P531,AE131) -> 0 | Q131: =IF(AF131="",Q531,AF131) -> 0 | R131: =SUM(N131:Q131) -> 0 | S131: =IF(AH131="",S531,AH131) -> 0 | T131: =IF(AI131="",T531,AI131) -> 0 | U131: =IF(AJ131="",U531,AJ131) -> 0 | W131: =E131 -> Product Line 4
B132: l | C132: l | E132: Product Line 5 | F132: =F532 -> 0 | G132: =G532 -> 0 | H132: =H532 -> 0 | I132: =IF(X132="",I532,X132) -> 0 | J132: =IF(Y132="",J532,Y132) -> 0 | K132: =IF(Z132="",K532,Z132) -> 0 | L132: =IF(AA132="",L532,AA132) -> 0 | M132: =SUM(I132:L132) -> 0 | N132: =IF(AC132="",N532,AC132) -> 0 | O132: =IF(AD132="",O532,AD132) -> 0 | P132: =IF(AE132="",P532,AE132) -> 0 | Q132: =IF(AF132="",Q532,AF132) -> 0 | R132: =SUM(N132:Q132) -> 0 | S132: =IF(AH132="",S532,AH132) -> 0 | T132: =IF(AI132="",T532,AI132) -> 0 | U132: =IF(AJ132="",U532,AJ132) -> 0 | W132: =E132 -> Product Line 5
B133: l | C133: l | E133: Product Line 6 | F133: =F533 -> 0 | G133: =G533 -> 0 | H133: =H533 -> 0 | I133: =IF(X133="",I533,X133) -> 0 | J133: =IF(Y133="",J533,Y133) -> 0 | K133: =IF(Z133="",K533,Z133) -> 0 | L133: =IF(AA133="",L533,AA133) -> 0 | M133: =SUM(I133:L133) -> 0 | N133: =IF(AC133="",N533,AC133) -> 0 | O133: =IF(AD133="",O533,AD133) -> 0 | P133: =IF(AE133="",P533,AE133) -> 0 | Q133: =IF(AF133="",Q533,AF133) -> 0 | R133: =SUM(N133:Q133) -> 0 | S133: =IF(AH133="",S533,AH133) -> 0 | T133: =IF(AI133="",T533,AI133) -> 0 | U133: =IF(AJ133="",U533,AJ133) -> 0 | W133: =E133 -> Product Line 6
B134: l | C134: l | E134: Product Line 7 | F134: =F534 -> 0 | G134: =G534 -> 0 | H134: =H534 -> 0 | I134: =IF(X134="",I534,X134) -> 0 | J134: =IF(Y134="",J534,Y134) -> 0 | K134: =IF(Z134="",K534,Z134) -> 0 | L134: =IF(AA134="",L534,AA134) -> 0 | M134: =SUM(I134:L134) -> 0 | N134: =IF(AC134="",N534,AC134) -> 0 | O134: =IF(AD134="",O534,AD134) -> 0 | P134: =IF(AE134="",P534,AE134) -> 0 | Q134: =IF(AF134="",Q534,AF134) -> 0 | R134: =SUM(N134:Q134) -> 0 | S134: =IF(AH134="",S534,AH134) -> 0 | T134: =IF(AI134="",T534,AI134) -> 0 | U134: =IF(AJ134="",U534,AJ134) -> 0 | W134: =E134 -> Product Line 7
E135: Total | F135: =SUM(F128:F134) -> 0 | G135: =SUM(G128:G134) -> 0 | H135: =SUM(H128:H134) -> 0 | I135: =SUM(I128:I134) -> 0 | J135: =SUM(J128:J134) -> 0 | K135: =SUM(K128:K134) -> 0 | L135: =SUM(L128:L134) -> 0 | M135: =SUM(M128:M134) -> 0 | ... U135: =SUM(U128:U134) -> 0
...

Sheet 2. OHCOGS
B3: Cash | C3: P&L | E3: ="Scenario 1: "&Inputs!B22 -> Scenario 1: Scenario 1
E4: =Inputs!C22 -> Scenario 1 Description
E7: Variances | W7: =E7 -> Variances
E8: Commerical assumptions 000s | W8: Key In expected Dollar amounts in 000s
F10: =Inputs!$C$7 -> 2023 | G10: =Inputs!$C$8 -> 2024 | H10: =Inputs!$C$9 -> 2025 | I10: Q1 | J10: Q2 | K10: Q3 | L10: Q4 | M10: =Inputs!$C$10 -> 2026 | N10: Q1 | O10: Q2 | P10: Q3 | Q10: Q4 | R10: =Inputs!$C$11 -> 2027 | S10: =Inputs!$C$12 -> 2028 | T10: =Inputs!$C$13 -> 2029 | U10: =Inputs!$C$14 -> 2030 | X10: Q1 | Y10: Q2 | Z10: Q3 | AA10: Q4 | AB10: =Inputs!$C$10 -> 2026 | AC10: Q1 | AD10: Q2 | AE10: Q3 | AF10: Q4 | AG10: =Inputs!$C$11 -> 2027 | AH10: =Inputs!$C$12 -> 2028 | AI10: =Inputs!$C$13 -> 2029 | AJ10: =Inputs!$C$14 -> 2030
F11: (000) | G11: (000) | H11: (000) | I11: (000) | J11: (000) | K11: (000) | L11: (000) | M11: (000) | N11: (000) | O11: (000) | P11: (000) | Q11: (000) | R11: (000) | S11: (000) | T11: (000) | U11: (000) | X11: $ | Y11: $ | Z11: $ | AA11: $ | AC11: $ | AD11: $ | AE11: $ | AF11: $ | AH11: $ | AI11: $ | AJ11: $
B12: l | C12: l | E12: Variances | F12: =F202 -> 0 | G12: =G202 -> 0 | H12: =H202 -> 0 | I12: =IF(X12="",I202,X12) -> 0 | J12: =IF(Y12="",J202,Y12) -> 0 | K12: =IF(Z12="",K202,Z12) -> 0 | L12: =IF(AA12="",L202,AA12) -> 0 | M12: =SUM(I12:L12) -> 0 | N12: =IF(AC12="",N202,AC12) -> 0 | O12: =IF(AD12="",O202,AD12) -> 0 | P12: =IF(AE12="",P202,AE12) -> 0 | Q12: =IF(AF12="",Q202,AF12) -> 0 | R12: =SUM(N12:Q12) -> 0 | S12: =IF(AH12="",S202,AH12) -> 0 | T12: =IF(AI12="",T202,AI12) -> 0 | U12: =IF(AJ12="",U202,AJ12) -> 0 | W12: =E12 -> Variances
B13: l | C13: l | E13: Exchange Gain/Loss | F13: =F203 -> 0 | G13: =G203 -> 0 | H13: =H203 -> 0 | I13: =IF(X13="",I203,X13) -> 0 | J13: =IF(Y13="",J203,Y13) -> 0 | K13: =IF(Z13="",K203,Z13) -> 0 | L13: =IF(AA13="",L203,AA13) -> 0 | M13: =SUM(I13:L13) -> 0 | N13: =IF(AC13="",N203,AC13) -> 0 | O13: =IF(AD13="",O203,AD13) -> 0 | P13: =IF(AE13="",P203,AE13) -> 0 | Q13: =IF(AF13="",Q203,AF13) -> 0 | R13: =SUM(N13:Q13) -> 0 | S13: =IF(AH13="",S203,AH13) -> 0 | T13: =IF(AI13="",T203,AI13) -> 0 | U13: =IF(AJ13="",U203,AJ13) -> 0 | W13: =E13 -> Exchange Gain/Loss
B14: l | C14: l | E14: blank | F14: =F204 -> 0 | G14: =G204 -> 0 | H14: =H204 -> 0 | I14: =IF(X14="",I204,X14) -> 0 | J14: =IF(Y14="",J204,Y14) -> 0 | K14: =IF(Z14="",K204,Z14) -> 0 | L14: =IF(AA14="",L204,AA14) -> 0 | M14: =SUM(I14:L14) -> 0 | N14: =IF(AC14="",N204,AC14) -> 0 | O14: =IF(AD14="",O204,AD14) -> 0 | P14: =IF(AE14="",P204,AE14) -> 0 | Q14: =IF(AF14="",Q204,AF14) -> 0 | R14: =SUM(N14:Q14) -> 0 | S14: =IF(AH14="",S204,AH14) -> 0 | T14: =IF(AI14="",T204,AI14) -> 0 | U14: =IF(AJ14="",U204,AJ14) -> 0 | W14: =E14 -> blank
B15: l | C15: l | E15: blank | F15: =F205 -> 0 | G15: =G205 -> 0 | H15: =H205 -> 0 | I15: =IF(X15="",I205,X15) -> 0 | J15: =IF(Y15="",J205,Y15) -> 0 | K15: =IF(Z15="",K205,Z15) -> 0 | L15: =IF(AA15="",L205,AA15) -> 0 | M15: =SUM(I15:L15) -> 0 | N15: =IF(AC15="",N205,AC15) -> 0 | O15: =IF(AD15="",O205,AD15) -> 0 | P15: =IF(AE15="",P205,AE15) -> 0 | Q15: =IF(AF15="",Q205,AF15) -> 0 | R15: =SUM(N15:Q15) -> 0 | S15: =IF(AH15="",S205,AH15) -> 0 | T15: =IF(AI15="",T205,AI15) -> 0 | U15: =IF(AJ15="",U205,AJ15) -> 0 | W15: =E15 -> blank
B16: l | C16: l | E16: blank | F16: =F206 -> 0 | G16: =G206 -> 0 | H16: =H206 -> 0 | I16: =IF(X16="",I206,X16) -> 0 | J16: =IF(Y16="",J206,Y16) -> 0 | K16: =IF(Z16="",K206,Z16) -> 0 | L16: =IF(AA16="",L206,AA16) -> 0 | M16: =SUM(I16:L16) -> 0 | N16: =IF(AC16="",N206,AC16) -> 0 | O16: =IF(AD16="",O206,AD16) -> 0 | P16: =IF(AE16="",P206,AE16) -> 0 | Q16: =IF(AF16="",Q206,AF16) -> 0 | R16: =SUM(N16:Q16) -> 0 | S16: =IF(AH16="",S206,AH16) -> 0 | T16: =IF(AI16="",T206,AI16) -> 0 | U16: =IF(AJ16="",U206,AJ16) -> 0 | W16: =E16 -> blank
B17: l | C17: l | E17: blank | F17: =F207 -> 0 | G17: =G207 -> 0 | H17: =H207 -> 0 | I17: =IF(X17="",I207,X17) -> 0 | J17: =IF(Y17="",J207,Y17) -> 0 | K17: =IF(Z17="",K207,Z17) -> 0 | L17: =IF(AA17="",L207,AA17) -> 0 | M17: =SUM(I17:L17) -> 0 | N17: =IF(AC17="",N207,AC17) -> 0 | O17: =IF(AD17="",O207,AD17) -> 0 | P17: =IF(AE17="",P207,AE17) -> 0 | Q17: =IF(AF17="",Q207,AF17) -> 0 | R17: =SUM(N17:Q17) -> 0 | S17: =IF(AH17="",S207,AH17) -> 0 | T17: =IF(AI17="",T207,AI17) -> 0 | U17: =IF(AJ17="",U207,AJ17) -> 0 | W17: =E17 -> blank
B18: l | C18: l | E18: blank | F18: =F208 -> 0 | G18: =G208 -> 0 | H18: =H208 -> 0 | I18: =IF(X18="",I208,X18) -> 0 | J18: =IF(Y18="",J208,Y18) -> 0 | K18: =IF(Z18="",K208,Z18) -> 0 | L18: =IF(AA18="",L208,AA18) -> 0 | M18: =SUM(I18:L18) -> 0 | N18: =IF(AC18="",N208,AC18) -> 0 | O18: =IF(AD18="",O208,AD18) -> 0 | P18: =IF(AE18="",P208,AE18) -> 0 | Q18: =IF(AF18="",Q208,AF18) -> 0 | R18: =SUM(N18:Q18) -> 0 | S18: =IF(AH18="",S208,AH18) -> 0 | T18: =IF(AI18="",T208,AI18) -> 0 | U18: =IF(AJ18="",U208,AJ18) -> 0 | W18: =E18 -> blank
B19: l | C19: l | E19: blank | F19: =F209 -> 0 | G19: =G209 -> 0 | H19: =H209 -> 0 | I19: =IF(X19="",I209,X19) -> 0 | J19: =IF(Y19="",J209,Y19) -> 0 | K19: =IF(Z19="",K209,Z19) -> 0 | L19: =IF(AA19="",L209,AA19) -> 0 | M19: =SUM(I19:L19) -> 0 | N19: =IF(AC19="",N209,AC19) -> 0 | O19: =IF(AD19="",O209,AD19) -> 0 | P19: =IF(AE19="",P209,AE19) -> 0 | Q19: =IF(AF19="",Q209,AF19) -> 0 | R19: =SUM(N19:Q19) -> 0 | S19: =IF(AH19="",S209,AH19) -> 0 | T19: =IF(AI19="",T209,AI19) -> 0 | U19: =IF(AJ19="",U209,AJ19) -> 0 | W19: =E19 -> blank
E20: Total | F20: =SUM(F12:F19) -> 0 | G20: =SUM(G12:G19) -> 0 | H20: =SUM(H12:H19) -> 0 | I20: =SUM(I12:I19) -> 0 | J20: =SUM(J12:J19) -> 0 | K20: =SUM(K12:K19) -> 0 | L20: =SUM(L12:L19) -> 0 | M20: =SUM(M12:M19) -> 0 | ... U20: =SUM(U12:U19) -> 0
E24: Overhead COGS | W24: =E24 -> Overhead COGS
E25: Commerical assumptions 000s | W25: Key In expected Dollar amounts in 000s
F27: =Inputs!$C$7 -> 2023 | G27: =Inputs!$C$8 -> 2024 | H27: =Inputs!$C$9 -> 2025 | I27: Q1 | J27: Q2 | K27: Q3 | L27: Q4 | M27: =Inputs!$C$10 -> 2026 | N27: Q1 | O27: Q2 | P27: Q3 | Q27: Q4 | R27: =Inputs!$C$11 -> 2027 | S27: =Inputs!$C$12 -> 2028 | T27: =Inputs!$C$13 -> 2029 | U27: =Inputs!$C$14 -> 2030 | X27: Q1 | Y27: Q2 | Z27: Q3 | AA27: Q4 | AB27: =Inputs!$C$10 -> 2026 | AC27: Q1 | AD27: Q2 | AE27: Q3 | AF27: Q4 | AG27: =Inputs!$C$11 -> 2027 | AH27: =Inputs!$C$12 -> 2028 | AI27: =Inputs!$C$13 -> 2029 | AJ27: =Inputs!$C$14 -> 2030
F28: (000) | G28: (000) | H28: (000) | I28: (000) | J28: (000) | K28: (000) | L28: (000) | M28: (000) | N28: (000) | O28: (000) | P28: (000) | Q28: (000) | R28: (000) | S28: (000) | T28: (000) | U28: (000) | X28: $ | Y28: $ | Z28: $ | AA28: $ | AC28: $ | AD28: $ | AE28: $ | AF28: $ | AH28: $ | AI28: $ | AJ28: $
B29: l | C29: l | E29: Fixed Mfg | F29: =F219 -> 0 | G29: =G219 -> 0 | H29: =H219 -> 0 | I29: =IF(X29="",I219,X29) -> 0 | J29: =IF(Y29="",J219,Y29) -> 0 | K29: =IF(Z29="",K219,Z29) -> 0 | L29: =IF(AA29="",L219,AA29) -> 0 | M29: =SUM(I29:L29) -> 0 | N29: =IF(AC29="",N219,AC29) -> 0 | O29: =IF(AD29="",O219,AD29) -> 0 | P29: =IF(AE29="",P219,AE29) -> 0 | Q29: =IF(AF29="",Q219,AF29) -> 0 | R29: =SUM(N29:Q29) -> 0 | S29: =IF(AH29="",S219,AH29) -> 0 | T29: =IF(AI29="",T219,AI29) -> 0 | U29: =IF(AJ29="",U219,AJ29) -> 0 | W29: =E29 -> Fixed Mfg
B30: l | C30: l | E30: blank | F30: =F220 -> 0 | G30: =G220 -> 0 | H30: =H220 -> 0 | I30: =IF(X30="",I220,X30) -> 0 | J30: =IF(Y30="",J220,Y30) -> 0 | K30: =IF(Z30="",K220,Z30) -> 0 | L30: =IF(AA30="",L220,AA30) -> 0 | M30: =SUM(I30:L30) -> 0 | N30: =IF(AC30="",N220,AC30) -> 0 | O30: =IF(AD30="",O220,AD30) -> 0 | P30: =IF(AE30="",P220,AE30) -> 0 | Q30: =IF(AF30="",Q220,AF30) -> 0 | R30: =SUM(N30:Q30) -> 0 | S30: =IF(AH30="",S220,AH30) -> 0 | T30: =IF(AI30="",T220,AI30) -> 0 | U30: =IF(AJ30="",U220,AJ30) -> 0 | W30: =E30 -> blank
B31: l | C31: l | E31: blank | F31: =F221 -> 0 | G31: =G221 -> 0 | H31: =H221 -> 0 | I31: =IF(X31="",I221,X31) -> 0 | J31: =IF(Y31="",J221,Y31) -> 0 | K31: =IF(Z31="",K221,Z31) -> 0 | L31: =IF(AA31="",L221,AA31) -> 0 | M31: =SUM(I31:L31) -> 0 | N31: =IF(AC31="",N221,AC31) -> 0 | O31: =IF(AD31="",O221,AD31) -> 0 | P31: =IF(AE31="",P221,AE31) -> 0 | Q31: =IF(AF31="",Q221,AF31) -> 0 | R31: =SUM(N31:Q31) -> 0 | S31: =IF(AH31="",S221,AH31) -> 0 | T31: =IF(AI31="",T221,AI31) -> 0 | U31: =IF(AJ31="",U221,AJ31) -> 0 | W31: =E31 -> blank
B32: l | C32: l | E32: blank | F32: =F222 -> 0 | G32: =G222 -> 0 | H32: =H222 -> 0 | I32: =IF(X32="",I222,X32) -> 0 | J32: =IF(Y32="",J222,Y32) -> 0 | K32: =IF(Z32="",K222,Z32) -> 0 | L32: =IF(AA32="",L222,AA32) -> 0 | M32: =SUM(I32:L32) -> 0 | N32: =IF(AC32="",N222,AC32) -> 0 | O32: =IF(AD32="",O222,AD32) -> 0 | P32: =IF(AE32="",P222,AE32) -> 0 | Q32: =IF(AF32="",Q222,AF32) -> 0 | R32: =SUM(N32:Q32) -> 0 | S32: =IF(AH32="",S222,AH32) -> 0 | T32: =IF(AI32="",T222,AI32) -> 0 | U32: =IF(AJ32="",U222,AJ32) -> 0 | W32: =E32 -> blank
B33: l | C33: l | E33: blank | F33: =F223 -> 0 | G33: =G223 -> 0 | H33: =H223 -> 0 | I33: =IF(X33="",I223,X33) -> 0 | J33: =IF(Y33="",J223,Y33) -> 0 | K33: =IF(Z33="",K223,Z33) -> 0 | L33: =IF(AA33="",L223,AA33) -> 0 | M33: =SUM(I33:L33) -> 0 | N33: =IF(AC33="",N223,AC33) -> 0 | O33: =IF(AD33="",O223,AD33) -> 0 | P33: =IF(AE33="",P223,AE33) -> 0 | Q33: =IF(AF33="",Q223,AF33) -> 0 | R33: =SUM(N33:Q33) -> 0 | S33: =IF(AH33="",S223,AH33) -> 0 | T33: =IF(AI33="",T223,AI33) -> 0 | U33: =IF(AJ33="",U223,AJ33) -> 0 | W33: =E33 -> blank
B34: l | C34: l | E34: blank | F34: =F224 -> 0 | G34: =G224 -> 0 | H34: =H224 -> 0 | I34: =IF(X34="",I224,X34) -> 0 | J34: =IF(Y34="",J224,Y34) -> 0 | K34: =IF(Z34="",K224,Z34) -> 0 | L34: =IF(AA34="",L224,AA34) -> 0 | M34: =SUM(I34:L34) -> 0 | N34: =IF(AC34="",N224,AC34) -> 0 | O34: =IF(AD34="",O224,AD34) -> 0 | P34: =IF(AE34="",P224,AE34) -> 0 | Q34: =IF(AF34="",Q224,AF34) -> 0 | R34: =SUM(N34:Q34) -> 0 | S34: =IF(AH34="",S224,AH34) -> 0 | T34: =IF(AI34="",T224,AI34) -> 0 | U34: =IF(AJ34="",U224,AJ34) -> 0 | W34: =E34 -> blank
B35: l | C35: l | E35: blank | F35: =F225 -> 0 | G35: =G225 -> 0 | H35: =H225 -> 0 | I35: =IF(X35="",I225,X35) -> 0 | J35: =IF(Y35="",J225,Y35) -> 0 | K35: =IF(Z35="",K225,Z35) -> 0 | L35: =IF(AA35="",L225,AA35) -> 0 | M35: =SUM(I35:L35) -> 0 | N35: =IF(AC35="",N225,AC35) -> 0 | O35: =IF(AD35="",O225,AD35) -> 0 | P35: =IF(AE35="",P225,AE35) -> 0 | Q35: =IF(AF35="",Q225,AF35) -> 0 | R35: =SUM(N35:Q35) -> 0 | S35: =IF(AH35="",S225,AH35) -> 0 | T35: =IF(AI35="",T225,AI35) -> 0 | U35: =IF(AJ35="",U225,AJ35) -> 0 | W35: =E35 -> blank
B36: l | C36: l | E36: blank | F36: =F226 -> 0 | G36: =G226 -> 0 | H36: =H226 -> 0 | I36: =IF(X36="",I226,X36) -> 0 | J36: =IF(Y36="",J226,Y36) -> 0 | K36: =IF(Z36="",K226,Z36) -> 0 | L36: =IF(AA36="",L226,AA36) -> 0 | M36: =SUM(I36:L36) -> 0 | N36: =IF(AC36="",N226,AC36) -> 0 | O36: =IF(AD36="",O226,AD36) -> 0 | P36: =IF(AE36="",P226,AE36) -> 0 | Q36: =IF(AF36="",Q226,AF36) -> 0 | R36: =SUM(N36:Q36) -> 0 | S36: =IF(AH36="",S226,AH36) -> 0 | T36: =IF(AI36="",T226,AI36) -> 0 | U36: =IF(AJ36="",U226,AJ36) -> 0 | W36: =E36 -> blank
E37: Total | F37: =SUM(F29:F36) -> 0 | G37: =SUM(G29:G36) -> 0 | H37: =SUM(H29:H36) -> 0 | I37: =SUM(I29:I36) -> 0 | J37: =SUM(J29:J36) -> 0 | K37: =SUM(K29:K36) -> 0 | L37: =SUM(L29:L36) -> 0 | M37: =SUM(M29:M36) -> 0 | ... U37: =SUM(U29:U36) -> 0
B41: Cash | C41: P&L | E41: ="Scenario 2: "&Inputs!B23 -> Scenario 2: Scenario 2
E42: =Inputs!C23 -> Scenario 2 Description
E45: Variances | W45: Variances
E46: Commerical assumptions 000s | W46: Key In expected Dollar amounts in 000s
F48: =Inputs!$C$7 -> 2023 | G48: =Inputs!$C$8 -> 2024 | H48: =Inputs!$C$9 -> 2025 | I48: Q1 | J48: Q2 | K48: Q3 | L48: Q4 | M48: =Inputs!$C$10 -> 2026 | N48: Q1 | O48: Q2 | P48: Q3 | Q48: Q4 | R48: =Inputs!$C$11 -> 2027 | S48: =Inputs!$C$12 -> 2028 | T48: =Inputs!$C$13 -> 2029 | U48: =Inputs!$C$14 -> 2030 | X48: Q1 | Y48: Q2 | Z48: Q3 | AA48: Q4 | AB48: =Inputs!$C$10 -> 2026 | AC48: Q1 | AD48: Q2 | AE48: Q3 | AF48: Q4 | AG48: =Inputs!$C$11 -> 2027 | AH48: =Inputs!$C$12 -> 2028 | AI48: =Inputs!$C$13 -> 2029 | AJ48: =Inputs!$C$14 -> 2030
F49: (000) | G49: (000) | H49: (000) | I49: (000) | J49: (000) | K49: (000) | L49: (000) | M49: (000) | N49: (000) | O49: (000) | P49: (000) | Q49: (000) | R49: (000) | S49: (000) | T49: (000) | U49: (000) | X49: $ | Y49: $ | Z49: $ | AA49: $ | AC49: $ | AD49: $ | AE49: $ | AF49: $ | AH49: $ | AI49: $ | AJ49: $
B50: l | C50: l | E50: Variances | F50: =F202 -> 0 | G50: =G202 -> 0 | H50: =H202 -> 0 | I50: =IF(X50="",I202,X50) -> 0 | J50: =IF(Y50="",J202,Y50) -> 0 | K50: =IF(Z50="",K202,Z50) -> 0 | L50: =IF(AA50="",L202,AA50) -> 0 | M50: =SUM(I50:L50) -> 0 | N50: =IF(AC50="",N202,AC50) -> 0 | O50: =IF(AD50="",O202,AD50) -> 0 | P50: =IF(AE50="",P202,AE50) -> 0 | Q50: =IF(AF50="",Q202,AF50) -> 0 | R50: =SUM(N50:Q50) -> 0 | S50: =IF(AH50="",S202,AH50) -> 0 | T50: =IF(AI50="",T202,AI50) -> 0 | U50: =IF(AJ50="",U202,AJ50) -> 0 | W50: =E50 -> Variances
B51: l | C51: l | E51: Exchange Gain/Loss | F51: =F203 -> 0 | G51: =G203 -> 0 | H51: =H203 -> 0 | I51: =IF(X51="",I203,X51) -> 0 | J51: =IF(Y51="",J203,Y51) -> 0 | K51: =IF(Z51="",K203,Z51) -> 0 | L51: =IF(AA51="",L203,AA51) -> 0 | M51: =SUM(I51:L51) -> 0 | N51: =IF(AC51="",N203,AC51) -> 0 | O51: =IF(AD51="",O203,AD51) -> 0 | P51: =IF(AE51="",P203,AE51) -> 0 | Q51: =IF(AF51="",Q203,AF51) -> 0 | R51: =SUM(N51:Q51) -> 0 | S51: =IF(AH51="",S203,AH51) -> 0 | T51: =IF(AI51="",T203,AI51) -> 0 | U51: =IF(AJ51="",U203,AJ51) -> 0 | W51: =E51 -> Exchange Gain/Loss
B52: l | C52: l | E52: blank | F52: =F204 -> 0 | G52: =G204 -> 0 | H52: =H204 -> 0 | I52: =IF(X52="",I204,X52) -> 0 | J52: =IF(Y52="",J204,Y52) -> 0 | K52: =IF(Z52="",K204,Z52) -> 0 | L52: =IF(AA52="",L204,AA52) -> 0 | M52: =SUM(I52:L52) -> 0 | N52: =IF(AC52="",N204,AC52) -> 0 | O52: =IF(AD52="",O204,AD52) -> 0 | P52: =IF(AE52="",P204,AE52) -> 0 | Q52: =IF(AF52="",Q204,AF52) -> 0 | R52: =SUM(N52:Q52) -> 0 | S52: =IF(AH52="",S204,AH52) -> 0 | T52: =IF(AI52="",T204,AI52) -> 0 | U52: =IF(AJ52="",U204,AJ52) -> 0 | W52: =E52 -> blank
B53: l | C53: l | E53: blank | F53: =F205 -> 0 | G53: =G205 -> 0 | H53: =H205 -> 0 | I53: =IF(X53="",I205,X53) -> 0 | J53: =IF(Y53="",J205,Y53) -> 0 | K53: =IF(Z53="",K205,Z53) -> 0 | L53: =IF(AA53="",L205,AA53) -> 0 | M53: =SUM(I53:L53) -> 0 | N53: =IF(AC53="",N205,AC53) -> 0 | O53: =IF(AD53="",O205,AD53) -> 0 | P53: =IF(AE53="",P205,AE53) -> 0 | Q53: =IF(AF53="",Q205,AF53) -> 0 | R53: =SUM(N53:Q53) -> 0 | S53: =IF(AH53="",S205,AH53) -> 0 | T53: =IF(AI53="",T205,AI53) -> 0 | U53: =IF(AJ53="",U205,AJ53) -> 0 | W53: =E53 -> blank
B54: l | C54: l | E54: blank | F54: =F206 -> 0 | G54: =G206 -> 0 | H54: =H206 -> 0 | I54: =IF(X54="",I206,X54) -> 0 | J54: =IF(Y54="",J206,Y54) -> 0 | K54: =IF(Z54="",K206,Z54) -> 0 | L54: =IF(AA54="",L206,AA54) -> 0 | M54: =SUM(I54:L54) -> 0 | N54: =IF(AC54="",N206,AC54) -> 0 | O54: =IF(AD54="",O206,AD54) -> 0 | P54: =IF(AE54="",P206,AE54) -> 0 | Q54: =IF(AF54="",Q206,AF54) -> 0 | R54: =SUM(N54:Q54) -> 0 | S54: =IF(AH54="",S206,AH54) -> 0 | T54: =IF(AI54="",T206,AI54) -> 0 | U54: =IF(AJ54="",U206,AJ54) -> 0 | W54: =E54 -> blank
B55: l | C55: l | E55: blank | F55: =F207 -> 0 | G55: =G207 -> 0 | H55: =H207 -> 0 | I55: =IF(X55="",I207,X55) -> 0 | J55: =IF(Y55="",J207,Y55) -> 0 | K55: =IF(Z55="",K207,Z55) -> 0 | L55: =IF(AA55="",L207,AA55) -> 0 | M55: =SUM(I55:L55) -> 0 | N55: =IF(AC55="",N207,AC55) -> 0 | O55: =IF(AD55="",O207,AD55) -> 0 | P55: =IF(AE55="",P207,AE55) -> 0 | Q55: =IF(AF55="",Q207,AF55) -> 0 | R55: =SUM(N55:Q55) -> 0 | S55: =IF(AH55="",S207,AH55) -> 0 | T55: =IF(AI55="",T207,AI55) -> 0 | U55: =IF(AJ55="",U207,AJ55) -> 0 | W55: =E55 -> blank
B56: l | C56: l | E56: blank | F56: =F208 -> 0 | G56: =G208 -> 0 | H56: =H208 -> 0 | I56: =IF(X56="",I208,X56) -> 0 | J56: =IF(Y56="",J208,Y56) -> 0 | K56: =IF(Z56="",K208,Z56) -> 0 | L56: =IF(AA56="",L208,AA56) -> 0 | M56: =SUM(I56:L56) -> 0 | N56: =IF(AC56="",N208,AC56) -> 0 | O56: =IF(AD56="",O208,AD56) -> 0 | P56: =IF(AE56="",P208,AE56) -> 0 | Q56: =IF(AF56="",Q208,AF56) -> 0 | R56: =SUM(N56:Q56) -> 0 | S56: =IF(AH56="",S208,AH56) -> 0 | T56: =IF(AI56="",T208,AI56) -> 0 | U56: =IF(AJ56="",U208,AJ56) -> 0 | W56: =E56 -> blank
B57: l | C57: l | E57: blank | F57: =F209 -> 0 | G57: =G209 -> 0 | H57: =H209 -> 0 | I57: =IF(X57="",I209,X57) -> 0 | J57: =IF(Y57="",J209,Y57) -> 0 | K57: =IF(Z57="",K209,Z57) -> 0 | L57: =IF(AA57="",L209,AA57) -> 0 | M57: =SUM(I57:L57) -> 0 | N57: =IF(AC57="",N209,AC57) -> 0 | O57: =IF(AD57="",O209,AD57) -> 0 | P57: =IF(AE57="",P209,AE57) -> 0 | Q57: =IF(AF57="",Q209,AF57) -> 0 | R57: =SUM(N57:Q57) -> 0 | S57: =IF(AH57="",S209,AH57) -> 0 | T57: =IF(AI57="",T209,AI57) -> 0 | U57: =IF(AJ57="",U209,AJ57) -> 0 | W57: =E57 -> blank
E58: Total | F58: =SUM(F50:F57) -> 0 | G58: =SUM(G50:G57) -> 0 | H58: =SUM(H50:H57) -> 0 | I58: =SUM(I50:I57) -> 0 | J58: =SUM(J50:J57) -> 0 | K58: =SUM(K50:K57) -> 0 | L58: =SUM(L50:L57) -> 0 | M58: =SUM(M50:M57) -> 0 | ... U58: =SUM(U50:U57) -> 0
E62: Overhead COGS | W62: Overhead COGS
E63: Commerical assumptions 000s | W63: Key In expected Dollar amounts in 000s
F65: =Inputs!$C$7 -> 2023 | G65: =Inputs!$C$8 -> 2024 | H65: =Inputs!$C$9 -> 2025 | I65: Q1 | J65: Q2 | K65: Q3 | L65: Q4 | M65: =Inputs!$C$10 -> 2026 | N65: Q1 | O65: Q2 | P65: Q3 | Q65: Q4 | R65: =Inputs!$C$11 -> 2027 | S65: =Inputs!$C$12 -> 2028 | T65: =Inputs!$C$13 -> 2029 | U65: =Inputs!$C$14 -> 2030 | X65: Q1 | Y65: Q2 | Z65: Q3 | AA65: Q4 | AB65: =Inputs!$C$10 -> 2026 | AC65: Q1 | AD65: Q2 | AE65: Q3 | AF65: Q4 | AG65: =Inputs!$C$11 -> 2027 | AH65: =Inputs!$C$12 -> 2028 | AI65: =Inputs!$C$13 -> 2029 | AJ65: =Inputs!$C$14 -> 2030
F66: (000) | G66: (000) | H66: (000) | I66: (000) | J66: (000) | K66: (000) | L66: (000) | M66: (000) | N66: (000) | O66: (000) | P66: (000) | Q66: (000) | R66: (000) | S66: (000) | T66: (000) | U66: (000) | X66: $ | Y66: $ | Z66: $ | AA66: $ | AC66: $ | AD66: $ | AE66: $ | AF66: $ | AH66: $ | AI66: $ | AJ66: $
B67: l | C67: l | E67: Fixed Mfg | F67: =F219 -> 0 | G67: =G219 -> 0 | H67: =H219 -> 0 | I67: =IF(X67="",I219,X67) -> 0 | J67: =IF(Y67="",J219,Y67) -> 0 | K67: =IF(Z67="",K219,Z67) -> 0 | L67: =IF(AA67="",L219,AA67) -> 0 | M67: =SUM(I67:L67) -> 0 | N67: =IF(AC67="",N219,AC67) -> 0 | O67: =IF(AD67="",O219,AD67) -> 0 | P67: =IF(AE67="",P219,AE67) -> 0 | Q67: =IF(AF67="",Q219,AF67) -> 0 | R67: =SUM(N67:Q67) -> 0 | S67: =IF(AH67="",S219,AH67) -> 0 | T67: =IF(AI67="",T219,AI67) -> 0 | U67: =IF(AJ67="",U219,AJ67) -> 0 | W67: =E67 -> Fixed Mfg
B68: l | C68: l | E68: blank | F68: =F220 -> 0 | G68: =G220 -> 0 | H68: =H220 -> 0 | I68: =IF(X68="",I220,X68) -> 0 | J68: =IF(Y68="",J220,Y68) -> 0 | K68: =IF(Z68="",K220,Z68) -> 0 | L68: =IF(AA68="",L220,AA68) -> 0 | M68: =SUM(I68:L68) -> 0 | N68: =IF(AC68="",N220,AC68) -> 0 | O68: =IF(AD68="",O220,AD68) -> 0 | P68: =IF(AE68="",P220,AE68) -> 0 | Q68: =IF(AF68="",Q220,AF68) -> 0 | R68: =SUM(N68:Q68) -> 0 | S68: =IF(AH68="",S220,AH68) -> 0 | T68: =IF(AI68="",T220,AI68) -> 0 | U68: =IF(AJ68="",U220,AJ68) -> 0 | W68: =E68 -> blank
B69: l | C69: l | E69: blank | F69: =F221 -> 0 | G69: =G221 -> 0 | H69: =H221 -> 0 | I69: =IF(X69="",I221,X69) -> 0 | J69: =IF(Y69="",J221,Y69) -> 0 | K69: =IF(Z69="",K221,Z69) -> 0 | L69: =IF(AA69="",L221,AA69) -> 0 | M69: =SUM(I69:L69) -> 0 | N69: =IF(AC69="",N221,AC69) -> 0 | O69: =IF(AD69="",O221,AD69) -> 0 | P69: =IF(AE69="",P221,AE69) -> 0 | Q69: =IF(AF69="",Q221,AF69) -> 0 | R69: =SUM(N69:Q69) -> 0 | S69: =IF(AH69="",S221,AH69) -> 0 | T69: =IF(AI69="",T221,AI69) -> 0 | U69: =IF(AJ69="",U221,AJ69) -> 0 | W69: =E69 -> blank
B70: l | C70: l | E70: blank | F70: =F222 -> 0 | G70: =G222 -> 0 | H70: =H222 -> 0 | I70: =IF(X70="",I222,X70) -> 0 | J70: =IF(Y70="",J222,Y70) -> 0 | K70: =IF(Z70="",K222,Z70) -> 0 | L70: =IF(AA70="",L222,AA70) -> 0 | M70: =SUM(I70:L70) -> 0 | N70: =IF(AC70="",N222,AC70) -> 0 | O70: =IF(AD70="",O222,AD70) -> 0 | P70: =IF(AE70="",P222,AE70) -> 0 | Q70: =IF(AF70="",Q222,AF70) -> 0 | R70: =SUM(N70:Q70) -> 0 | S70: =IF(AH70="",S222,AH70) -> 0 | T70: =IF(AI70="",T222,AI70) -> 0 | U70: =IF(AJ70="",U222,AJ70) -> 0 | W70: =E70 -> blank
B71: l | C71: l | E71: blank | F71: =F223 -> 0 | G71: =G223 -> 0 | H71: =H223 -> 0 | I71: =IF(X71="",I223,X71) -> 0 | J71: =IF(Y71="",J223,Y71) -> 0 | K71: =IF(Z71="",K223,Z71) -> 0 | L71: =IF(AA71="",L223,AA71) -> 0 | M71: =SUM(I71:L71) -> 0 | N71: =IF(AC71="",N223,AC71) -> 0 | O71: =IF(AD71="",O223,AD71) -> 0 | P71: =IF(AE71="",P223,AE71) -> 0 | Q71: =IF(AF71="",Q223,AF71) -> 0 | R71: =SUM(N71:Q71) -> 0 | S71: =IF(AH71="",S223,AH71) -> 0 | T71: =IF(AI71="",T223,AI71) -> 0 | U71: =IF(AJ71="",U223,AJ71) -> 0 | W71: =E71 -> blank
B72: l | C72: l | E72: blank | F72: =F224 -> 0 | G72: =G224 -> 0 | H72: =H224 -> 0 | I72: =IF(X72="",I224,X72) -> 0 | J72: =IF(Y72="",J224,Y72) -> 0 | K72: =IF(Z72="",K224,Z72) -> 0 | L72: =IF(AA72="",L224,AA72) -> 0 | M72: =SUM(I72:L72) -> 0 | N72: =IF(AC72="",N224,AC72) -> 0 | O72: =IF(AD72="",O224,AD72) -> 0 | P72: =IF(AE72="",P224,AE72) -> 0 | Q72: =IF(AF72="",Q224,AF72) -> 0 | R72: =SUM(N72:Q72) -> 0 | S72: =IF(AH72="",S224,AH72) -> 0 | T72: =IF(AI72="",T224,AI72) -> 0 | U72: =IF(AJ72="",U224,AJ72) -> 0 | W72: =E72 -> blank
B73: l | C73: l | E73: blank | F73: =F225 -> 0 | G73: =G225 -> 0 | H73: =H225 -> 0 | I73: =IF(X73="",I225,X73) -> 0 | J73: =IF(Y73="",J225,Y73) -> 0 | K73: =IF(Z73="",K225,Z73) -> 0 | L73: =IF(AA73="",L225,AA73) -> 0 | M73: =SUM(I73:L73) -> 0 | N73: =IF(AC73="",N225,AC73) -> 0 | O73: =IF(AD73="",O225,AD73) -> 0 | P73: =IF(AE73="",P225,AE73) -> 0 | Q73: =IF(AF73="",Q225,AF73) -> 0 | R73: =SUM(N73:Q73) -> 0 | S73: =IF(AH73="",S225,AH73) -> 0 | T73: =IF(AI73="",T225,AI73) -> 0 | U73: =IF(AJ73="",U225,AJ73) -> 0 | W73: =E73 -> blank
B74: l | C74: l | E74: blank | F74: =F226 -> 0 | G74: =G226 -> 0 | H74: =H226 -> 0 | I74: =IF(X74="",I226,X74) -> 0 | J74: =IF(Y74="",J226,Y74) -> 0 | K74: =IF(Z74="",K226,Z74) -> 0 | L74: =IF(AA74="",L226,AA74) -> 0 | M74: =SUM(I74:L74) -> 0 | N74: =IF(AC74="",N226,AC74) -> 0 | O74: =IF(AD74="",O226,AD74) -> 0 | P74: =IF(AE74="",P226,AE74) -> 0 | Q74: =IF(AF74="",Q226,AF74) -> 0 | R74: =SUM(N74:Q74) -> 0 | S74: =IF(AH74="",S226,AH74) -> 0 | T74: =IF(AI74="",T226,AI74) -> 0 | U74: =IF(AJ74="",U226,AJ74) -> 0 | W74: =E74 -> blank
E75: Total | F75: =SUM(F67:F74) -> 0 | G75: =SUM(G67:G74) -> 0 | H75: =SUM(H67:H74) -> 0 | I75: =SUM(I67:I74) -> 0 | J75: =SUM(J67:J74) -> 0 | K75: =SUM(K67:K74) -> 0 | L75: =SUM(L67:L74) -> 0 | M75: =SUM(M67:M74) -> 0 | ... U75: =SUM(U67:U74) -> 0
B79: Cash | C79: P&L | E79: ="Scenario 3: "&Inputs!B24 -> Scenario 3: Scenario 3
E80: =Inputs!C24 -> Scenario 3 Description
E83: Variances | W83: Variances
E84: Commerical assumptions 000s | W84: Key In expected Dollar amounts in 000s
F86: =Inputs!$C$7 -> 2023 | G86: =Inputs!$C$8 -> 2024 | H86: =Inputs!$C$9 -> 2025 | I86: Q1 | J86: Q2 | K86: Q3 | L86: Q4 | M86: =Inputs!$C$10 -> 2026 | N86: Q1 | O86: Q2 | P86: Q3 | Q86: Q4 | R86: =Inputs!$C$11 -> 2027 | S86: =Inputs!$C$12 -> 2028 | T86: =Inputs!$C$13 -> 2029 | U86: =Inputs!$C$14 -> 2030 | X86: Q1 | Y86: Q2 | Z86: Q3 | AA86: Q4 | AB86: =Inputs!$C$10 -> 2026 | AC86: Q1 | AD86: Q2 | AE86: Q3 | AF86: Q4 | AG86: =Inputs!$C$11 -> 2027 | AH86: =Inputs!$C$12 -> 2028 | AI86: =Inputs!$C$13 -> 2029 | AJ86: =Inputs!$C$14 -> 2030
F87: (000) | G87: (000) | H87: (000) | I87: (000) | J87: (000) | K87: (000) | L87: (000) | M87: (000) | N87: (000) | O87: (000) | P87: (000) | Q87: (000) | R87: (000) | S87: (000) | T87: (000) | U87: (000) | X87: $ | Y87: $ | Z87: $ | AA87: $ | AC87: $ | AD87: $ | AE87: $ | AF87: $ | AH87: $ | AI87: $ | AJ87: $
B88: l | C88: l | E88: Variances | F88: =F202 -> 0 | G88: =G202 -> 0 | H88: =H202 -> 0 | I88: =IF(X88="",I202,X88) -> 0 | J88: =IF(Y88="",J202,Y88) -> 0 | K88: =IF(Z88="",K202,Z88) -> 0 | L88: =IF(AA88="",L202,AA88) -> 0 | M88: =SUM(I88:L88) -> 0 | N88: =IF(AC88="",N202,AC88) -> 0 | O88: =IF(AD88="",O202,AD88) -> 0 | P88: =IF(AE88="",P202,AE88) -> 0 | Q88: =IF(AF88="",Q202,AF88) -> 0 | R88: =SUM(N88:Q88) -> 0 | S88: =IF(AH88="",S202,AH88) -> 0 | T88: =IF(AI88="",T202,AI88) -> 0 | U88: =IF(AJ88="",U202,AJ88) -> 0 | W88: =E88 -> Variances
B89: l | C89: l | E89: Exchange Gain/Loss | F89: =F203 -> 0 | G89: =G203 -> 0 | H89: =H203 -> 0 | I89: =IF(X89="",I203,X89) -> 0 | J89: =IF(Y89="",J203,Y89) -> 0 | K89: =IF(Z89="",K203,Z89) -> 0 | L89: =IF(AA89="",L203,AA89) -> 0 | M89: =SUM(I89:L89) -> 0 | N89: =IF(AC89="",N203,AC89) -> 0 | O89: =IF(AD89="",O203,AD89) -> 0 | P89: =IF(AE89="",P203,AE89) -> 0 | Q89: =IF(AF89="",Q203,AF89) -> 0 | R89: =SUM(N89:Q89) -> 0 | S89: =IF(AH89="",S203,AH89) -> 0 | T89: =IF(AI89="",T203,AI89) -> 0 | U89: =IF(AJ89="",U203,AJ89) -> 0 | W89: =E89 -> Exchange Gain/Loss
B90: l | C90: l | E90: blank | F90: =F204 -> 0 | G90: =G204 -> 0 | H90: =H204 -> 0 | I90: =IF(X90="",I204,X90) -> 0 | J90: =IF(Y90="",J204,Y90) -> 0 | K90: =IF(Z90="",K204,Z90) -> 0 | L90: =IF(AA90="",L204,AA90) -> 0 | M90: =SUM(I90:L90) -> 0 | N90: =IF(AC90="",N204,AC90) -> 0 | O90: =IF(AD90="",O204,AD90) -> 0 | P90: =IF(AE90="",P204,AE90) -> 0 | Q90: =IF(AF90="",Q204,AF90) -> 0 | R90: =SUM(N90:Q90) -> 0 | S90: =IF(AH90="",S204,AH90) -> 0 | T90: =IF(AI90="",T204,AI90) -> 0 | U90: =IF(AJ90="",U204,AJ90) -> 0 | W90: =E90 -> blank
B91: l | C91: l | E91: blank | F91: =F205 -> 0 | G91: =G205 -> 0 | H91: =H205 -> 0 | I91: =IF(X91="",I205,X91) -> 0 | J91: =IF(Y91="",J205,Y91) -> 0 | K91: =IF(Z91="",K205,Z91) -> 0 | L91: =IF(AA91="",L205,AA91) -> 0 | M91: =SUM(I91:L91) -> 0 | N91: =IF(AC91="",N205,AC91) -> 0 | O91: =IF(AD91="",O205,AD91) -> 0 | P91: =IF(AE91="",P205,AE91) -> 0 | Q91: =IF(AF91="",Q205,AF91) -> 0 | R91: =SUM(N91:Q91) -> 0 | S91: =IF(AH91="",S205,AH91) -> 0 | T91: =IF(AI91="",T205,AI91) -> 0 | U91: =IF(AJ91="",U205,AJ91) -> 0 | W91: =E91 -> blank
B92: l | C92: l | E92: blank | F92: =F206 -> 0 | G92: =G206 -> 0 | H92: =H206 -> 0 | I92: =IF(X92="",I206,X92) -> 0 | J92: =IF(Y92="",J206,Y92) -> 0 | K92: =IF(Z92="",K206,Z92) -> 0 | L92: =IF(AA92="",L206,AA92) -> 0 | M92: =SUM(I92:L92) -> 0 | N92: =IF(AC92="",N206,AC92) -> 0 | O92: =IF(AD92="",O206,AD92) -> 0 | P92: =IF(AE92="",P206,AE92) -> 0 | Q92: =IF(AF92="",Q206,AF92) -> 0 | R92: =SUM(N92:Q92) -> 0 | S92: =IF(AH92="",S206,AH92) -> 0 | T92: =IF(AI92="",T206,AI92) -> 0 | U92: =IF(AJ92="",U206,AJ92) -> 0 | W92: =E92 -> blank
B93: l | C93: l | E93: blank | F93: =F207 -> 0 | G93: =G207 -> 0 | H93: =H207 -> 0 | I93: =IF(X93="",I207,X93) -> 0 | J93: =IF(Y93="",J207,Y93) -> 0 | K93: =IF(Z93="",K207,Z93) -> 0 | L93: =IF(AA93="",L207,AA93) -> 0 | M93: =SUM(I93:L93) -> 0 | N93: =IF(AC93="",N207,AC93) -> 0 | O93: =IF(AD93="",O207,AD93) -> 0 | P93: =IF(AE93="",P207,AE93) -> 0 | Q93: =IF(AF93="",Q207,AF93) -> 0 | R93: =SUM(N93:Q93) -> 0 | S93: =IF(AH93="",S207,AH93) -> 0 | T93: =IF(AI93="",T207,AI93) -> 0 | U93: =IF(AJ93="",U207,AJ93) -> 0 | W93: =E93 -> blank
B94: l | C94: l | E94: blank | F94: =F208 -> 0 | G94: =G208 -> 0 | H94: =H208 -> 0 | I94: =IF(X94="",I208,X94) -> 0 | J94: =IF(Y94="",J208,Y94) -> 0 | K94: =IF(Z94="",K208,Z94) -> 0 | L94: =IF(AA94="",L208,AA94) -> 0 | M94: =SUM(I94:L94) -> 0 | N94: =IF(AC94="",N208,AC94) -> 0 | O94: =IF(AD94="",O208,AD94) -> 0 | P94: =IF(AE94="",P208,AE94) -> 0 | Q94: =IF(AF94="",Q208,AF94) -> 0 | R94: =SUM(N94:Q94) -> 0 | S94: =IF(AH94="",S208,AH94) -> 0 | T94: =IF(AI94="",T208,AI94) -> 0 | U94: =IF(AJ94="",U208,AJ94) -> 0 | W94: =E94 -> blank
B95: l | C95: l | E95: blank | F95: =F209 -> 0 | G95: =G209 -> 0 | H95: =H209 -> 0 | I95: =IF(X95="",I209,X95) -> 0 | J95: =IF(Y95="",J209,Y95) -> 0 | K95: =IF(Z95="",K209,Z95) -> 0 | L95: =IF(AA95="",L209,AA95) -> 0 | M95: =SUM(I95:L95) -> 0 | N95: =IF(AC95="",N209,AC95) -> 0 | O95: =IF(AD95="",O209,AD95) -> 0 | P95: =IF(AE95="",P209,AE95) -> 0 | Q95: =IF(AF95="",Q209,AF95) -> 0 | R95: =SUM(N95:Q95) -> 0 | S95: =IF(AH95="",S209,AH95) -> 0 | T95: =IF(AI95="",T209,AI95) -> 0 | U95: =IF(AJ95="",U209,AJ95) -> 0 | W95: =E95 -> blank
E96: Total | F96: =SUM(F88:F95) -> 0 | G96: =SUM(G88:G95) -> 0 | H96: =SUM(H88:H95) -> 0 | I96: =SUM(I88:I95) -> 0 | J96: =SUM(J88:J95) -> 0 | K96: =SUM(K88:K95) -> 0 | L96: =SUM(L88:L95) -> 0 | M96: =SUM(M88:M95) -> 0 | ... U96: =SUM(U88:U95) -> 0
E100: Overhead COGS | W100: Overhead COGS
E101: Commerical assumptions 000s | W101: Key In expected Dollar amounts in 000s
F103: =Inputs!$C$7 -> 2023 | G103: =Inputs!$C$8 -> 2024 | H103: =Inputs!$C$9 -> 2025 | I103: Q1 | J103: Q2 | K103: Q3 | L103: Q4 | M103: =Inputs!$C$10 -> 2026 | N103: Q1 | O103: Q2 | P103: Q3 | Q103: Q4 | R103: =Inputs!$C$11 -> 2027 | S103: =Inputs!$C$12 -> 2028 | T103: =Inputs!$C$13 -> 2029 | U103: =Inputs!$C$14 -> 2030 | X103: Q1 | Y103: Q2 | Z103: Q3 | AA103: Q4 | AB103: =Inputs!$C$10 -> 2026 | AC103: Q1 | AD103: Q2 | AE103: Q3 | AF103: Q4 | AG103: =Inputs!$C$11 -> 2027 | AH103: =Inputs!$C$12 -> 2028 | AI103: =Inputs!$C$13 -> 2029 | AJ103: =Inputs!$C$14 -> 2030
F104: (000) | G104: (000) | H104: (000) | I104: (000) | J104: (000) | K104: (000) | L104: (000) | M104: (000) | N104: (000) | O104: (000) | P104: (000) | Q104: (000) | R104: (000) | S104: (000) | T104: (000) | U104: (000) | X104: $ | Y104: $ | Z104: $ | AA104: $ | AC104: $ | AD104: $ | AE104: $ | AF104: $ | AH104: $ | AI104: $ | AJ104: $
B105: l | C105: l | E105: Fixed Mfg | F105: =F219 -> 0 | G105: =G219 -> 0 | H105: =H219 -> 0 | I105: =IF(X105="",I219,X105) -> 0 | J105: =IF(Y105="",J219,Y105) -> 0 | K105: =IF(Z105="",K219,Z105) -> 0 | L105: =IF(AA105="",L219,AA105) -> 0 | M105: =SUM(I105:L105) -> 0 | N105: =IF(AC105="",N219,AC105) -> 0 | O105: =IF(AD105="",O219,AD105) -> 0 | P105: =IF(AE105="",P219,AE105) -> 0 | Q105: =IF(AF105="",Q219,AF105) -> 0 | R105: =SUM(N105:Q105) -> 0 | S105: =IF(AH105="",S219,AH105) -> 0 | T105: =IF(AI105="",T219,AI105) -> 0 | U105: =IF(AJ105="",U219,AJ105) -> 0 | W105: =E105 -> Fixed Mfg
B106: l | C106: l | E106: blank | F106: =F220 -> 0 | G106: =G220 -> 0 | H106: =H220 -> 0 | I106: =IF(X106="",I220,X106) -> 0 | J106: =IF(Y106="",J220,Y106) -> 0 | K106: =IF(Z106="",K220,Z106) -> 0 | L106: =IF(AA106="",L220,AA106) -> 0 | M106: =SUM(I106:L106) -> 0 | N106: =IF(AC106="",N220,AC106) -> 0 | O106: =IF(AD106="",O220,AD106) -> 0 | P106: =IF(AE106="",P220,AE106) -> 0 | Q106: =IF(AF106="",Q220,AF106) -> 0 | R106: =SUM(N106:Q106) -> 0 | S106: =IF(AH106="",S220,AH106) -> 0 | T106: =IF(AI106="",T220,AI106) -> 0 | U106: =IF(AJ106="",U220,AJ106) -> 0 | W106: =E106 -> blank
B107: l | C107: l | E107: blank | F107: =F221 -> 0 | G107: =G221 -> 0 | H107: =H221 -> 0 | I107: =IF(X107="",I221,X107) -> 0 | J107: =IF(Y107="",J221,Y107) -> 0 | K107: =IF(Z107="",K221,Z107) -> 0 | L107: =IF(AA107="",L221,AA107) -> 0 | M107: =SUM(I107:L107) -> 0 | N107: =IF(AC107="",N221,AC107) -> 0 | O107: =IF(AD107="",O221,AD107) -> 0 | P107: =IF(AE107="",P221,AE107) -> 0 | Q107: =IF(AF107="",Q221,AF107) -> 0 | R107: =SUM(N107:Q107) -> 0 | S107: =IF(AH107="",S221,AH107) -> 0 | T107: =IF(AI107="",T221,AI107) -> 0 | U107: =IF(AJ107="",U221,AJ107) -> 0 | W107: =E107 -> blank
B108: l | C108: l | E108: blank | F108: =F222 -> 0 | G108: =G222 -> 0 | H108: =H222 -> 0 | I108: =IF(X108="",I222,X108) -> 0 | J108: =IF(Y108="",J222,Y108) -> 0 | K108: =IF(Z108="",K222,Z108) -> 0 | L108: =IF(AA108="",L222,AA108) -> 0 | M108: =SUM(I108:L108) -> 0 | N108: =IF(AC108="",N222,AC108) -> 0 | O108: =IF(AD108="",O222,AD108) -> 0 | P108: =IF(AE108="",P222,AE108) -> 0 | Q108: =IF(AF108="",Q222,AF108) -> 0 | R108: =SUM(N108:Q108) -> 0 | S108: =IF(AH108="",S222,AH108) -> 0 | T108: =IF(AI108="",T222,AI108) -> 0 | U108: =IF(AJ108="",U222,AJ108) -> 0 | W108: =E108 -> blank
B109: l | C109: l | E109: blank | F109: =F223 -> 0 | G109: =G223 -> 0 | H109: =H223 -> 0 | I109: =IF(X109="",I223,X109) -> 0 | J109: =IF(Y109="",J223,Y109) -> 0 | K109: =IF(Z109="",K223,Z109) -> 0 | L109: =IF(AA109="",L223,AA109) -> 0 | M109: =SUM(I109:L109) -> 0 | N109: =IF(AC109="",N223,AC109) -> 0 | O109: =IF(AD109="",O223,AD109) -> 0 | P109: =IF(AE109="",P223,AE109) -> 0 | Q109: =IF(AF109="",Q223,AF109) -> 0 | R109: =SUM(N109:Q109) -> 0 | S109: =IF(AH109="",S223,AH109) -> 0 | T109: =IF(AI109="",T223,AI109) -> 0 | U109: =IF(AJ109="",U223,AJ109) -> 0 | W109: =E109 -> blank
B110: l | C110: l | E110: blank | F110: =F224 -> 0 | G110: =G224 -> 0 | H110: =H224 -> 0 | I110: =IF(X110="",I224,X110) -> 0 | J110: =IF(Y110="",J224,Y110) -> 0 | K110: =IF(Z110="",K224,Z110) -> 0 | L110: =IF(AA110="",L224,AA110) -> 0 | M110: =SUM(I110:L110) -> 0 | N110: =IF(AC110="",N224,AC110) -> 0 | O110: =IF(AD110="",O224,AD110) -> 0 | P110: =IF(AE110="",P224,AE110) -> 0 | Q110: =IF(AF110="",Q224,AF110) -> 0 | R110: =SUM(N110:Q110) -> 0 | S110: =IF(AH110="",S224,AH110) -> 0 | T110: =IF(AI110="",T224,AI110) -> 0 | U110: =IF(AJ110="",U224,AJ110) -> 0 | W110: =E110 -> blank
B111: l | C111: l | E111: blank | F111: =F225 -> 0 | G111: =G225 -> 0 | H111: =H225 -> 0 | I111: =IF(X111="",I225,X111) -> 0 | J111: =IF(Y111="",J225,Y111) -> 0 | K111: =IF(Z111="",K225,Z111) -> 0 | L111: =IF(AA111="",L225,AA111) -> 0 | M111: =SUM(I111:L111) -> 0 | N111: =IF(AC111="",N225,AC111) -> 0 | O111: =IF(AD111="",O225,AD111) -> 0 | P111: =IF(AE111="",P225,AE111) -> 0 | Q111: =IF(AF111="",Q225,AF111) -> 0 | R111: =SUM(N111:Q111) -> 0 | S111: =IF(AH111="",S225,AH111) -> 0 | T111: =IF(AI111="",T225,AI111) -> 0 | U111: =IF(AJ111="",U225,AJ111) -> 0 | W111: =E111 -> blank
B112: l | C112: l | E112: blank | F112: =F226 -> 0 | G112: =G226 -> 0 | H112: =H226 -> 0 | I112: =IF(X112="",I226,X112) -> 0 | J112: =IF(Y112="",J226,Y112) -> 0 | K112: =IF(Z112="",K226,Z112) -> 0 | L112: =IF(AA112="",L226,AA112) -> 0 | M112: =SUM(I112:L112) -> 0 | N112: =IF(AC112="",N226,AC112) -> 0 | O112: =IF(AD112="",O226,AD112) -> 0 | P112: =IF(AE112="",P226,AE112) -> 0 | Q112: =IF(AF112="",Q226,AF112) -> 0 | R112: =SUM(N112:Q112) -> 0 | S112: =IF(AH112="",S226,AH112) -> 0 | T112: =IF(AI112="",T226,AI112) -> 0 | U112: =IF(AJ112="",U226,AJ112) -> 0 | W112: =E112 -> blank
E113: Total | F113: =SUM(F105:F112) -> 0 | G113: =SUM(G105:G112) -> 0 | H113: =SUM(H105:H112) -> 0 | I113: =SUM(I105:I112) -> 0 | J113: =SUM(J105:J112) -> 0 | K113: =SUM(K105:K112) -> 0 | L113: =SUM(L105:L112) -> 0 | M113: =SUM(M105:M112) -> 0 | ... U113: =SUM(U105:U112) -> 0
B117: Cash | C117: P&L | E117: ="Scenario 4: "&Inputs!B25 -> Scenario 4: Scenario 4
E118: =Inputs!C25 -> Scenario 4 Description
E121: Variances | W121: Variances
E122: Commerical assumptions 000s | W122: Key In expected Dollar amounts in 000s
F124: =Inputs!$C$7 -> 2023 | G124: =Inputs!$C$8 -> 2024 | H124: =Inputs!$C$9 -> 2025 | I124: Q1 | J124: Q2 | K124: Q3 | L124: Q4 | M124: =Inputs!$C$10 -> 2026 | N124: Q1 | O124: Q2 | P124: Q3 | Q124: Q4 | R124: =Inputs!$C$11 -> 2027 | S124: =Inputs!$C$12 -> 2028 | T124: =Inputs!$C$13 -> 2029 | U124: =Inputs!$C$14 -> 2030 | X124: Q1 | Y124: Q2 | Z124: Q3 | AA124: Q4 | AB124: =Inputs!$C$10 -> 2026 | AC124: Q1 | AD124: Q2 | AE124: Q3 | AF124: Q4 | AG124: =Inputs!$C$11 -> 2027 | AH124: =Inputs!$C$12 -> 2028 | AI124: =Inputs!$C$13 -> 2029 | AJ124: =Inputs!$C$14 -> 2030
F125: (000) | G125: (000) | H125: (000) | I125: (000) | J125: (000) | K125: (000) | L125: (000) | M125: (000) | N125: (000) | O125: (000) | P125: (000) | Q125: (000) | R125: (000) | S125: (000) | T125: (000) | U125: (000) | X125: $ | Y125: $ | Z125: $ | AA125: $ | AC125: $ | AD125: $ | AE125: $ | AF125: $ | AH125: $ | AI125: $ | AJ125: $
B126: l | C126: l | E126: Variances | F126: =F202 -> 0 | G126: =G202 -> 0 | H126: =H202 -> 0 | I126: =IF(X126="",I202,X126) -> 0 | J126: =IF(Y126="",J202,Y126) -> 0 | K126: =IF(Z126="",K202,Z126) -> 0 | L126: =IF(AA126="",L202,AA126) -> 0 | M126: =SUM(I126:L126) -> 0 | N126: =IF(AC126="",N202,AC126) -> 0 | O126: =IF(AD126="",O202,AD126) -> 0 | P126: =IF(AE126="",P202,AE126) -> 0 | Q126: =IF(AF126="",Q202,AF126) -> 0 | R126: =SUM(N126:Q126) -> 0 | S126: =IF(AH126="",S202,AH126) -> 0 | T126: =IF(AI126="",T202,AI126) -> 0 | U126: =IF(AJ126="",U202,AJ126) -> 0 | W126: =E126 -> Variances
B127: l | C127: l | E127: Exchange Gain/Loss | F127: =F203 -> 0 | G127: =G203 -> 0 | H127: =H203 -> 0 | I127: =IF(X127="",I203,X127) -> 0 | J127: =IF(Y127="",J203,Y127) -> 0 | K127: =IF(Z127="",K203,Z127) -> 0 | L127: =IF(AA127="",L203,AA127) -> 0 | M127: =SUM(I127:L127) -> 0 | N127: =IF(AC127="",N203,AC127) -> 0 | O127: =IF(AD127="",O203,AD127) -> 0 | P127: =IF(AE127="",P203,AE127) -> 0 | Q127: =IF(AF127="",Q203,AF127) -> 0 | R127: =SUM(N127:Q127) -> 0 | S127: =IF(AH127="",S203,AH127) -> 0 | T127: =IF(AI127="",T203,AI127) -> 0 | U127: =IF(AJ127="",U203,AJ127) -> 0 | W127: =E127 -> Exchange Gain/Loss
B128: l | C128: l | E128: blank | F128: =F204 -> 0 | G128: =G204 -> 0 | H128: =H204 -> 0 | I128: =IF(X128="",I204,X128) -> 0 | J128: =IF(Y128="",J204,Y128) -> 0 | K128: =IF(Z128="",K204,Z128) -> 0 | L128: =IF(AA128="",L204,AA128) -> 0 | M128: =SUM(I128:L128) -> 0 | N128: =IF(AC128="",N204,AC128) -> 0 | O128: =IF(AD128="",O204,AD128) -> 0 | P128: =IF(AE128="",P204,AE128) -> 0 | Q128: =IF(AF128="",Q204,AF128) -> 0 | R128: =SUM(N128:Q128) -> 0 | S128: =IF(AH128="",S204,AH128) -> 0 | T128: =IF(AI128="",T204,AI128) -> 0 | U128: =IF(AJ128="",U204,AJ128) -> 0 | W128: =E128 -> blank
B129: l | C129: l | E129: blank | F129: =F205 -> 0 | G129: =G205 -> 0 | H129: =H205 -> 0 | I129: =IF(X129="",I205,X129) -> 0 | J129: =IF(Y129="",J205,Y129) -> 0 | K129: =IF(Z129="",K205,Z129) -> 0 | L129: =IF(AA129="",L205,AA129) -> 0 | M129: =SUM(I129:L129) -> 0 | N129: =IF(AC129="",N205,AC129) -> 0 | O129: =IF(AD129="",O205,AD129) -> 0 | P129: =IF(AE129="",P205,AE129) -> 0 | Q129: =IF(AF129="",Q205,AF129) -> 0 | R129: =SUM(N129:Q129) -> 0 | S129: =IF(AH129="",S205,AH129) -> 0 | T129: =IF(AI129="",T205,AI129) -> 0 | U129: =IF(AJ129="",U205,AJ129) -> 0 | W129: =E129 -> blank
B130: l | C130: l | E130: blank | F130: =F206 -> 0 | G130: =G206 -> 0 | H130: =H206 -> 0 | I130: =IF(X130="",I206,X130) -> 0 | J130: =IF(Y130="",J206,Y130) -> 0 | K130: =IF(Z130="",K206,Z130) -> 0 | L130: =IF(AA130="",L206,AA130) -> 0 | M130: =SUM(I130:L130) -> 0 | N130: =IF(AC130="",N206,AC130) -> 0 | O130: =IF(AD130="",O206,AD130) -> 0 | P130: =IF(AE130="",P206,AE130) -> 0 | Q130: =IF(AF130="",Q206,AF130) -> 0 | R130: =SUM(N130:Q130) -> 0 | S130: =IF(AH130="",S206,AH130) -> 0 | T130: =IF(AI130="",T206,AI130) -> 0 | U130: =IF(AJ130="",U206,AJ130) -> 0 | W130: =E130 -> blank
B131: l | C131: l | E131: blank | F131: =F207 -> 0 | G131: =G207 -> 0 | H131: =H207 -> 0 | I131: =IF(X131="",I207,X131) -> 0 | J131: =IF(Y131="",J207,Y131) -> 0 | K131: =IF(Z131="",K207,Z131) -> 0 | L131: =IF(AA131="",L207,AA131) -> 0 | M131: =SUM(I131:L131) -> 0 | N131: =IF(AC131="",N207,AC131) -> 0 | O131: =IF(AD131="",O207,AD131) -> 0 | P131: =IF(AE131="",P207,AE131) -> 0 | Q131: =IF(AF131="",Q207,AF131) -> 0 | R131: =SUM(N131:Q131) -> 0 | S131: =IF(AH131="",S207,AH131) -> 0 | T131: =IF(AI131="",T207,AI131) -> 0 | U131: =IF(AJ131="",U207,AJ131) -> 0 | W131: =E131 -> blank
B132: l | C132: l | E132: blank | F132: =F208 -> 0 | G132: =G208 -> 0 | H132: =H208 -> 0 | I132: =IF(X132="",I208,X132) -> 0 | J132: =IF(Y132="",J208,Y132) -> 0 | K132: =IF(Z132="",K208,Z132) -> 0 | L132: =IF(AA132="",L208,AA132) -> 0 | M132: =SUM(I132:L132) -> 0 | N132: =IF(AC132="",N208,AC132) -> 0 | O132: =IF(AD132="",O208,AD132) -> 0 | P132: =IF(AE132="",P208,AE132) -> 0 | Q132: =IF(AF132="",Q208,AF132) -> 0 | R132: =SUM(N132:Q132) -> 0 | S132: =IF(AH132="",S208,AH132) -> 0 | T132: =IF(AI132="",T208,AI132) -> 0 | U132: =IF(AJ132="",U208,AJ132) -> 0 | W132: =E132 -> blank
B133: l | C133: l | E133: blank | F133: =F209 -> 0 | G133: =G209 -> 0 | H133: =H209 -> 0 | I133: =IF(X133="",I209,X133) -> 0 | J133: =IF(Y133="",J209,Y133) -> 0 | K133: =IF(Z133="",K209,Z133) -> 0 | L133: =IF(AA133="",L209,AA133) -> 0 | M133: =SUM(I133:L133) -> 0 | N133: =IF(AC133="",N209,AC133) -> 0 | O133: =IF(AD133="",O209,AD133) -> 0 | P133: =IF(AE133="",P209,AE133) -> 0 | Q133: =IF(AF133="",Q209,AF133) -> 0 | R133: =SUM(N133:Q133) -> 0 | S133: =IF(AH133="",S209,AH133) -> 0 | T133: =IF(AI133="",T209,AI133) -> 0 | U133: =IF(AJ133="",U209,AJ133) -> 0 | W133: =E133 -> blank
E134: Total | F134: =SUM(F126:F133) -> 0 | G134: =SUM(G126:G133) -> 0 | H134: =SUM(H126:H133) -> 0 | I134: =SUM(I126:I133) -> 0 | J134: =SUM(J126:J133) -> 0 | K134: =SUM(K126:K133) -> 0 | L134: =SUM(L126:L133) -> 0 | M134: =SUM(M126:M133) -> 0 | ... U134: =SUM(U126:U133) -> 0
E138: Overhead COGS | W138: Overhead COGS
...

Sheet 3. Opex
B3: Cash | C3: P&L | E3: ="Scenario 1: "&Inputs!B22 -> Scenario 1: Scenario 1
E4: =Inputs!C22 -> Scenario 1 Description
E7: Operating Expenses | W7: Operating Expenses
E8: Commerical assumptions 000s | W8: Key In expected Dollar amounts in 000s
F10: =Inputs!$C$7 -> 2023 | G10: =Inputs!$C$8 -> 2024 | H10: =Inputs!$C$9 -> 2025 | I10: Q1 | J10: Q2 | K10: Q3 | L10: Q4 | M10: =Inputs!$C$10 -> 2026 | N10: Q1 | O10: Q2 | P10: Q3 | Q10: Q4 | R10: =Inputs!$C$11 -> 2027 | S10: =Inputs!$C$12 -> 2028 | T10: =Inputs!$C$13 -> 2029 | U10: =Inputs!$C$14 -> 2030 | X10: Q1 | Y10: Q2 | Z10: Q3 | AA10: Q4 | AB10: =Inputs!$C$10 -> 2026 | AC10: Q1 | AD10: Q2 | AE10: Q3 | AF10: Q4 | AG10: =Inputs!$C$11 -> 2027 | AH10: =Inputs!$C$12 -> 2028 | AI10: =Inputs!$C$13 -> 2029 | AJ10: =Inputs!$C$14 -> 2030
F11: (000) | G11: (000) | H11: (000) | I11: (000) | J11: (000) | K11: (000) | L11: (000) | M11: (000) | N11: (000) | O11: (000) | P11: (000) | Q11: (000) | R11: (000) | S11: (000) | T11: (000) | U11: (000) | X11: $ | Y11: $ | Z11: $ | AA11: $ | AC11: $ | AD11: $ | AE11: $ | AF11: $ | AH11: $ | AI11: $ | AJ11: $
B12: l | C12: l | E12: R&D | F12: =F132 -> 0 | G12: =G132 -> 0 | H12: =H132 -> 0 | I12: =IF(X12="",I132,X12) -> 0 | J12: =IF(Y12="",J132,Y12) -> 0 | K12: =IF(Z12="",K132,Z12) -> 0 | L12: =IF(AA12="",L132,AA12) -> 0 | M12: =SUM(I12:L12) -> 0 | N12: =IF(AC12="",N132,AC12) -> 0 | O12: =IF(AD12="",O132,AD12) -> 0 | P12: =IF(AE12="",P132,AE12) -> 0 | Q12: =IF(AF12="",Q132,AF12) -> 0 | R12: =SUM(N12:Q12) -> 0 | S12: =IF(AH12="",S132,AH12) -> 0 | T12: =IF(AI12="",T132,AI12) -> 0 | U12: =IF(AJ12="",U132,AJ12) -> 0 | W12: =E12 -> R&D
B13: l | C13: l | E13: Marketing | F13: =F133 -> 0 | G13: =G133 -> 0 | H13: =H133 -> 0 | I13: =IF(X13="",I133,X13) -> 0 | J13: =IF(Y13="",J133,Y13) -> 0 | K13: =IF(Z13="",K133,Z13) -> 0 | L13: =IF(AA13="",L133,AA13) -> 0 | M13: =SUM(I13:L13) -> 0 | N13: =IF(AC13="",N133,AC13) -> 0 | O13: =IF(AD13="",O133,AD13) -> 0 | P13: =IF(AE13="",P133,AE13) -> 0 | Q13: =IF(AF13="",Q133,AF13) -> 0 | R13: =SUM(N13:Q13) -> 0 | S13: =IF(AH13="",S133,AH13) -> 0 | T13: =IF(AI13="",T133,AI13) -> 0 | U13: =IF(AJ13="",U133,AJ13) -> 0 | W13: =E13 -> Marketing
B14: l | C14: l | E14: Sales | F14: =F134 -> 0 | G14: =G134 -> 0 | H14: =H134 -> 0 | I14: =IF(X14="",I134,X14) -> 0 | J14: =IF(Y14="",J134,Y14) -> 0 | K14: =IF(Z14="",K134,Z14) -> 0 | L14: =IF(AA14="",L134,AA14) -> 0 | M14: =SUM(I14:L14) -> 0 | N14: =IF(AC14="",N134,AC14) -> 0 | O14: =IF(AD14="",O134,AD14) -> 0 | P14: =IF(AE14="",P134,AE14) -> 0 | Q14: =IF(AF14="",Q134,AF14) -> 0 | R14: =SUM(N14:Q14) -> 0 | S14: =IF(AH14="",S134,AH14) -> 0 | T14: =IF(AI14="",T134,AI14) -> 0 | U14: =IF(AJ14="",U134,AJ14) -> 0 | W14: =E14 -> Sales
B15: l | C15: l | E15: G&A | F15: =F135 -> 0 | G15: =G135 -> 0 | H15: =H135 -> 0 | I15: =IF(X15="",I135,X15) -> 0 | J15: =IF(Y15="",J135,Y15) -> 0 | K15: =IF(Z15="",K135,Z15) -> 0 | L15: =IF(AA15="",L135,AA15) -> 0 | M15: =SUM(I15:L15) -> 0 | N15: =IF(AC15="",N135,AC15) -> 0 | O15: =IF(AD15="",O135,AD15) -> 0 | P15: =IF(AE15="",P135,AE15) -> 0 | Q15: =IF(AF15="",Q135,AF15) -> 0 | R15: =SUM(N15:Q15) -> 0 | S15: =IF(AH15="",S135,AH15) -> 0 | T15: =IF(AI15="",T135,AI15) -> 0 | U15: =IF(AJ15="",U135,AJ15) -> 0 | W15: =E15 -> G&A
B16: l | C16: l | E16: Finance | F16: =F136 -> 0 | G16: =G136 -> 0 | H16: =H136 -> 0 | I16: =IF(X16="",I136,X16) -> 0 | J16: =IF(Y16="",J136,Y16) -> 0 | K16: =IF(Z16="",K136,Z16) -> 0 | L16: =IF(AA16="",L136,AA16) -> 0 | M16: =SUM(I16:L16) -> 0 | N16: =IF(AC16="",N136,AC16) -> 0 | O16: =IF(AD16="",O136,AD16) -> 0 | P16: =IF(AE16="",P136,AE16) -> 0 | Q16: =IF(AF16="",Q136,AF16) -> 0 | R16: =SUM(N16:Q16) -> 0 | S16: =IF(AH16="",S136,AH16) -> 0 | T16: =IF(AI16="",T136,AI16) -> 0 | U16: =IF(AJ16="",U136,AJ16) -> 0 | W16: =E16 -> Finance
B17: l | C17: l | E17: IT | F17: =F137 -> 0 | G17: =G137 -> 0 | H17: =H137 -> 0 | I17: =IF(X17="",I137,X17) -> 0 | J17: =IF(Y17="",J137,Y17) -> 0 | K17: =IF(Z17="",K137,Z17) -> 0 | L17: =IF(AA17="",L137,AA17) -> 0 | M17: =SUM(I17:L17) -> 0 | N17: =IF(AC17="",N137,AC17) -> 0 | O17: =IF(AD17="",O137,AD17) -> 0 | P17: =IF(AE17="",P137,AE17) -> 0 | Q17: =IF(AF17="",Q137,AF17) -> 0 | R17: =SUM(N17:Q17) -> 0 | S17: =IF(AH17="",S137,AH17) -> 0 | T17: =IF(AI17="",T137,AI17) -> 0 | U17: =IF(AJ17="",U137,AJ17) -> 0 | W17: =E17 -> IT
B18: l | C18: l | E18: HR | F18: =F138 -> 0 | G18: =G138 -> 0 | H18: =H138 -> 0 | I18: =IF(X18="",I138,X18) -> 0 | J18: =IF(Y18="",J138,Y18) -> 0 | K18: =IF(Z18="",K138,Z18) -> 0 | L18: =IF(AA18="",L138,AA18) -> 0 | M18: =SUM(I18:L18) -> 0 | N18: =IF(AC18="",N138,AC18) -> 0 | O18: =IF(AD18="",O138,AD18) -> 0 | P18: =IF(AE18="",P138,AE18) -> 0 | Q18: =IF(AF18="",Q138,AF18) -> 0 | R18: =SUM(N18:Q18) -> 0 | S18: =IF(AH18="",S138,AH18) -> 0 | T18: =IF(AI18="",T138,AI18) -> 0 | U18: =IF(AJ18="",U138,AJ18) -> 0 | W18: =E18 -> HR
B19: l | C19: l | E19: Global IT | F19: =F139 -> 0 | G19: =G139 -> 0 | H19: =H139 -> 0 | I19: =IF(X19="",I139,X19) -> 0 | J19: =IF(Y19="",J139,Y19) -> 0 | K19: =IF(Z19="",K139,Z19) -> 0 | L19: =IF(AA19="",L139,AA19) -> 0 | M19: =SUM(I19:L19) -> 0 | N19: =IF(AC19="",N139,AC19) -> 0 | O19: =IF(AD19="",O139,AD19) -> 0 | P19: =IF(AE19="",P139,AE19) -> 0 | Q19: =IF(AF19="",Q139,AF19) -> 0 | R19: =SUM(N19:Q19) -> 0 | S19: =IF(AH19="",S139,AH19) -> 0 | T19: =IF(AI19="",T139,AI19) -> 0 | U19: =IF(AJ19="",U139,AJ19) -> 0 | W19: =E19 -> Global IT
B20: l | C20: l | E20: All other Period Expenses | F20: =F140 -> 0 | G20: =G140 -> 0 | H20: =H140 -> 0 | I20: =IF(X20="",I140,X20) -> 0 | J20: =IF(Y20="",J140,Y20) -> 0 | K20: =IF(Z20="",K140,Z20) -> 0 | L20: =IF(AA20="",L140,AA20) -> 0 | M20: =SUM(I20:L20) -> 0 | N20: =IF(AC20="",N140,AC20) -> 0 | O20: =IF(AD20="",O140,AD20) -> 0 | P20: =IF(AE20="",P140,AE20) -> 0 | Q20: =IF(AF20="",Q140,AF20) -> 0 | R20: =SUM(N20:Q20) -> 0 | S20: =IF(AH20="",S140,AH20) -> 0 | T20: =IF(AI20="",T140,AI20) -> 0 | U20: =IF(AJ20="",U140,AJ20) -> 0 | W20: =E20 -> All other Period Expenses
B21: l | C21: l | E21: Blank | F21: =F141 -> 0 | G21: =G141 -> 0 | H21: =H141 -> 0 | I21: =IF(X21="",I141,X21) -> 0 | J21: =IF(Y21="",J141,Y21) -> 0 | K21: =IF(Z21="",K141,Z21) -> 0 | L21: =IF(AA21="",L141,AA21) -> 0 | M21: =SUM(I21:L21) -> 0 | N21: =IF(AC21="",N141,AC21) -> 0 | O21: =IF(AD21="",O141,AD21) -> 0 | P21: =IF(AE21="",P141,AE21) -> 0 | Q21: =IF(AF21="",Q141,AF21) -> 0 | R21: =SUM(N21:Q21) -> 0 | S21: =IF(AH21="",S141,AH21) -> 0 | T21: =IF(AI21="",T141,AI21) -> 0 | U21: =IF(AJ21="",U141,AJ21) -> 0 | W21: =E21 -> Blank
B22: l | C22: l | E22: Blank | F22: =F142 -> 0 | G22: =G142 -> 0 | H22: =H142 -> 0 | I22: =IF(X22="",I142,X22) -> 0 | J22: =IF(Y22="",J142,Y22) -> 0 | K22: =IF(Z22="",K142,Z22) -> 0 | L22: =IF(AA22="",L142,AA22) -> 0 | M22: =SUM(I22:L22) -> 0 | N22: =IF(AC22="",N142,AC22) -> 0 | O22: =IF(AD22="",O142,AD22) -> 0 | P22: =IF(AE22="",P142,AE22) -> 0 | Q22: =IF(AF22="",Q142,AF22) -> 0 | R22: =SUM(N22:Q22) -> 0 | S22: =IF(AH22="",S142,AH22) -> 0 | T22: =IF(AI22="",T142,AI22) -> 0 | U22: =IF(AJ22="",U142,AJ22) -> 0 | W22: =E22 -> Blank
E23: Total | F23: =SUM(F12:F22) -> 0 | G23: =SUM(G12:G22) -> 0 | H23: =SUM(H12:H22) -> 0 | I23: =SUM(I12:I22) -> 0 | J23: =SUM(J12:J22) -> 0 | K23: =SUM(K12:K22) -> 0 | L23: =SUM(L12:L22) -> 0 | M23: =SUM(M12:M22) -> 0 | ... U23: =SUM(U12:U22) -> 0
B27: Cash | C27: P&L | E27: ="Scenario 2: "&Inputs!B23 -> Scenario 2: Scenario 2
E28: =Inputs!C23 -> Scenario 2 Description
E31: Operating Expenses | W31: Operating Expenses
E32: Commerical assumptions 000s | W32: Commerical assumptions 000s
F34: =Inputs!$C$7 -> 2023 | G34: =Inputs!$C$8 -> 2024 | H34: =Inputs!$C$9 -> 2025 | I34: Q1 | J34: Q2 | K34: Q3 | L34: Q4 | M34: =Inputs!$C$10 -> 2026 | N34: Q1 | O34: Q2 | P34: Q3 | Q34: Q4 | R34: =Inputs!$C$11 -> 2027 | S34: =Inputs!$C$12 -> 2028 | T34: =Inputs!$C$13 -> 2029 | U34: =Inputs!$C$14 -> 2030 | X34: Q1 | Y34: Q2 | Z34: Q3 | AA34: Q4 | AB34: =Inputs!$C$10 -> 2026 | AC34: Q1 | AD34: Q2 | AE34: Q3 | AF34: Q4 | AG34: =Inputs!$C$11 -> 2027 | AH34: =Inputs!$C$12 -> 2028 | AI34: =Inputs!$C$13 -> 2029 | AJ34: =Inputs!$C$14 -> 2030
F35: (000) | G35: (000) | H35: (000) | I35: (000) | J35: (000) | K35: (000) | L35: (000) | M35: (000) | N35: (000) | O35: (000) | P35: (000) | Q35: (000) | R35: (000) | S35: (000) | T35: (000) | U35: (000) | X35: $ | Y35: $ | Z35: $ | AA35: $ | AC35: $ | AD35: $ | AE35: $ | AF35: $ | AH35: $ | AI35: $ | AJ35: $
B36: l | C36: l | E36: R&D | F36: =F132 -> 0 | G36: =G132 -> 0 | H36: =H132 -> 0 | I36: =IF(X36="",I132,X36) -> 0 | J36: =IF(Y36="",J132,Y36) -> 0 | K36: =IF(Z36="",K132,Z36) -> 0 | L36: =IF(AA36="",L132,AA36) -> 0 | M36: =SUM(I36:L36) -> 0 | N36: =IF(AC36="",N132,AC36) -> 0 | O36: =IF(AD36="",O132,AD36) -> 0 | P36: =IF(AE36="",P132,AE36) -> 0 | Q36: =IF(AF36="",Q132,AF36) -> 0 | R36: =SUM(N36:Q36) -> 0 | S36: =IF(AH36="",S132,AH36) -> 0 | T36: =IF(AI36="",T132,AI36) -> 0 | U36: =IF(AJ36="",U132,AJ36) -> 0 | W36: =E36 -> R&D
B37: l | C37: l | E37: Marketing | F37: =F133 -> 0 | G37: =G133 -> 0 | H37: =H133 -> 0 | I37: =IF(X37="",I133,X37) -> 0 | J37: =IF(Y37="",J133,Y37) -> 0 | K37: =IF(Z37="",K133,Z37) -> 0 | L37: =IF(AA37="",L133,AA37) -> 0 | M37: =SUM(I37:L37) -> 0 | N37: =IF(AC37="",N133,AC37) -> 0 | O37: =IF(AD37="",O133,AD37) -> 0 | P37: =IF(AE37="",P133,AE37) -> 0 | Q37: =IF(AF37="",Q133,AF37) -> 0 | R37: =SUM(N37:Q37) -> 0 | S37: =IF(AH37="",S133,AH37) -> 0 | T37: =IF(AI37="",T133,AI37) -> 0 | U37: =IF(AJ37="",U133,AJ37) -> 0 | W37: =E37 -> Marketing
B38: l | C38: l | E38: Sales | F38: =F134 -> 0 | G38: =G134 -> 0 | H38: =H134 -> 0 | I38: =IF(X38="",I134,X38) -> 0 | J38: =IF(Y38="",J134,Y38) -> 0 | K38: =IF(Z38="",K134,Z38) -> 0 | L38: =IF(AA38="",L134,AA38) -> 0 | M38: =SUM(I38:L38) -> 0 | N38: =IF(AC38="",N134,AC38) -> 0 | O38: =IF(AD38="",O134,AD38) -> 0 | P38: =IF(AE38="",P134,AE38) -> 0 | Q38: =IF(AF38="",Q134,AF38) -> 0 | R38: =SUM(N38:Q38) -> 0 | S38: =IF(AH38="",S134,AH38) -> 0 | T38: =IF(AI38="",T134,AI38) -> 0 | U38: =IF(AJ38="",U134,AJ38) -> 0 | W38: =E38 -> Sales
B39: l | C39: l | E39: G&A | F39: =F135 -> 0 | G39: =G135 -> 0 | H39: =H135 -> 0 | I39: =IF(X39="",I135,X39) -> 0 | J39: =IF(Y39="",J135,Y39) -> 0 | K39: =IF(Z39="",K135,Z39) -> 0 | L39: =IF(AA39="",L135,AA39) -> 0 | M39: =SUM(I39:L39) -> 0 | N39: =IF(AC39="",N135,AC39) -> 0 | O39: =IF(AD39="",O135,AD39) -> 0 | P39: =IF(AE39="",P135,AE39) -> 0 | Q39: =IF(AF39="",Q135,AF39) -> 0 | R39: =SUM(N39:Q39) -> 0 | S39: =IF(AH39="",S135,AH39) -> 0 | T39: =IF(AI39="",T135,AI39) -> 0 | U39: =IF(AJ39="",U135,AJ39) -> 0 | W39: =E39 -> G&A
B40: l | C40: l | E40: Finance | F40: =F136 -> 0 | G40: =G136 -> 0 | H40: =H136 -> 0 | I40: =IF(X40="",I136,X40) -> 0 | J40: =IF(Y40="",J136,Y40) -> 0 | K40: =IF(Z40="",K136,Z40) -> 0 | L40: =IF(AA40="",L136,AA40) -> 0 | M40: =SUM(I40:L40) -> 0 | N40: =IF(AC40="",N136,AC40) -> 0 | O40: =IF(AD40="",O136,AD40) -> 0 | P40: =IF(AE40="",P136,AE40) -> 0 | Q40: =IF(AF40="",Q136,AF40) -> 0 | R40: =SUM(N40:Q40) -> 0 | S40: =IF(AH40="",S136,AH40) -> 0 | T40: =IF(AI40="",T136,AI40) -> 0 | U40: =IF(AJ40="",U136,AJ40) -> 0 | W40: =E40 -> Finance
B41: l | C41: l | E41: IT | F41: =F137 -> 0 | G41: =G137 -> 0 | H41: =H137 -> 0 | I41: =IF(X41="",I137,X41) -> 0 | J41: =IF(Y41="",J137,Y41) -> 0 | K41: =IF(Z41="",K137,Z41) -> 0 | L41: =IF(AA41="",L137,AA41) -> 0 | M41: =SUM(I41:L41) -> 0 | N41: =IF(AC41="",N137,AC41) -> 0 | O41: =IF(AD41="",O137,AD41) -> 0 | P41: =IF(AE41="",P137,AE41) -> 0 | Q41: =IF(AF41="",Q137,AF41) -> 0 | R41: =SUM(N41:Q41) -> 0 | S41: =IF(AH41="",S137,AH41) -> 0 | T41: =IF(AI41="",T137,AI41) -> 0 | U41: =IF(AJ41="",U137,AJ41) -> 0 | W41: =E41 -> IT
B42: l | C42: l | E42: HR | F42: =F138 -> 0 | G42: =G138 -> 0 | H42: =H138 -> 0 | I42: =IF(X42="",I138,X42) -> 0 | J42: =IF(Y42="",J138,Y42) -> 0 | K42: =IF(Z42="",K138,Z42) -> 0 | L42: =IF(AA42="",L138,AA42) -> 0 | M42: =SUM(I42:L42) -> 0 | N42: =IF(AC42="",N138,AC42) -> 0 | O42: =IF(AD42="",O138,AD42) -> 0 | P42: =IF(AE42="",P138,AE42) -> 0 | Q42: =IF(AF42="",Q138,AF42) -> 0 | R42: =SUM(N42:Q42) -> 0 | S42: =IF(AH42="",S138,AH42) -> 0 | T42: =IF(AI42="",T138,AI42) -> 0 | U42: =IF(AJ42="",U138,AJ42) -> 0 | W42: =E42 -> HR
B43: l | C43: l | E43: Global IT | F43: =F139 -> 0 | G43: =G139 -> 0 | H43: =H139 -> 0 | I43: =IF(X43="",I139,X43) -> 0 | J43: =IF(Y43="",J139,Y43) -> 0 | K43: =IF(Z43="",K139,Z43) -> 0 | L43: =IF(AA43="",L139,AA43) -> 0 | M43: =SUM(I43:L43) -> 0 | N43: =IF(AC43="",N139,AC43) -> 0 | O43: =IF(AD43="",O139,AD43) -> 0 | P43: =IF(AE43="",P139,AE43) -> 0 | Q43: =IF(AF43="",Q139,AF43) -> 0 | R43: =SUM(N43:Q43) -> 0 | S43: =IF(AH43="",S139,AH43) -> 0 | T43: =IF(AI43="",T139,AI43) -> 0 | U43: =IF(AJ43="",U139,AJ43) -> 0 | W43: =E43 -> Global IT
B44: l | C44: l | E44: All other Period Expenses | F44: =F140 -> 0 | G44: =G140 -> 0 | H44: =H140 -> 0 | I44: =IF(X44="",I140,X44) -> 0 | J44: =IF(Y44="",J140,Y44) -> 0 | K44: =IF(Z44="",K140,Z44) -> 0 | L44: =IF(AA44="",L140,AA44) -> 0 | M44: =SUM(I44:L44) -> 0 | N44: =IF(AC44="",N140,AC44) -> 0 | O44: =IF(AD44="",O140,AD44) -> 0 | P44: =IF(AE44="",P140,AE44) -> 0 | Q44: =IF(AF44="",Q140,AF44) -> 0 | R44: =SUM(N44:Q44) -> 0 | S44: =IF(AH44="",S140,AH44) -> 0 | T44: =IF(AI44="",T140,AI44) -> 0 | U44: =IF(AJ44="",U140,AJ44) -> 0 | W44: =E44 -> All other Period Expenses
B45: l | C45: l | E45: Blank | F45: =F141 -> 0 | G45: =G141 -> 0 | H45: =H141 -> 0 | I45: =IF(X45="",I141,X45) -> 0 | J45: =IF(Y45="",J141,Y45) -> 0 | K45: =IF(Z45="",K141,Z45) -> 0 | L45: =IF(AA45="",L141,AA45) -> 0 | M45: =SUM(I45:L45) -> 0 | N45: =IF(AC45="",N141,AC45) -> 0 | O45: =IF(AD45="",O141,AD45) -> 0 | P45: =IF(AE45="",P141,AE45) -> 0 | Q45: =IF(AF45="",Q141,AF45) -> 0 | R45: =SUM(N45:Q45) -> 0 | S45: =IF(AH45="",S141,AH45) -> 0 | T45: =IF(AI45="",T141,AI45) -> 0 | U45: =IF(AJ45="",U141,AJ45) -> 0 | W45: =E45 -> Blank
B46: l | C46: l | E46: Blank | F46: =F142 -> 0 | G46: =G142 -> 0 | H46: =H142 -> 0 | I46: =IF(X46="",I142,X46) -> 0 | J46: =IF(Y46="",J142,Y46) -> 0 | K46: =IF(Z46="",K142,Z46) -> 0 | L46: =IF(AA46="",L142,AA46) -> 0 | M46: =SUM(I46:L46) -> 0 | N46: =IF(AC46="",N142,AC46) -> 0 | O46: =IF(AD46="",O142,AD46) -> 0 | P46: =IF(AE46="",P142,AE46) -> 0 | Q46: =IF(AF46="",Q142,AF46) -> 0 | R46: =SUM(N46:Q46) -> 0 | S46: =IF(AH46="",S142,AH46) -> 0 | T46: =IF(AI46="",T142,AI46) -> 0 | U46: =IF(AJ46="",U142,AJ46) -> 0 | W46: =E46 -> Blank
E47: Total | F47: =SUM(F36:F46) -> 0 | G47: =SUM(G36:G46) -> 0 | H47: =SUM(H36:H46) -> 0 | I47: =SUM(I36:I46) -> 0 | J47: =SUM(J36:J46) -> 0 | K47: =SUM(K36:K46) -> 0 | L47: =SUM(L36:L46) -> 0 | M47: =SUM(M36:M46) -> 0 | ... U47: =SUM(U36:U46) -> 0
B51: Cash | C51: P&L | E51: ="Scenario 3: "&Inputs!B24 -> Scenario 3: Scenario 3
E52: =Inputs!C24 -> Scenario 3 Description
E55: Operating Expenses | W55: Operating Expenses
E56: Commerical assumptions 000s | W56: Commerical assumptions 000s
F58: =Inputs!$C$7 -> 2023 | G58: =Inputs!$C$8 -> 2024 | H58: =Inputs!$C$9 -> 2025 | I58: Q1 | J58: Q2 | K58: Q3 | L58: Q4 | M58: =Inputs!$C$10 -> 2026 | N58: Q1 | O58: Q2 | P58: Q3 | Q58: Q4 | R58: =Inputs!$C$11 -> 2027 | S58: =Inputs!$C$12 -> 2028 | T58: =Inputs!$C$13 -> 2029 | U58: =Inputs!$C$14 -> 2030 | X58: Q1 | Y58: Q2 | Z58: Q3 | AA58: Q4 | AB58: =Inputs!$C$10 -> 2026 | AC58: Q1 | AD58: Q2 | AE58: Q3 | AF58: Q4 | AG58: =Inputs!$C$11 -> 2027 | AH58: =Inputs!$C$12 -> 2028 | AI58: =Inputs!$C$13 -> 2029 | AJ58: =Inputs!$C$14 -> 2030
F59: (000) | G59: (000) | H59: (000) | I59: (000) | J59: (000) | K59: (000) | L59: (000) | M59: (000) | N59: (000) | O59: (000) | P59: (000) | Q59: (000) | R59: (000) | S59: (000) | T59: (000) | U59: (000) | X59: $ | Y59: $ | Z59: $ | AA59: $ | AC59: $ | AD59: $ | AE59: $ | AF59: $ | AH59: $ | AI59: $ | AJ59: $
B60: l | C60: l | E60: R&D | F60: =F132 -> 0 | G60: =G132 -> 0 | H60: =H132 -> 0 | I60: =IF(X60="",I132,X60) -> 0 | J60: =IF(Y60="",J132,Y60) -> 0 | K60: =IF(Z60="",K132,Z60) -> 0 | L60: =IF(AA60="",L132,AA60) -> 0 | M60: =SUM(I60:L60) -> 0 | N60: =IF(AC60="",N132,AC60) -> 0 | O60: =IF(AD60="",O132,AD60) -> 0 | P60: =IF(AE60="",P132,AE60) -> 0 | Q60: =IF(AF60="",Q132,AF60) -> 0 | R60: =SUM(N60:Q60) -> 0 | S60: =IF(AH60="",S132,AH60) -> 0 | T60: =IF(AI60="",T132,AI60) -> 0 | U60: =IF(AJ60="",U132,AJ60) -> 0 | W60: =E60 -> R&D
B61: l | C61: l | E61: Marketing | F61: =F133 -> 0 | G61: =G133 -> 0 | H61: =H133 -> 0 | I61: =IF(X61="",I133,X61) -> 0 | J61: =IF(Y61="",J133,Y61) -> 0 | K61: =IF(Z61="",K133,Z61) -> 0 | L61: =IF(AA61="",L133,AA61) -> 0 | M61: =SUM(I61:L61) -> 0 | N61: =IF(AC61="",N133,AC61) -> 0 | O61: =IF(AD61="",O133,AD61) -> 0 | P61: =IF(AE61="",P133,AE61) -> 0 | Q61: =IF(AF61="",Q133,AF61) -> 0 | R61: =SUM(N61:Q61) -> 0 | S61: =IF(AH61="",S133,AH61) -> 0 | T61: =IF(AI61="",T133,AI61) -> 0 | U61: =IF(AJ61="",U133,AJ61) -> 0 | W61: =E61 -> Marketing
B62: l | C62: l | E62: Sales | F62: =F134 -> 0 | G62: =G134 -> 0 | H62: =H134 -> 0 | I62: =IF(X62="",I134,X62) -> 0 | J62: =IF(Y62="",J134,Y62) -> 0 | K62: =IF(Z62="",K134,Z62) -> 0 | L62: =IF(AA62="",L134,AA62) -> 0 | M62: =SUM(I62:L62) -> 0 | N62: =IF(AC62="",N134,AC62) -> 0 | O62: =IF(AD62="",O134,AD62) -> 0 | P62: =IF(AE62="",P134,AE62) -> 0 | Q62: =IF(AF62="",Q134,AF62) -> 0 | R62: =SUM(N62:Q62) -> 0 | S62: =IF(AH62="",S134,AH62) -> 0 | T62: =IF(AI62="",T134,AI62) -> 0 | U62: =IF(AJ62="",U134,AJ62) -> 0 | W62: =E62 -> Sales
B63: l | C63: l | E63: G&A | F63: =F135 -> 0 | G63: =G135 -> 0 | H63: =H135 -> 0 | I63: =IF(X63="",I135,X63) -> 0 | J63: =IF(Y63="",J135,Y63) -> 0 | K63: =IF(Z63="",K135,Z63) -> 0 | L63: =IF(AA63="",L135,AA63) -> 0 | M63: =SUM(I63:L63) -> 0 | N63: =IF(AC63="",N135,AC63) -> 0 | O63: =IF(AD63="",O135,AD63) -> 0 | P63: =IF(AE63="",P135,AE63) -> 0 | Q63: =IF(AF63="",Q135,AF63) -> 0 | R63: =SUM(N63:Q63) -> 0 | S63: =IF(AH63="",S135,AH63) -> 0 | T63: =IF(AI63="",T135,AI63) -> 0 | U63: =IF(AJ63="",U135,AJ63) -> 0 | W63: =E63 -> G&A
B64: l | C64: l | E64: Finance | F64: =F136 -> 0 | G64: =G136 -> 0 | H64: =H136 -> 0 | I64: =IF(X64="",I136,X64) -> 0 | J64: =IF(Y64="",J136,Y64) -> 0 | K64: =IF(Z64="",K136,Z64) -> 0 | L64: =IF(AA64="",L136,AA64) -> 0 | M64: =SUM(I64:L64) -> 0 | N64: =IF(AC64="",N136,AC64) -> 0 | O64: =IF(AD64="",O136,AD64) -> 0 | P64: =IF(AE64="",P136,AE64) -> 0 | Q64: =IF(AF64="",Q136,AF64) -> 0 | R64: =SUM(N64:Q64) -> 0 | S64: =IF(AH64="",S136,AH64) -> 0 | T64: =IF(AI64="",T136,AI64) -> 0 | U64: =IF(AJ64="",U136,AJ64) -> 0 | W64: =E64 -> Finance
B65: l | C65: l | E65: IT | F65: =F137 -> 0 | G65: =G137 -> 0 | H65: =H137 -> 0 | I65: =IF(X65="",I137,X65) -> 0 | J65: =IF(Y65="",J137,Y65) -> 0 | K65: =IF(Z65="",K137,Z65) -> 0 | L65: =IF(AA65="",L137,AA65) -> 0 | M65: =SUM(I65:L65) -> 0 | N65: =IF(AC65="",N137,AC65) -> 0 | O65: =IF(AD65="",O137,AD65) -> 0 | P65: =IF(AE65="",P137,AE65) -> 0 | Q65: =IF(AF65="",Q137,AF65) -> 0 | R65: =SUM(N65:Q65) -> 0 | S65: =IF(AH65="",S137,AH65) -> 0 | T65: =IF(AI65="",T137,AI65) -> 0 | U65: =IF(AJ65="",U137,AJ65) -> 0 | W65: =E65 -> IT
B66: l | C66: l | E66: HR | F66: =F138 -> 0 | G66: =G138 -> 0 | H66: =H138 -> 0 | I66: =IF(X66="",I138,X66) -> 0 | J66: =IF(Y66="",J138,Y66) -> 0 | K66: =IF(Z66="",K138,Z66) -> 0 | L66: =IF(AA66="",L138,AA66) -> 0 | M66: =SUM(I66:L66) -> 0 | N66: =IF(AC66="",N138,AC66) -> 0 | O66: =IF(AD66="",O138,AD66) -> 0 | P66: =IF(AE66="",P138,AE66) -> 0 | Q66: =IF(AF66="",Q138,AF66) -> 0 | R66: =SUM(N66:Q66) -> 0 | S66: =IF(AH66="",S138,AH66) -> 0 | T66: =IF(AI66="",T138,AI66) -> 0 | U66: =IF(AJ66="",U138,AJ66) -> 0 | W66: =E66 -> HR
B67: l | C67: l | E67: Global IT | F67: =F139 -> 0 | G67: =G139 -> 0 | H67: =H139 -> 0 | I67: =IF(X67="",I139,X67) -> 0 | J67: =IF(Y67="",J139,Y67) -> 0 | K67: =IF(Z67="",K139,Z67) -> 0 | L67: =IF(AA67="",L139,AA67) -> 0 | M67: =SUM(I67:L67) -> 0 | N67: =IF(AC67="",N139,AC67) -> 0 | O67: =IF(AD67="",O139,AD67) -> 0 | P67: =IF(AE67="",P139,AE67) -> 0 | Q67: =IF(AF67="",Q139,AF67) -> 0 | R67: =SUM(N67:Q67) -> 0 | S67: =IF(AH67="",S139,AH67) -> 0 | T67: =IF(AI67="",T139,AI67) -> 0 | U67: =IF(AJ67="",U139,AJ67) -> 0 | W67: =E67 -> Global IT
B68: l | C68: l | E68: All other Period Expenses | F68: =F140 -> 0 | G68: =G140 -> 0 | H68: =H140 -> 0 | I68: =IF(X68="",I140,X68) -> 0 | J68: =IF(Y68="",J140,Y68) -> 0 | K68: =IF(Z68="",K140,Z68) -> 0 | L68: =IF(AA68="",L140,AA68) -> 0 | M68: =SUM(I68:L68) -> 0 | N68: =IF(AC68="",N140,AC68) -> 0 | O68: =IF(AD68="",O140,AD68) -> 0 | P68: =IF(AE68="",P140,AE68) -> 0 | Q68: =IF(AF68="",Q140,AF68) -> 0 | R68: =SUM(N68:Q68) -> 0 | S68: =IF(AH68="",S140,AH68) -> 0 | T68: =IF(AI68="",T140,AI68) -> 0 | U68: =IF(AJ68="",U140,AJ68) -> 0 | W68: =E68 -> All other Period Expenses
B69: l | C69: l | E69: Blank | F69: =F141 -> 0 | G69: =G141 -> 0 | H69: =H141 -> 0 | I69: =IF(X69="",I141,X69) -> 0 | J69: =IF(Y69="",J141,Y69) -> 0 | K69: =IF(Z69="",K141,Z69) -> 0 | L69: =IF(AA69="",L141,AA69) -> 0 | M69: =SUM(I69:L69) -> 0 | N69: =IF(AC69="",N141,AC69) -> 0 | O69: =IF(AD69="",O141,AD69) -> 0 | P69: =IF(AE69="",P141,AE69) -> 0 | Q69: =IF(AF69="",Q141,AF69) -> 0 | R69: =SUM(N69:Q69) -> 0 | S69: =IF(AH69="",S141,AH69) -> 0 | T69: =IF(AI69="",T141,AI69) -> 0 | U69: =IF(AJ69="",U141,AJ69) -> 0 | W69: =E69 -> Blank
B70: l | C70: l | E70: Blank | F70: =F142 -> 0 | G70: =G142 -> 0 | H70: =H142 -> 0 | I70: =IF(X70="",I142,X70) -> 0 | J70: =IF(Y70="",J142,Y70) -> 0 | K70: =IF(Z70="",K142,Z70) -> 0 | L70: =IF(AA70="",L142,AA70) -> 0 | M70: =SUM(I70:L70) -> 0 | N70: =IF(AC70="",N142,AC70) -> 0 | O70: =IF(AD70="",O142,AD70) -> 0 | P70: =IF(AE70="",P142,AE70) -> 0 | Q70: =IF(AF70="",Q142,AF70) -> 0 | R70: =SUM(N70:Q70) -> 0 | S70: =IF(AH70="",S142,AH70) -> 0 | T70: =IF(AI70="",T142,AI70) -> 0 | U70: =IF(AJ70="",U142,AJ70) -> 0 | W70: =E70 -> Blank
E71: Total | F71: =SUM(F60:F70) -> 0 | G71: =SUM(G60:G70) -> 0 | H71: =SUM(H60:H70) -> 0 | I71: =SUM(I60:I70) -> 0 | J71: =SUM(J60:J70) -> 0 | K71: =SUM(K60:K70) -> 0 | L71: =SUM(L60:L70) -> 0 | M71: =SUM(M60:M70) -> 0 | ... U71: =SUM(U60:U70) -> 0
B75: Cash | C75: P&L | E75: ="Scenario 4: "&Inputs!B25 -> Scenario 4: Scenario 4
E76: =Inputs!C25 -> Scenario 4 Description
E79: Operating Expenses | W79: Operating Expenses
E80: Commerical assumptions 000s | W80: Commerical assumptions 000s
F82: =Inputs!$C$7 -> 2023 | G82: =Inputs!$C$8 -> 2024 | H82: =Inputs!$C$9 -> 2025 | I82: Q1 | J82: Q2 | K82: Q3 | L82: Q4 | M82: =Inputs!$C$10 -> 2026 | N82: Q1 | O82: Q2 | P82: Q3 | Q82: Q4 | R82: =Inputs!$C$11 -> 2027 | S82: =Inputs!$C$12 -> 2028 | T82: =Inputs!$C$13 -> 2029 | U82: =Inputs!$C$14 -> 2030 | X82: Q1 | Y82: Q2 | Z82: Q3 | AA82: Q4 | AB82: =Inputs!$C$10 -> 2026 | AC82: Q1 | AD82: Q2 | AE82: Q3 | AF82: Q4 | AG82: =Inputs!$C$11 -> 2027 | AH82: =Inputs!$C$12 -> 2028 | AI82: =Inputs!$C$13 -> 2029 | AJ82: =Inputs!$C$14 -> 2030
F83: (000) | G83: (000) | H83: (000) | I83: (000) | J83: (000) | K83: (000) | L83: (000) | M83: (000) | N83: (000) | O83: (000) | P83: (000) | Q83: (000) | R83: (000) | S83: (000) | T83: (000) | U83: (000) | X83: $ | Y83: $ | Z83: $ | AA83: $ | AC83: $ | AD83: $ | AE83: $ | AF83: $ | AH83: $ | AI83: $ | AJ83: $
B84: l | C84: l | E84: R&D | F84: =F132 -> 0 | G84: =G132 -> 0 | H84: =H132 -> 0 | I84: =IF(X84="",I132,X84) -> 0 | J84: =IF(Y84="",J132,Y84) -> 0 | K84: =IF(Z84="",K132,Z84) -> 0 | L84: =IF(AA84="",L132,AA84) -> 0 | M84: =SUM(I84:L84) -> 0 | N84: =IF(AC84="",N132,AC84) -> 0 | O84: =IF(AD84="",O132,AD84) -> 0 | P84: =IF(AE84="",P132,AE84) -> 0 | Q84: =IF(AF84="",Q132,AF84) -> 0 | R84: =SUM(N84:Q84) -> 0 | S84: =IF(AH84="",S132,AH84) -> 0 | T84: =IF(AI84="",T132,AI84) -> 0 | U84: =IF(AJ84="",U132,AJ84) -> 0 | W84: =E84 -> R&D
B85: l | C85: l | E85: Marketing | F85: =F133 -> 0 | G85: =G133 -> 0 | H85: =H133 -> 0 | I85: =IF(X85="",I133,X85) -> 0 | J85: =IF(Y85="",J133,Y85) -> 0 | K85: =IF(Z85="",K133,Z85) -> 0 | L85: =IF(AA85="",L133,AA85) -> 0 | M85: =SUM(I85:L85) -> 0 | N85: =IF(AC85="",N133,AC85) -> 0 | O85: =IF(AD85="",O133,AD85) -> 0 | P85: =IF(AE85="",P133,AE85) -> 0 | Q85: =IF(AF85="",Q133,AF85) -> 0 | R85: =SUM(N85:Q85) -> 0 | S85: =IF(AH85="",S133,AH85) -> 0 | T85: =IF(AI85="",T133,AI85) -> 0 | U85: =IF(AJ85="",U133,AJ85) -> 0 | W85: =E85 -> Marketing
B86: l | C86: l | E86: Sales | F86: =F134 -> 0 | G86: =G134 -> 0 | H86: =H134 -> 0 | I86: =IF(X86="",I134,X86) -> 0 | J86: =IF(Y86="",J134,Y86) -> 0 | K86: =IF(Z86="",K134,Z86) -> 0 | L86: =IF(AA86="",L134,AA86) -> 0 | M86: =SUM(I86:L86) -> 0 | N86: =IF(AC86="",N134,AC86) -> 0 | O86: =IF(AD86="",O134,AD86) -> 0 | P86: =IF(AE86="",P134,AE86) -> 0 | Q86: =IF(AF86="",Q134,AF86) -> 0 | R86: =SUM(N86:Q86) -> 0 | S86: =IF(AH86="",S134,AH86) -> 0 | T86: =IF(AI86="",T134,AI86) -> 0 | U86: =IF(AJ86="",U134,AJ86) -> 0 | W86: =E86 -> Sales
B87: l | C87: l | E87: G&A | F87: =F135 -> 0 | G87: =G135 -> 0 | H87: =H135 -> 0 | I87: =IF(X87="",I135,X87) -> 0 | J87: =IF(Y87="",J135,Y87) -> 0 | K87: =IF(Z87="",K135,Z87) -> 0 | L87: =IF(AA87="",L135,AA87) -> 0 | M87: =SUM(I87:L87) -> 0 | N87: =IF(AC87="",N135,AC87) -> 0 | O87: =IF(AD87="",O135,AD87) -> 0 | P87: =IF(AE87="",P135,AE87) -> 0 | Q87: =IF(AF87="",Q135,AF87) -> 0 | R87: =SUM(N87:Q87) -> 0 | S87: =IF(AH87="",S135,AH87) -> 0 | T87: =IF(AI87="",T135,AI87) -> 0 | U87: =IF(AJ87="",U135,AJ87) -> 0 | W87: =E87 -> G&A
B88: l | C88: l | E88: Finance | F88: =F136 -> 0 | G88: =G136 -> 0 | H88: =H136 -> 0 | I88: =IF(X88="",I136,X88) -> 0 | J88: =IF(Y88="",J136,Y88) -> 0 | K88: =IF(Z88="",K136,Z88) -> 0 | L88: =IF(AA88="",L136,AA88) -> 0 | M88: =SUM(I88:L88) -> 0 | N88: =IF(AC88="",N136,AC88) -> 0 | O88: =IF(AD88="",O136,AD88) -> 0 | P88: =IF(AE88="",P136,AE88) -> 0 | Q88: =IF(AF88="",Q136,AF88) -> 0 | R88: =SUM(N88:Q88) -> 0 | S88: =IF(AH88="",S136,AH88) -> 0 | T88: =IF(AI88="",T136,AI88) -> 0 | U88: =IF(AJ88="",U136,AJ88) -> 0 | W88: =E88 -> Finance
B89: l | C89: l | E89: IT | F89: =F137 -> 0 | G89: =G137 -> 0 | H89: =H137 -> 0 | I89: =IF(X89="",I137,X89) -> 0 | J89: =IF(Y89="",J137,Y89) -> 0 | K89: =IF(Z89="",K137,Z89) -> 0 | L89: =IF(AA89="",L137,AA89) -> 0 | M89: =SUM(I89:L89) -> 0 | N89: =IF(AC89="",N137,AC89) -> 0 | O89: =IF(AD89="",O137,AD89) -> 0 | P89: =IF(AE89="",P137,AE89) -> 0 | Q89: =IF(AF89="",Q137,AF89) -> 0 | R89: =SUM(N89:Q89) -> 0 | S89: =IF(AH89="",S137,AH89) -> 0 | T89: =IF(AI89="",T137,AI89) -> 0 | U89: =IF(AJ89="",U137,AJ89) -> 0 | W89: =E89 -> IT
B90: l | C90: l | E90: HR | F90: =F138 -> 0 | G90: =G138 -> 0 | H90: =H138 -> 0 | I90: =IF(X90="",I138,X90) -> 0 | J90: =IF(Y90="",J138,Y90) -> 0 | K90: =IF(Z90="",K138,Z90) -> 0 | L90: =IF(AA90="",L138,AA90) -> 0 | M90: =SUM(I90:L90) -> 0 | N90: =IF(AC90="",N138,AC90) -> 0 | O90: =IF(AD90="",O138,AD90) -> 0 | P90: =IF(AE90="",P138,AE90) -> 0 | Q90: =IF(AF90="",Q138,AF90) -> 0 | R90: =SUM(N90:Q90) -> 0 | S90: =IF(AH90="",S138,AH90) -> 0 | T90: =IF(AI90="",T138,AI90) -> 0 | U90: =IF(AJ90="",U138,AJ90) -> 0 | W90: =E90 -> HR
B91: l | C91: l | E91: Global IT | F91: =F139 -> 0 | G91: =G139 -> 0 | H91: =H139 -> 0 | I91: =IF(X91="",I139,X91) -> 0 | J91: =IF(Y91="",J139,Y91) -> 0 | K91: =IF(Z91="",K139,Z91) -> 0 | L91: =IF(AA91="",L139,AA91) -> 0 | M91: =SUM(I91:L91) -> 0 | N91: =IF(AC91="",N139,AC91) -> 0 | O91: =IF(AD91="",O139,AD91) -> 0 | P91: =IF(AE91="",P139,AE91) -> 0 | Q91: =IF(AF91="",Q139,AF91) -> 0 | R91: =SUM(N91:Q91) -> 0 | S91: =IF(AH91="",S139,AH91) -> 0 | T91: =IF(AI91="",T139,AI91) -> 0 | U91: =IF(AJ91="",U139,AJ91) -> 0 | W91: =E91 -> Global IT
B92: l | C92: l | E92: All other Period Expenses | F92: =F140 -> 0 | G92: =G140 -> 0 | H92: =H140 -> 0 | I92: =IF(X92="",I140,X92) -> 0 | J92: =IF(Y92="",J140,Y92) -> 0 | K92: =IF(Z92="",K140,Z92) -> 0 | L92: =IF(AA92="",L140,AA92) -> 0 | M92: =SUM(I92:L92) -> 0 | N92: =IF(AC92="",N140,AC92) -> 0 | O92: =IF(AD92="",O140,AD92) -> 0 | P92: =IF(AE92="",P140,AE92) -> 0 | Q92: =IF(AF92="",Q140,AF92) -> 0 | R92: =SUM(N92:Q92) -> 0 | S92: =IF(AH92="",S140,AH92) -> 0 | T92: =IF(AI92="",T140,AI92) -> 0 | U92: =IF(AJ92="",U140,AJ92) -> 0 | W92: =E92 -> All other Period Expenses
B93: l | C93: l | E93: Blank | F93: =F141 -> 0 | G93: =G141 -> 0 | H93: =H141 -> 0 | I93: =IF(X93="",I141,X93) -> 0 | J93: =IF(Y93="",J141,Y93) -> 0 | K93: =IF(Z93="",K141,Z93) -> 0 | L93: =IF(AA93="",L141,AA93) -> 0 | M93: =SUM(I93:L93) -> 0 | N93: =IF(AC93="",N141,AC93) -> 0 | O93: =IF(AD93="",O141,AD93) -> 0 | P93: =IF(AE93="",P141,AE93) -> 0 | Q93: =IF(AF93="",Q141,AF93) -> 0 | R93: =SUM(N93:Q93) -> 0 | S93: =IF(AH93="",S141,AH93) -> 0 | T93: =IF(AI93="",T141,AI93) -> 0 | U93: =IF(AJ93="",U141,AJ93) -> 0 | W93: =E93 -> Blank
B94: l | C94: l | E94: Blank | F94: =F142 -> 0 | G94: =G142 -> 0 | H94: =H142 -> 0 | I94: =IF(X94="",I142,X94) -> 0 | J94: =IF(Y94="",J142,Y94) -> 0 | K94: =IF(Z94="",K142,Z94) -> 0 | L94: =IF(AA94="",L142,AA94) -> 0 | M94: =SUM(I94:L94) -> 0 | N94: =IF(AC94="",N142,AC94) -> 0 | O94: =IF(AD94="",O142,AD94) -> 0 | P94: =IF(AE94="",P142,AE94) -> 0 | Q94: =IF(AF94="",Q142,AF94) -> 0 | R94: =SUM(N94:Q94) -> 0 | S94: =IF(AH94="",S142,AH94) -> 0 | T94: =IF(AI94="",T142,AI94) -> 0 | U94: =IF(AJ94="",U142,AJ94) -> 0 | W94: =E94 -> Blank
E95: Total | F95: =SUM(F84:F94) -> 0 | G95: =SUM(G84:G94) -> 0 | H95: =SUM(H84:H94) -> 0 | I95: =SUM(I84:I94) -> 0 | J95: =SUM(J84:J94) -> 0 | K95: =SUM(K84:K94) -> 0 | L95: =SUM(L84:L94) -> 0 | M95: =SUM(M84:M94) -> 0 | ... U95: =SUM(U84:U94) -> 0
B99: Cash | C99: P&L | E99: ="Scenario 5: "&Inputs!B26 -> Scenario 5: Scenario 5
E100: =Inputs!C26 -> Scenario 5 Description
E103: Operating Expenses | W103: Operating Expenses
E104: Commerical assumptions 000s | W104: Commerical assumptions 000s
F106: =Inputs!$C$7 -> 2023 | G106: =Inputs!$C$8 -> 2024 | H106: =Inputs!$C$9 -> 2025 | I106: Q1 | J106: Q2 | K106: Q3 | L106: Q4 | M106: =Inputs!$C$10 -> 2026 | N106: Q1 | O106: Q2 | P106: Q3 | Q106: Q4 | R106: =Inputs!$C$11 -> 2027 | S106: =Inputs!$C$12 -> 2028 | T106: =Inputs!$C$13 -> 2029 | U106: =Inputs!$C$14 -> 2030 | X106: Q1 | Y106: Q2 | Z106: Q3 | AA106: Q4 | AB106: =Inputs!$C$10 -> 2026 | AC106: Q1 | AD106: Q2 | AE106: Q3 | AF106: Q4 | AG106: =Inputs!$C$11 -> 2027 | AH106: =Inputs!$C$12 -> 2028 | AI106: =Inputs!$C$13 -> 2029 | AJ106: =Inputs!$C$14 -> 2030
F107: (000) | G107: (000) | H107: (000) | I107: (000) | J107: (000) | K107: (000) | L107: (000) | M107: (000) | N107: (000) | O107: (000) | P107: (000) | Q107: (000) | R107: (000) | S107: (000) | T107: (000) | U107: (000) | X107: $ | Y107: $ | Z107: $ | AA107: $ | AC107: $ | AD107: $ | AE107: $ | AF107: $ | AH107: $ | AI107: $ | AJ107: $
B108: l | C108: l | E108: R&D | F108: =F132 -> 0 | G108: =G132 -> 0 | H108: =H132 -> 0 | I108: =IF(X108="",I132,X108) -> 0 | J108: =IF(Y108="",J132,Y108) -> 0 | K108: =IF(Z108="",K132,Z108) -> 0 | L108: =IF(AA108="",L132,AA108) -> 0 | M108: =SUM(I108:L108) -> 0 | N108: =IF(AC108="",N132,AC108) -> 0 | O108: =IF(AD108="",O132,AD108) -> 0 | P108: =IF(AE108="",P132,AE108) -> 0 | Q108: =IF(AF108="",Q132,AF108) -> 0 | R108: =SUM(N108:Q108) -> 0 | S108: =IF(AH108="",S132,AH108) -> 0 | T108: =IF(AI108="",T132,AI108) -> 0 | U108: =IF(AJ108="",U132,AJ108) -> 0 | W108: =E108 -> R&D
B109: l | C109: l | E109: Marketing | F109: =F133 -> 0 | G109: =G133 -> 0 | H109: =H133 -> 0 | I109: =IF(X109="",I133,X109) -> 0 | J109: =IF(Y109="",J133,Y109) -> 0 | K109: =IF(Z109="",K133,Z109) -> 0 | L109: =IF(AA109="",L133,AA109) -> 0 | M109: =SUM(I109:L109) -> 0 | N109: =IF(AC109="",N133,AC109) -> 0 | O109: =IF(AD109="",O133,AD109) -> 0 | P109: =IF(AE109="",P133,AE109) -> 0 | Q109: =IF(AF109="",Q133,AF109) -> 0 | R109: =SUM(N109:Q109) -> 0 | S109: =IF(AH109="",S133,AH109) -> 0 | T109: =IF(AI109="",T133,AI109) -> 0 | U109: =IF(AJ109="",U133,AJ109) -> 0 | W109: =E109 -> Marketing
B110: l | C110: l | E110: Sales | F110: =F134 -> 0 | G110: =G134 -> 0 | H110: =H134 -> 0 | I110: =IF(X110="",I134,X110) -> 0 | J110: =IF(Y110="",J134,Y110) -> 0 | K110: =IF(Z110="",K134,Z110) -> 0 | L110: =IF(AA110="",L134,AA110) -> 0 | M110: =SUM(I110:L110) -> 0 | N110: =IF(AC110="",N134,AC110) -> 0 | O110: =IF(AD110="",O134,AD110) -> 0 | P110: =IF(AE110="",P134,AE110) -> 0 | Q110: =IF(AF110="",Q134,AF110) -> 0 | R110: =SUM(N110:Q110) -> 0 | S110: =IF(AH110="",S134,AH110) -> 0 | T110: =IF(AI110="",T134,AI110) -> 0 | U110: =IF(AJ110="",U134,AJ110) -> 0 | W110: =E110 -> Sales
B111: l | C111: l | E111: G&A | F111: =F135 -> 0 | G111: =G135 -> 0 | H111: =H135 -> 0 | I111: =IF(X111="",I135,X111) -> 0 | J111: =IF(Y111="",J135,Y111) -> 0 | K111: =IF(Z111="",K135,Z111) -> 0 | L111: =IF(AA111="",L135,AA111) -> 0 | M111: =SUM(I111:L111) -> 0 | N111: =IF(AC111="",N135,AC111) -> 0 | O111: =IF(AD111="",O135,AD111) -> 0 | P111: =IF(AE111="",P135,AE111) -> 0 | Q111: =IF(AF111="",Q135,AF111) -> 0 | R111: =SUM(N111:Q111) -> 0 | S111: =IF(AH111="",S135,AH111) -> 0 | T111: =IF(AI111="",T135,AI111) -> 0 | U111: =IF(AJ111="",U135,AJ111) -> 0 | W111: =E111 -> G&A
B112: l | C112: l | E112: Finance | F112: =F136 -> 0 | G112: =G136 -> 0 | H112: =H136 -> 0 | I112: =IF(X112="",I136,X112) -> 0 | J112: =IF(Y112="",J136,Y112) -> 0 | K112: =IF(Z112="",K136,Z112) -> 0 | L112: =IF(AA112="",L136,AA112) -> 0 | M112: =SUM(I112:L112) -> 0 | N112: =IF(AC112="",N136,AC112) -> 0 | O112: =IF(AD112="",O136,AD112) -> 0 | P112: =IF(AE112="",P136,AE112) -> 0 | Q112: =IF(AF112="",Q136,AF112) -> 0 | R112: =SUM(N112:Q112) -> 0 | S112: =IF(AH112="",S136,AH112) -> 0 | T112: =IF(AI112="",T136,AI112) -> 0 | U112: =IF(AJ112="",U136,AJ112) -> 0 | W112: =E112 -> Finance
B113: l | C113: l | E113: IT | F113: =F137 -> 0 | G113: =G137 -> 0 | H113: =H137 -> 0 | I113: =IF(X113="",I137,X113) -> 0 | J113: =IF(Y113="",J137,Y113) -> 0 | K113: =IF(Z113="",K137,Z113) -> 0 | L113: =IF(AA113="",L137,AA113) -> 0 | M113: =SUM(I113:L113) -> 0 | N113: =IF(AC113="",N137,AC113) -> 0 | O113: =IF(AD113="",O137,AD113) -> 0 | P113: =IF(AE113="",P137,AE113) -> 0 | Q113: =IF(AF113="",Q137,AF113) -> 0 | R113: =SUM(N113:Q113) -> 0 | S113: =IF(AH113="",S137,AH113) -> 0 | T113: =IF(AI113="",T137,AI113) -> 0 | U113: =IF(AJ113="",U137,AJ113) -> 0 | W113: =E113 -> IT
B114: l | C114: l | E114: HR | F114: =F138 -> 0 | G114: =G138 -> 0 | H114: =H138 -> 0 | I114: =IF(X114="",I138,X114) -> 0 | J114: =IF(Y114="",J138,Y114) -> 0 | K114: =IF(Z114="",K138,Z114) -> 0 | L114: =IF(AA114="",L138,AA114) -> 0 | M114: =SUM(I114:L114) -> 0 | N114: =IF(AC114="",N138,AC114) -> 0 | O114: =IF(AD114="",O138,AD114) -> 0 | P114: =IF(AE114="",P138,AE114) -> 0 | Q114: =IF(AF114="",Q138,AF114) -> 0 | R114: =SUM(N114:Q114) -> 0 | S114: =IF(AH114="",S138,AH114) -> 0 | T114: =IF(AI114="",T138,AI114) -> 0 | U114: =IF(AJ114="",U138,AJ114) -> 0 | W114: =E114 -> HR
B115: l | C115: l | E115: Global IT | F115: =F139 -> 0 | G115: =G139 -> 0 | H115: =H139 -> 0 | I115: =IF(X115="",I139,X115) -> 0 | J115: =IF(Y115="",J139,Y115) -> 0 | K115: =IF(Z115="",K139,Z115) -> 0 | L115: =IF(AA115="",L139,AA115) -> 0 | M115: =SUM(I115:L115) -> 0 | N115: =IF(AC115="",N139,AC115) -> 0 | O115: =IF(AD115="",O139,AD115) -> 0 | P115: =IF(AE115="",P139,AE115) -> 0 | Q115: =IF(AF115="",Q139,AF115) -> 0 | R115: =SUM(N115:Q115) -> 0 | S115: =IF(AH115="",S139,AH115) -> 0 | T115: =IF(AI115="",T139,AI115) -> 0 | U115: =IF(AJ115="",U139,AJ115) -> 0 | W115: =E115 -> Global IT
B116: l | C116: l | E116: All other Period Expenses | F116: =F140 -> 0 | G116: =G140 -> 0 | H116: =H140 -> 0 | I116: =IF(X116="",I140,X116) -> 0 | J116: =IF(Y116="",J140,Y116) -> 0 | K116: =IF(Z116="",K140,Z116) -> 0 | L116: =IF(AA116="",L140,AA116) -> 0 | M116: =SUM(I116:L116) -> 0 | N116: =IF(AC116="",N140,AC116) -> 0 | O116: =IF(AD116="",O140,AD116) -> 0 | P116: =IF(AE116="",P140,AE116) -> 0 | Q116: =IF(AF116="",Q140,AF116) -> 0 | R116: =SUM(N116:Q116) -> 0 | S116: =IF(AH116="",S140,AH116) -> 0 | T116: =IF(AI116="",T140,AI116) -> 0 | U116: =IF(AJ116="",U140,AJ116) -> 0 | W116: =E116 -> All other Period Expenses
B117: l | C117: l | E117: Blank | F117: =F141 -> 0 | G117: =G141 -> 0 | H117: =H141 -> 0 | I117: =IF(X117="",I141,X117) -> 0 | J117: =IF(Y117="",J141,Y117) -> 0 | K117: =IF(Z117="",K141,Z117) -> 0 | L117: =IF(AA117="",L141,AA117) -> 0 | M117: =SUM(I117:L117) -> 0 | N117: =IF(AC117="",N141,AC117) -> 0 | O117: =IF(AD117="",O141,AD117) -> 0 | P117: =IF(AE117="",P141,AE117) -> 0 | Q117: =IF(AF117="",Q141,AF117) -> 0 | R117: =SUM(N117:Q117) -> 0 | S117: =IF(AH117="",S141,AH117) -> 0 | T117: =IF(AI117="",T141,AI117) -> 0 | U117: =IF(AJ117="",U141,AJ117) -> 0 | W117: =E117 -> Blank
B118: l | C118: l | E118: Blank | F118: =F142 -> 0 | G118: =G142 -> 0 | H118: =H142 -> 0 | I118: =IF(X118="",I142,X118) -> 0 | J118: =IF(Y118="",J142,Y118) -> 0 | K118: =IF(Z118="",K142,Z118) -> 0 | L118: =IF(AA118="",L142,AA118) -> 0 | M118: =SUM(I118:L118) -> 0 | N118: =IF(AC118="",N142,AC118) -> 0 | O118: =IF(AD118="",O142,AD118) -> 0 | P118: =IF(AE118="",P142,AE118) -> 0 | Q118: =IF(AF118="",Q142,AF118) -> 0 | R118: =SUM(N118:Q118) -> 0 | S118: =IF(AH118="",S142,AH118) -> 0 | T118: =IF(AI118="",T142,AI118) -> 0 | U118: =IF(AJ118="",U142,AJ118) -> 0 | W118: =E118 -> Blank
E119: Total | F119: =SUM(F108:F118) -> 0 | G119: =SUM(G108:G118) -> 0 | H119: =SUM(H108:H118) -> 0 | I119: =SUM(I108:I118) -> 0 | J119: =SUM(J108:J118) -> 0 | K119: =SUM(K108:K118) -> 0 | L119: =SUM(L108:L118) -> 0 | M119: =SUM(M108:M118) -> 0 | ... U119: =SUM(U108:U118) -> 0
E123: Actuals
E124: Key in actuals for prior years and uploaded forecast for outer years - Pull from Internal System
E127: Operating Expenses
E128: Commerical assumptions 000s
F130: =Inputs!$C$7 -> 2023 | G130: =Inputs!$C$8 -> 2024 | H130: =Inputs!$C$9 -> 2025 | I130: Q1 | J130: Q2 | K130: Q3 | L130: Q4 | M130: =Inputs!$C$10 -> 2026 | N130: Q1 | O130: Q2 | P130: Q3 | Q130: Q4 | R130: =Inputs!$C$11 -> 2027 | S130: =Inputs!$C$12 -> 2028 | T130: =Inputs!$C$13 -> 2029 | U130: =Inputs!$C$14 -> 2030
F131: (000) | G131: (000) | H131: (000) | I131: (000) | J131: (000) | K131: (000) | L131: (000) | M131: (000) | N131: (000) | O131: (000) | P131: (000) | Q131: (000) | R131: (000) | S131: (000) | T131: (000) | U131: (000)
E132: R&D | M132: =SUM(I132:L132) -> 0 | R132: =SUM(N132:Q132) -> 0
E133: Marketing | M133: =SUM(I133:L133) -> 0 | R133: =SUM(N133:Q133) -> 0
E134: Sales | M134: =SUM(I134:L134) -> 0 | R134: =SUM(N134:Q134) -> 0
E135: G&A | M135: =SUM(I135:L135) -> 0 | R135: =SUM(N135:Q135) -> 0
...

Sheet 4. Investments
B3: Cash | C3: P&L | E3: ="Scenario 1: "&Inputs!B22 -> Scenario 1: Scenario 1
E4: =Inputs!C22 -> Scenario 1 Description
E7: Investments Required | W7: Investments Required
E8: Commerical assumptions 000s | W8: Key In expected Dollar amounts in 000s
F10: =Inputs!$C$7 -> 2023 | G10: =Inputs!$C$8 -> 2024 | H10: =Inputs!$C$9 -> 2025 | I10: Q1 | J10: Q2 | K10: Q3 | L10: Q4 | M10: =Inputs!$C$10 -> 2026 | N10: Q1 | O10: Q2 | P10: Q3 | Q10: Q4 | R10: =Inputs!$C$11 -> 2027 | S10: =Inputs!$C$12 -> 2028 | T10: =Inputs!$C$13 -> 2029 | U10: =Inputs!$C$14 -> 2030 | X10: Q1 | Y10: Q2 | Z10: Q3 | AA10: Q4 | AB10: =Inputs!$C$10 -> 2026 | AC10: Q1 | AD10: Q2 | AE10: Q3 | AF10: Q4 | AG10: =Inputs!$C$11 -> 2027 | AH10: =Inputs!$C$12 -> 2028 | AI10: =Inputs!$C$13 -> 2029 | AJ10: =Inputs!$C$14 -> 2030
F11: (000) | G11: (000) | H11: (000) | I11: (000) | J11: (000) | K11: (000) | L11: (000) | M11: (000) | N11: (000) | O11: (000) | P11: (000) | Q11: (000) | R11: (000) | S11: (000) | T11: (000) | U11: (000) | X11: $ | Y11: $ | Z11: $ | AA11: $ | AC11: $ | AD11: $ | AE11: $ | AF11: $ | AH11: $ | AI11: $ | AJ11: $
B12: l | C12: l | E12: 3rd Party Expenses 1 | F12: =F397 -> 0 | G12: =G397 -> 0 | H12: =H397 -> 0 | I12: =IF(X12="",I397,X12) -> 0 | J12: =IF(Y12="",J397,Y12) -> 0 | K12: =IF(Z12="",K397,Z12) -> 0 | L12: =IF(AA12="",L397,AA12) -> 0 | M12: =SUM(I12:L12) -> 0 | N12: =IF(AC12="",N397,AC12) -> 0 | O12: =IF(AD12="",O397,AD12) -> 0 | P12: =IF(AE12="",P397,AE12) -> 0 | Q12: =IF(AF12="",Q397,AF12) -> 0 | R12: =SUM(N12:Q12) -> 0 | S12: =IF(AH12="",S397,AH12) -> 0 | T12: =IF(AI12="",T397,AI12) -> 0 | U12: =IF(AJ12="",U397,AJ12) -> 0 | W12: =E12 -> 3rd Party Expenses 1
B13: l | C13: l | E13: 3rd Party Expenses 2 | F13: =F398 -> 0 | G13: =G398 -> 0 | H13: =H398 -> 0 | I13: =IF(X13="",I398,X13) -> 0 | J13: =IF(Y13="",J398,Y13) -> 0 | K13: =IF(Z13="",K398,Z13) -> 0 | L13: =IF(AA13="",L398,AA13) -> 0 | M13: =SUM(I13:L13) -> 0 | N13: =IF(AC13="",N398,AC13) -> 0 | O13: =IF(AD13="",O398,AD13) -> 0 | P13: =IF(AE13="",P398,AE13) -> 0 | Q13: =IF(AF13="",Q398,AF13) -> 0 | R13: =SUM(N13:Q13) -> 0 | S13: =IF(AH13="",S398,AH13) -> 0 | T13: =IF(AI13="",T398,AI13) -> 0 | U13: =IF(AJ13="",U398,AJ13) -> 0 | W13: =E13 -> 3rd Party Expenses 2
B14: l | C14: l | E14: 3rd Party Expenses 3 | F14: =F399 -> 0 | G14: =G399 -> 0 | H14: =H399 -> 0 | I14: =IF(X14="",I399,X14) -> 0 | J14: =IF(Y14="",J399,Y14) -> 0 | K14: =IF(Z14="",K399,Z14) -> 0 | L14: =IF(AA14="",L399,AA14) -> 0 | M14: =SUM(I14:L14) -> 0 | N14: =IF(AC14="",N399,AC14) -> 0 | O14: =IF(AD14="",O399,AD14) -> 0 | P14: =IF(AE14="",P399,AE14) -> 0 | Q14: =IF(AF14="",Q399,AF14) -> 0 | R14: =SUM(N14:Q14) -> 0 | S14: =IF(AH14="",S399,AH14) -> 0 | T14: =IF(AI14="",T399,AI14) -> 0 | U14: =IF(AJ14="",U399,AJ14) -> 0 | W14: =E14 -> 3rd Party Expenses 3
B15: l | C15: l | E15: 3rd Party Expenses 4 | F15: =F400 -> 0 | G15: =G400 -> 0 | H15: =H400 -> 0 | I15: =IF(X15="",I400,X15) -> 0 | J15: =IF(Y15="",J400,Y15) -> 0 | K15: =IF(Z15="",K400,Z15) -> 0 | L15: =IF(AA15="",L400,AA15) -> 0 | M15: =SUM(I15:L15) -> 0 | N15: =IF(AC15="",N400,AC15) -> 0 | O15: =IF(AD15="",O400,AD15) -> 0 | P15: =IF(AE15="",P400,AE15) -> 0 | Q15: =IF(AF15="",Q400,AF15) -> 0 | R15: =SUM(N15:Q15) -> 0 | S15: =IF(AH15="",S400,AH15) -> 0 | T15: =IF(AI15="",T400,AI15) -> 0 | U15: =IF(AJ15="",U400,AJ15) -> 0 | W15: =E15 -> 3rd Party Expenses 4
B16: l | C16: l | E16: All Other | F16: =F401 -> 0 | G16: =G401 -> 0 | H16: =H401 -> 0 | I16: =IF(X16="",I401,X16) -> 0 | J16: =IF(Y16="",J401,Y16) -> 0 | K16: =IF(Z16="",K401,Z16) -> 0 | L16: =IF(AA16="",L401,AA16) -> 0 | M16: =SUM(I16:L16) -> 0 | N16: =IF(AC16="",N401,AC16) -> 0 | O16: =IF(AD16="",O401,AD16) -> 0 | P16: =IF(AE16="",P401,AE16) -> 0 | Q16: =IF(AF16="",Q401,AF16) -> 0 | R16: =SUM(N16:Q16) -> 0 | S16: =IF(AH16="",S401,AH16) -> 0 | T16: =IF(AI16="",T401,AI16) -> 0 | U16: =IF(AJ16="",U401,AJ16) -> 0 | W16: =E16 -> All Other
